Verilog_file/BRAM_Model.v
module bram(
    input  wire            clka,
    input  wire            ena,
    input  wire            wea,
    input  wire  [31:0]    addra,
    input  wire  [31:0]    dina,
    output reg   [31:0]    douta
);

    reg [31:0] mem [0:7999];
    reg [31:0] mem1;
    reg [31:0] mem2;
    reg [31:0] mem3;
    reg [31:0] mem4;
    reg [31:0] mem5;
    reg [31:0] mem6;
    reg [31:0] mem7;
    reg [31:0] mem8;
    reg [31:0] mem9;
    reg [31:0] mem10;
    reg [31:0] mem11;

    // 13비트 주소 인덱스 (0~8191까지 가능, 실제는 0~7999만 사용)
    wire [12:0] addr_index = addra[12:0];

    integer i;

    // 초기화 블록 (시뮬레이션용)
    initial begin
        for (i = 0; i <= 7999; i = i + 1) begin
            mem[i] = 32'd0;
        end
    end

    // 동기식 동작 (읽기/쓰기)
    always @(posedge clka) begin
        if (ena) begin
            if (wea != 1'b0) begin
                mem[addr_index] = dina;
            end
            douta <= mem[addr_index];

            // 디버깅용 특정 위치 레지스터 저장
            mem1 <= mem[0];
            mem2 <= mem[4];
            mem3 <= mem[8];
            mem4 <= mem[12];
            mem5 <= mem[16];
            mem6 <= mem[20];
            mem7 <= mem[24];
            mem8 <= mem[28];
            mem9 <= mem[32];
            mem10 <= mem[36];
            mem11 <= mem[40];

            // 디버깅 출력
            // $display("[READ ] MEM[%0d] [0x%08X] => 0x%08X", addr_index, dina, mem[addr_index]);
        end
    end

endmodule

Verilog_file/PulseGenFin/fp32_adder.v
module fp32_adder (
    input  [31:0] a,
    input  [31:0] b,
    output [31:0] result
);
    wire sign_a = a[31];
    wire sign_b = b[31];
    wire [7:0] exp_a = a[30:23];
    wire [7:0] exp_b = b[30:23];
    wire [23:0] mant_a = (exp_a == 0) ? {1'b0, a[22:0]} : {1'b1, a[22:0]};
    wire [23:0] mant_b = (exp_b == 0) ? {1'b0, b[22:0]} : {1'b1, b[22:0]};

    reg [7:0] exp_diff;
    reg [23:0] aligned_a, aligned_b;
    reg [7:0] exp_res;
    reg [24:0] mant_sum;
    reg sign_res;
    reg [22:0] frac_res;

    always @(*) begin
        // 지수 맞춤
        if (exp_a > exp_b) begin
            exp_diff = exp_a - exp_b;
            aligned_a = mant_a;
            aligned_b = mant_b >> exp_diff;
            exp_res = exp_a;
            sign_res = sign_a;
        end else begin
            exp_diff = exp_b - exp_a;
            aligned_a = mant_a >> exp_diff;
            aligned_b = mant_b;
            exp_res = exp_b;
            sign_res = sign_b;
        end

        // 같은 부호만 지원 (간단 버전)
        if (sign_a == sign_b) begin
            mant_sum = aligned_a + aligned_b;
            if (mant_sum[24]) begin
                mant_sum = mant_sum >> 1;
                exp_res = exp_res + 1;
            end
        end else begin
            // 부호 다르면 뺄셈인데, 여기선 간단히 무시
            mant_sum = 0;
        end

        frac_res = mant_sum[22:0];
    end

    assign result = {sign_res, exp_res, frac_res};
endmodule

Verilog_file/PulseGenFin/PulseGenGam.v
`timescale 1ns / 1ps
`include "./Verilog_file/BRAM_Model.v"
`include "./Verilog_file/fp32_adder.v"

module PulseGenGam(
    input wire clk,
    input wire [31:0] cps,
    output reg [31:0] bram_addr,
    output reg [31:0] bram_data_in,
    output reg ena,
    output reg bram_we,
    input wire [31:0] bram_data_out
);
    // reg [9:0] lfsr = 10'b1010101010;  // 10비트 초기값
    reg [10:0] lfsr = 11'b10101010101;  // 11비트 초기값

    reg [31:0] count = 0;
    reg [31:0] prev_cps = 0;

    reg [31:0] mem_count = 0;
    reg [31:0] count_gam = 0;

    reg [3:0] mem_control_state = 0;

    // Gamma Pulse Data Table
    reg [31:0] float_data [0:12];

    initial begin
        float_data[0] = 32'h3D7C5048; // 0.0616
        float_data[1] = 32'h3E99652C; // 0.2996
        float_data[2] = 32'h3E0E3BCD; // 0.1389
        float_data[3] = 32'h3D83126F; // 0.0640
        float_data[4] = 32'h3CF1A9FC; // 0.0295
        float_data[5] = 32'h3C5ED289; // 0.0136
        float_data[6] = 32'h3BCE703B; // 0.0063
        float_data[7] = 32'h3B3E0DED; // 0.0029
        float_data[8] = 32'h3AAA64C3; // 0.0013
        float_data[9] = 32'h3A1D4952; // 0.0006
        float_data[10] = 32'h399D4952; // 0.0003
        float_data[11] = 32'h38D1B717; // 0.0001
        float_data[12] = 32'h38D1B717; // 0.0001
    end

    wire [31:0] fp_add_result;
    reg [31:0] fp_table_input;

    fp32_adder adder_inst (
        .a(bram_data_out),
        .b(fp_table_input),         // IEEE 754
        .result(fp_add_result)
    );

    always @(posedge clk) begin
        if (cps == 0) begin
            // Input/Output Parameter --
            bram_addr <= 0;
            ena <= 0;
            bram_we <= 0;

            // Local Parameter --
            // lfsr <= 10'b1010101010;
            // lfsr <= 11'b10101010101; // 11비트 초기값
            lfsr <= {lfsr[9:0], lfsr[10] ^ lfsr[7]}; // 11비트 LFSR로 변경 (이전 변경 값을 가져다 씀)
            
            count <= 0;
            prev_cps <= 0;

            mem_count <= 0;
            count_gam <= 0;

            mem_control_state <= 0;
        end else begin
            // cps가 변경되었을 경우 재시작
            if (cps != prev_cps) begin
                // Input/Output Parameter --
                bram_addr <= 0;
                ena <= 0;
                bram_we <= 0;

                // Local Parameter --
                // lfsr <= 10'b1010101010;
                // lfsr <= 11'b10101010101; // 11비트 초기값
                lfsr <= {lfsr[9:0], lfsr[10] ^ lfsr[7]}; // 11비트 LFSR로 변경 (이전 변경 값을 가져다 씀)

                count <= 0;
                prev_cps <= cps;

                mem_count <= 0;
                count_gam <= 0;

                mem_control_state <= 0;
            end else if (count < cps) begin
                if (mem_count == 0) begin
                    // Input/Output Parameter --
                    // bram_addr <= 32'b100; // lfsr * 4;                // 0 ~ 1023 개 가능
                    bram_addr <= lfsr * 4;                // 11비트 0 ~ 2047 개 가능
                    bram_data_in <= 0;                    // Pulse Initialization
                    ena <= 1;                             // 활성화         
                    bram_we <= 0;                         // 펄스 읽기

                    // Local Parameter --
                    // 10비트 LFSR: x^10 + x^7 + 1
                    // lfsr <= {lfsr[8:0], lfsr[9] ^ lfsr[6]};
                    lfsr <= {lfsr[9:0], lfsr[10] ^ lfsr[7]}; // 11비트 LFSR로 변경
                    
                    // Pulse 메모리에 1 부터 증가하는 값 쓰기
                    mem_count <= 1;                 // 메모리 카운트 증가

                    mem_control_state <= 1;
                end else begin
                    if (mem_count > 13) begin
                        // 메모리 카운트가 13 이상이면 펄스 종료
                        // Input/Output Parameter --
                        ena <= 0;                             // 비횔성화      
                        bram_we <= 0;                         // 펄스 읽기
                        // Local Parameter --
                        mem_count <= 0;                 // 메모리 카운트 초기화

                        mem_control_state <= 0;         // BRAM 제어 상태 초기화
                        // Gamma Pulse 카운트 증가 (1 cps = 2 pulse)
                        if (count_gam == 1) begin
                            count <= count + 1;
                            count_gam <= 0;
                        end else begin
                            count_gam <= count_gam + 1;
                        end

                    end else begin
                        case (mem_control_state)
                            0: begin
                                bram_addr <= bram_addr + 4;
                                bram_we <= 0;                   // 펄스 읽기
                                ena <= 1;                       // 활성화
                                // 주소 유지
                                mem_control_state <= 1;
                            end
                            1: begin
                                // 대기 
                                bram_we <= 0;                   // 펄스 읽기
                                ena <= 0;                       // 비활성화
                                //
                                fp_table_input <= float_data[mem_count - 1]; // 0.1 ~ 0.6
                                mem_control_state <= 2;
                            end
                            2: begin
                                // write 완료, 다음 주소로 이동
                                bram_addr <= bram_addr;
                                bram_data_in <= fp_add_result;

                                bram_we <= 1;                   // 펄스 쓰기
                                ena <= 1;                       // 활성화
                                //
                                mem_count <= mem_count + 1;
                                mem_control_state <= 0; // 다음 루프
                            end
                        endcase
                    end
                end

            end else begin
                bram_we <= 0;                   
                ena <= 0;

                mem_count <= 0;
            end 
        end
    end
endmodule


module tb_PulseGenGam();

    // Inputs
    reg clk;
    reg [31:0] cps;

    // Outputs
    wire [31:0] bram_addr;
    wire [31:0] bram_data_in;
    wire ena;
    wire bram_we;
    wire [31:0] bram_data_out;

    // Instantiate the Unit Under Test (UUT)
    PulseGenGam uut (
        .clk(clk),
        .cps(cps),
        .bram_addr(bram_addr),
        .bram_data_in(bram_data_in),
        .ena(ena),
        .bram_we(bram_we),
        .bram_data_out(bram_data_out)
    );

    bram pulse_bram_inst (
        .clka(clk),
        .ena(ena),
        .wea(bram_we),
        .addra(bram_addr),
        .dina(bram_data_in),
        .douta(bram_data_out)  // Read output not used in this test
    );

    // Clock generation: 10ns period
    always #5 clk = ~clk;

    initial begin
        $dumpfile("Verilog_file/PulseGenFin/PulseGenGam.vcd");
        $dumpvars(0, tb_PulseGenGam);
        // Initialize inputs
        clk = 0;
        cps = 0;

        // Wait for global reset
        #20;

        // Test 1: cps = 0 → 모듈 초기화 상태 유지
        cps = 0;
        #50;

        // Test 2: cps = 10 → 10개의 pulse 발생
        cps = 1;
        #2000;

        cps = 0;
        #50

        // Test 2: cps = 10 → 10개의 pulse 발생
        cps = 1;
        #500;

        // // Test 3: cps = 5 → 다시 시작됨 (변경된 cps 값)
        // cps = 5;
        // #500;

        // // Test 4: cps = 0 → 종료
        // cps = 0;
        // #100;

        $finish;
    end

endmodule

Verilog_file/PulseGenFin/PulseGenGam.vcd
$date
	Mon Aug 04 23:47:08 2025
$end
$version
	Icarus Verilog
$end
$timescale
	1ps
$end
$scope module tb_PulseGenGam $end
$var wire 1 ! ena $end
$var wire 1 " bram_we $end
$var wire 32 # bram_data_out [31:0] $end
$var wire 32 $ bram_data_in [31:0] $end
$var wire 32 % bram_addr [31:0] $end
$var reg 1 & clk $end
$var reg 32 ' cps [31:0] $end
$scope module pulse_bram_inst $end
$var wire 1 & clka $end
$var wire 1 " wea $end
$var wire 1 ! ena $end
$var wire 32 ( dina [31:0] $end
$var wire 32 ) addra [31:0] $end
$var wire 13 * addr_index [12:0] $end
$var reg 32 + douta [31:0] $end
$var reg 32 , mem1 [31:0] $end
$var reg 32 - mem10 [31:0] $end
$var reg 32 . mem11 [31:0] $end
$var reg 32 / mem2 [31:0] $end
$var reg 32 0 mem3 [31:0] $end
$var reg 32 1 mem4 [31:0] $end
$var reg 32 2 mem5 [31:0] $end
$var reg 32 3 mem6 [31:0] $end
$var reg 32 4 mem7 [31:0] $end
$var reg 32 5 mem8 [31:0] $end
$var reg 32 6 mem9 [31:0] $end
$var integer 32 7 i [31:0] $end
$upscope $end
$scope module uut $end
$var wire 32 8 bram_data_out [31:0] $end
$var wire 1 & clk $end
$var wire 32 9 cps [31:0] $end
$var wire 32 : fp_add_result [31:0] $end
$var reg 32 ; bram_addr [31:0] $end
$var reg 32 < bram_data_in [31:0] $end
$var reg 1 " bram_we $end
$var reg 32 = count [31:0] $end
$var reg 32 > count_gam [31:0] $end
$var reg 1 ! ena $end
$var reg 32 ? fp_table_input [31:0] $end
$var reg 11 @ lfsr [10:0] $end
$var reg 4 A mem_control_state [3:0] $end
$var reg 32 B mem_count [31:0] $end
$var reg 32 C prev_cps [31:0] $end
$scope module adder_inst $end
$var wire 32 D a [31:0] $end
$var wire 32 E b [31:0] $end
$var wire 1 F sign_b $end
$var wire 1 G sign_a $end
$var wire 32 H result [31:0] $end
$var wire 24 I mant_b [23:0] $end
$var wire 24 J mant_a [23:0] $end
$var wire 8 K exp_b [7:0] $end
$var wire 8 L exp_a [7:0] $end
$var reg 24 M aligned_a [23:0] $end
$var reg 24 N aligned_b [23:0] $end
$var reg 8 O exp_diff [7:0] $end
$var reg 8 P exp_res [7:0] $end
$var reg 23 Q frac_res [22:0] $end
$var reg 25 R mant_sum [24:0] $end
$var reg 1 S sign_res $end
$upscope $end
$upscope $end
$upscope $end
$enddefinitions $end
$comment Show the parameter values. $end
$dumpall
$end
#0
$dumpvars
xS
b0 R
b0 Q
bx P
bx O
bx N
bx M
bx L
bx K
bx J
bx I
bx00000000000000000000000 H
xG
xF
bx E
bx D
b0 C
b0 B
b0 A
b10101010101 @
bx ?
b0 >
b0 =
bx <
bx ;
bx00000000000000000000000 :
b0 9
bx 8
b1111101000000 7
bx 6
bx 5
bx 4
bx 3
bx 2
bx 1
bx 0
bx /
bx .
bx -
bx ,
bx +
bx *
bx )
bx (
b0 '
0&
bx %
bx $
bx #
x"
x!
$end
#5000
b0 *
b1010101011 @
0"
0!
b0 %
b0 )
b0 ;
1&
#10000
0&
#15000
b10101010111 @
1&
#20000
0&
#25000
b1010101111 @
1&
#30000
0&
#35000
b10101011111 @
1&
#40000
0&
#45000
b1010111111 @
1&
#50000
0&
#55000
b10101111111 @
1&
#60000
0&
#65000
b1011111111 @
1&
#70000
0&
b1 '
b1 9
#75000
b1 C
b10111111111 @
1&
#80000
0&
#85000
b1011111111100 *
b1 A
b1 B
b1111111110 @
1!
b0 $
b0 (
b0 <
b1011111111100 %
b1011111111100 )
b1011111111100 ;
1&
#90000
0&
#95000
b0 J
b11111000101000001001000 Q
b111111000101000001001000 R
0S
b111101011111000101000001001000 :
b111101011111000101000001001000 H
b1111010 P
b111111000101000001001000 N
b0 M
b1111010 O
b111111000101000001001000 I
0G
b0 L
0F
b1111010 K
b0 .
b0 -
b0 6
b0 5
b0 4
b0 3
b0 2
b0 1
b0 0
b0 /
b0 ,
b0 #
b0 +
b0 8
b0 D
b10 A
b111101011111000101000001001000 ?
b111101011111000101000001001000 E
0!
1&
#100000
0&
#105000
b0 A
b10 B
1!
1"
b111101011111000101000001001000 $
b111101011111000101000001001000 (
b111101011111000101000001001000 <
1&
#110000
0&
#115000
b111101111111000101000001001000 :
b111101111111000101000001001000 H
b1111011 P
b111111000101000001001000 R
b111111000101000001001000 M
b0 O
b111111000101000001001000 J
b1111010 L
b1100000000000 *
b111101011111000101000001001000 #
b111101011111000101000001001000 +
b111101011111000101000001001000 8
b111101011111000101000001001000 D
b1 A
0"
b1100000000000 %
b1100000000000 )
b1100000000000 ;
1&
#120000
0&
#125000
b110010110010100101100 Q
b100110010110010100101100 R
b100110010110010100101100 N
b100110010110010100101100 I
b111110100110010110010100101100 :
b111110100110010110010100101100 H
b1111101 P
b0 M
b1111101 O
b0 J
b1111101 K
b0 L
b10 A
b111110100110010110010100101100 ?
b111110100110010110010100101100 E
0!
b0 #
b0 +
b0 8
b0 D
1&
#130000
0&
#135000
b0 A
b11 B
1!
1"
b111110100110010110010100101100 $
b111110100110010110010100101100 (
b111110100110010110010100101100 <
1&
#140000
0&
#145000
b111111000110010110010100101100 :
b111111000110010110010100101100 H
b1111110 P
b100110010110010100101100 R
b100110010110010100101100 M
b0 O
b100110010110010100101100 J
b1100000000100 *
b1111101 L
b1 A
0"
b1100000000100 %
b1100000000100 )
b1100000000100 ;
b111110100110010110010100101100 #
b111110100110010110010100101100 +
b111110100110010110010100101100 8
b111110100110010110010100101100 D
1&
#150000
0&
#155000
b0 J
b11100011101111001101 Q
b100011100011101111001101 R
b111110000011100011101111001101 :
b111110000011100011101111001101 H
b1111100 P
b100011100011101111001101 N
b0 M
b1111100 O
b100011100011101111001101 I
b0 L
b1111100 K
b0 #
b0 +
b0 8
b0 D
b10 A
b111110000011100011101111001101 ?
b111110000011100011101111001101 E
0!
1&
#160000
0&
#165000
b0 A
b100 B
1!
1"
b111110000011100011101111001101 $
b111110000011100011101111001101 (
b111110000011100011101111001101 <
1&
#170000
0&
#175000
b111110100011100011101111001101 :
b111110100011100011101111001101 H
b1111101 P
b100011100011101111001101 R
b100011100011101111001101 M
b0 O
b100011100011101111001101 J
b1111100 L
b1100000001000 *
b111110000011100011101111001101 #
b111110000011100011101111001101 +
b111110000011100011101111001101 8
b111110000011100011101111001101 D
b1 A
0"
b1100000001000 %
b1100000001000 )
b1100000001000 ;
1&
#180000
0&
#185000
b110001001001101111 Q
b100000110001001001101111 R
b100000110001001001101111 N
b100000110001001001101111 I
b111101100000110001001001101111 :
b111101100000110001001001101111 H
b1111011 P
b0 M
b1111011 O
b0 J
b1111011 K
b0 L
b10 A
b111101100000110001001001101111 ?
b111101100000110001001001101111 E
0!
b0 #
b0 +
b0 8
b0 D
1&
#190000
0&
#195000
b0 A
b101 B
1!
1"
b111101100000110001001001101111 $
b111101100000110001001001101111 (
b111101100000110001001001101111 <
1&
#200000
0&
#205000
b111110000000110001001001101111 :
b111110000000110001001001101111 H
b1111100 P
b100000110001001001101111 R
b100000110001001001101111 M
b0 O
b100000110001001001101111 J
b1100000001100 *
b1111011 L
b1 A
0"
b1100000001100 %
b1100000001100 )
b1100000001100 ;
b111101100000110001001001101111 #
b111101100000110001001001101111 +
b111101100000110001001001101111 8
b111101100000110001001001101111 D
1&
#210000
0&
#215000
b0 J
b11100011010100111111100 Q
b111100011010100111111100 R
b111100111100011010100111111100 :
b111100111100011010100111111100 H
b1111001 P
b111100011010100111111100 N
b0 M
b1111001 O
b111100011010100111111100 I
b0 L
b1111001 K
b0 #
b0 +
b0 8
b0 D
b10 A
b111100111100011010100111111100 ?
b111100111100011010100111111100 E
0!
1&
#220000
0&
#225000
b0 A
b110 B
1!
1"
b111100111100011010100111111100 $
b111100111100011010100111111100 (
b111100111100011010100111111100 <
1&
#230000
0&
#235000
b111101011100011010100111111100 :
b111101011100011010100111111100 H
b1111010 P
b111100011010100111111100 R
b111100011010100111111100 M
b0 O
b111100011010100111111100 J
b1111001 L
b1100000010000 *
b111100111100011010100111111100 #
b111100111100011010100111111100 +
b111100111100011010100111111100 8
b111100111100011010100111111100 D
b1 A
0"
b1100000010000 %
b1100000010000 )
b1100000010000 ;
1&
#240000
0&
#245000
b10111101101001010001001 Q
b110111101101001010001001 R
b110111101101001010001001 N
b110111101101001010001001 I
b111100010111101101001010001001 :
b111100010111101101001010001001 H
b1111000 P
b0 M
b1111000 O
b0 J
b1111000 K
b0 L
b10 A
b111100010111101101001010001001 ?
b111100010111101101001010001001 E
0!
b0 #
b0 +
b0 8
b0 D
1&
#250000
0&
#255000
b0 A
b111 B
1!
1"
b111100010111101101001010001001 $
b111100010111101101001010001001 (
b111100010111101101001010001001 <
1&
#260000
0&
#265000
b111100110111101101001010001001 :
b111100110111101101001010001001 H
b1111001 P
b110111101101001010001001 R
b110111101101001010001001 M
b0 O
b110111101101001010001001 J
b1100000010100 *
b1111000 L
b1 A
0"
b1100000010100 %
b1100000010100 )
b1100000010100 ;
b111100010111101101001010001001 #
b111100010111101101001010001001 +
b111100010111101101001010001001 8
b111100010111101101001010001001 D
1&
#270000
0&
#275000
b0 J
b10011100111000000111011 Q
b110011100111000000111011 R
b111011110011100111000000111011 :
b111011110011100111000000111011 H
b1110111 P
b110011100111000000111011 N
b0 M
b1110111 O
b110011100111000000111011 I
b0 L
b1110111 K
b0 #
b0 +
b0 8
b0 D
b10 A
b111011110011100111000000111011 ?
b111011110011100111000000111011 E
0!
1&
#280000
0&
#285000
b0 A
b1000 B
1!
1"
b111011110011100111000000111011 $
b111011110011100111000000111011 (
b111011110011100111000000111011 <
1&
#290000
0&
#295000
b111100010011100111000000111011 :
b111100010011100111000000111011 H
b1111000 P
b110011100111000000111011 R
b110011100111000000111011 M
b0 O
b110011100111000000111011 J
b1110111 L
b1100000011000 *
b111011110011100111000000111011 #
b111011110011100111000000111011 +
b111011110011100111000000111011 8
b111011110011100111000000111011 D
b1 A
0"
b1100000011000 %
b1100000011000 )
b1100000011000 ;
1&
#300000
0&
#305000
b1111100000110111101101 Q
b101111100000110111101101 R
b101111100000110111101101 N
b101111100000110111101101 I
b111011001111100000110111101101 :
b111011001111100000110111101101 H
b1110110 P
b0 M
b1110110 O
b0 J
b1110110 K
b0 L
b10 A
b111011001111100000110111101101 ?
b111011001111100000110111101101 E
0!
b0 #
b0 +
b0 8
b0 D
1&
#310000
0&
#315000
b0 A
b1001 B
1!
1"
b111011001111100000110111101101 $
b111011001111100000110111101101 (
b111011001111100000110111101101 <
1&
#320000
0&
#325000
b111011101111100000110111101101 :
b111011101111100000110111101101 H
b1110111 P
b101111100000110111101101 R
b101111100000110111101101 M
b0 O
b101111100000110111101101 J
b1100000011100 *
b1110110 L
b1 A
0"
b1100000011100 %
b1100000011100 )
b1100000011100 ;
b111011001111100000110111101101 #
b111011001111100000110111101101 +
b111011001111100000110111101101 8
b111011001111100000110111101101 D
1&
#330000
0&
#335000
b0 J
b1010100110010011000011 Q
b101010100110010011000011 R
b111010101010100110010011000011 :
b111010101010100110010011000011 H
b1110101 P
b101010100110010011000011 N
b0 M
b1110101 O
b101010100110010011000011 I
b0 L
b1110101 K
b0 #
b0 +
b0 8
b0 D
b10 A
b111010101010100110010011000011 ?
b111010101010100110010011000011 E
0!
1&
#340000
0&
#345000
b0 A
b1010 B
1!
1"
b111010101010100110010011000011 $
b111010101010100110010011000011 (
b111010101010100110010011000011 <
1&
#350000
0&
#355000
b111011001010100110010011000011 :
b111011001010100110010011000011 H
b1110110 P
b101010100110010011000011 R
b101010100110010011000011 M
b0 O
b101010100110010011000011 J
b1110101 L
b1100000100000 *
b111010101010100110010011000011 #
b111010101010100110010011000011 +
b111010101010100110010011000011 8
b111010101010100110010011000011 D
b1 A
0"
b1100000100000 %
b1100000100000 )
b1100000100000 ;
1&
#360000
0&
#365000
b111010100100101010010 Q
b100111010100100101010010 R
b100111010100100101010010 N
b100111010100100101010010 I
b111010000111010100100101010010 :
b111010000111010100100101010010 H
b1110100 P
b0 M
b1110100 O
b0 J
b1110100 K
b0 L
b10 A
b111010000111010100100101010010 ?
b111010000111010100100101010010 E
0!
b0 #
b0 +
b0 8
b0 D
1&
#370000
0&
#375000
b0 A
b1011 B
1!
1"
b111010000111010100100101010010 $
b111010000111010100100101010010 (
b111010000111010100100101010010 <
1&
#380000
0&
#385000
b111010100111010100100101010010 :
b111010100111010100100101010010 H
b1110101 P
b100111010100100101010010 R
b100111010100100101010010 M
b0 O
b100111010100100101010010 J
b1100000100100 *
b1110100 L
b1 A
0"
b1100000100100 %
b1100000100100 )
b1100000100100 ;
b111010000111010100100101010010 #
b111010000111010100100101010010 +
b111010000111010100100101010010 8
b111010000111010100100101010010 D
1&
#390000
0&
#395000
b0 J
b111001100111010100100101010010 :
b111001100111010100100101010010 H
b1110011 P
b0 M
b1110011 O
b0 L
b1110011 K
b0 #
b0 +
b0 8
b0 D
b10 A
b111001100111010100100101010010 ?
b111001100111010100100101010010 E
0!
1&
#400000
0&
#405000
b0 A
b1100 B
1!
1"
b111001100111010100100101010010 $
b111001100111010100100101010010 (
b111001100111010100100101010010 <
1&
#410000
0&
#415000
b111010000111010100100101010010 :
b111010000111010100100101010010 H
b1110100 P
b100111010100100101010010 R
b100111010100100101010010 M
b0 O
b100111010100100101010010 J
b1110011 L
b1100000101000 *
b111001100111010100100101010010 #
b111001100111010100100101010010 +
b111001100111010100100101010010 8
b111001100111010100100101010010 D
b1 A
0"
b1100000101000 %
b1100000101000 )
b1100000101000 ;
1&
#420000
0&
#425000
b10100011011011100010111 Q
b110100011011011100010111 R
b110100011011011100010111 N
b110100011011011100010111 I
b111000110100011011011100010111 :
b111000110100011011011100010111 H
b1110001 P
b0 M
b1110001 O
b0 J
b1110001 K
b0 L
b10 A
b111000110100011011011100010111 ?
b111000110100011011011100010111 E
0!
b0 #
b0 +
b0 8
b0 D
1&
#430000
0&
#435000
b0 A
b1101 B
1!
1"
b111000110100011011011100010111 $
b111000110100011011011100010111 (
b111000110100011011011100010111 <
1&
#440000
0&
#445000
b111001010100011011011100010111 :
b111001010100011011011100010111 H
b1110010 P
b110100011011011100010111 R
b110100011011011100010111 M
b0 O
b110100011011011100010111 J
b1100000101100 *
b1110001 L
b1 A
0"
b1100000101100 %
b1100000101100 )
b1100000101100 ;
b111000110100011011011100010111 #
b111000110100011011011100010111 +
b111000110100011011011100010111 8
b111000110100011011011100010111 D
1&
#450000
0&
#455000
b111000110100011011011100010111 :
b111000110100011011011100010111 H
b1110001 P
b0 M
b1110001 O
b0 J
b0 L
b0 #
b0 +
b0 8
b0 D
b10 A
0!
1&
#460000
0&
#465000
b0 A
b1110 B
1!
1"
1&
#470000
0&
#475000
b111001010100011011011100010111 :
b111001010100011011011100010111 H
b1110010 P
b110100011011011100010111 R
b110100011011011100010111 M
b0 O
b110100011011011100010111 J
b1110001 L
b111000110100011011011100010111 #
b111000110100011011011100010111 +
b111000110100011011011100010111 8
b111000110100011011011100010111 D
b1 >
b0 B
0"
0!
1&
#480000
0&
#485000
b111111111000 *
b1 A
b1 B
b11111111101 @
1!
b0 $
b0 (
b0 <
b111111111000 %
b111111111000 )
b111111111000 ;
1&
#490000
0&
#495000
b0 J
b11111000101000001001000 Q
b111111000101000001001000 R
b111101011111000101000001001000 :
b111101011111000101000001001000 H
b1111010 P
b111111000101000001001000 N
b0 M
b1111010 O
b111111000101000001001000 I
b0 L
b1111010 K
b0 #
b0 +
b0 8
b0 D
b10 A
b111101011111000101000001001000 ?
b111101011111000101000001001000 E
0!
1&
#500000
0&
#505000
b0 A
b10 B
1!
1"
b111101011111000101000001001000 $
b111101011111000101000001001000 (
b111101011111000101000001001000 <
1&
#510000
0&
#515000
b111101111111000101000001001000 :
b111101111111000101000001001000 H
b1111011 P
b111111000101000001001000 R
b111111000101000001001000 M
b0 O
b111111000101000001001000 J
b1111010 L
b111111111100 *
b111101011111000101000001001000 #
b111101011111000101000001001000 +
b111101011111000101000001001000 8
b111101011111000101000001001000 D
b1 A
0"
b111111111100 %
b111111111100 )
b111111111100 ;
1&
#520000
0&
#525000
b110010110010100101100 Q
b100110010110010100101100 R
b100110010110010100101100 N
b100110010110010100101100 I
b111110100110010110010100101100 :
b111110100110010110010100101100 H
b1111101 P
b0 M
b1111101 O
b0 J
b1111101 K
b0 L
b10 A
b111110100110010110010100101100 ?
b111110100110010110010100101100 E
0!
b0 #
b0 +
b0 8
b0 D
1&
#530000
0&
#535000
b0 A
b11 B
1!
1"
b111110100110010110010100101100 $
b111110100110010110010100101100 (
b111110100110010110010100101100 <
1&
#540000
0&
#545000
b111111000110010110010100101100 :
b111111000110010110010100101100 H
b1111110 P
b100110010110010100101100 R
b100110010110010100101100 M
b0 O
b100110010110010100101100 J
b1000000000000 *
b1111101 L
b1 A
0"
b1000000000000 %
b1000000000000 )
b1000000000000 ;
b111110100110010110010100101100 #
b111110100110010110010100101100 +
b111110100110010110010100101100 8
b111110100110010110010100101100 D
1&
#550000
0&
#555000
b0 J
b11100011101111001101 Q
b100011100011101111001101 R
b111110000011100011101111001101 :
b111110000011100011101111001101 H
b1111100 P
b100011100011101111001101 N
b0 M
b1111100 O
b100011100011101111001101 I
b0 L
b1111100 K
b0 #
b0 +
b0 8
b0 D
b10 A
b111110000011100011101111001101 ?
b111110000011100011101111001101 E
0!
1&
#560000
0&
#565000
b0 A
b100 B
1!
1"
b111110000011100011101111001101 $
b111110000011100011101111001101 (
b111110000011100011101111001101 <
1&
#570000
0&
#575000
b111110100011100011101111001101 :
b111110100011100011101111001101 H
b1111101 P
b100011100011101111001101 R
b100011100011101111001101 M
b0 O
b100011100011101111001101 J
b1111100 L
b1000000000100 *
b111110000011100011101111001101 #
b111110000011100011101111001101 +
b111110000011100011101111001101 8
b111110000011100011101111001101 D
b1 A
0"
b1000000000100 %
b1000000000100 )
b1000000000100 ;
1&
#580000
0&
#585000
b110001001001101111 Q
b100000110001001001101111 R
b100000110001001001101111 N
b100000110001001001101111 I
b111101100000110001001001101111 :
b111101100000110001001001101111 H
b1111011 P
b0 M
b1111011 O
b0 J
b1111011 K
b0 L
b10 A
b111101100000110001001001101111 ?
b111101100000110001001001101111 E
0!
b0 #
b0 +
b0 8
b0 D
1&
#590000
0&
#595000
b0 A
b101 B
1!
1"
b111101100000110001001001101111 $
b111101100000110001001001101111 (
b111101100000110001001001101111 <
1&
#600000
0&
#605000
b111110000000110001001001101111 :
b111110000000110001001001101111 H
b1111100 P
b100000110001001001101111 R
b100000110001001001101111 M
b0 O
b100000110001001001101111 J
b1000000001000 *
b1111011 L
b1 A
0"
b1000000001000 %
b1000000001000 )
b1000000001000 ;
b111101100000110001001001101111 #
b111101100000110001001001101111 +
b111101100000110001001001101111 8
b111101100000110001001001101111 D
1&
#610000
0&
#615000
b0 J
b11100011010100111111100 Q
b111100011010100111111100 R
b111100111100011010100111111100 :
b111100111100011010100111111100 H
b1111001 P
b111100011010100111111100 N
b0 M
b1111001 O
b111100011010100111111100 I
b0 L
b1111001 K
b0 #
b0 +
b0 8
b0 D
b10 A
b111100111100011010100111111100 ?
b111100111100011010100111111100 E
0!
1&
#620000
0&
#625000
b0 A
b110 B
1!
1"
b111100111100011010100111111100 $
b111100111100011010100111111100 (
b111100111100011010100111111100 <
1&
#630000
0&
#635000
b111101011100011010100111111100 :
b111101011100011010100111111100 H
b1111010 P
b111100011010100111111100 R
b111100011010100111111100 M
b0 O
b111100011010100111111100 J
b1111001 L
b1000000001100 *
b111100111100011010100111111100 #
b111100111100011010100111111100 +
b111100111100011010100111111100 8
b111100111100011010100111111100 D
b1 A
0"
b1000000001100 %
b1000000001100 )
b1000000001100 ;
1&
#640000
0&
#645000
b10111101101001010001001 Q
b110111101101001010001001 R
b110111101101001010001001 N
b110111101101001010001001 I
b111100010111101101001010001001 :
b111100010111101101001010001001 H
b1111000 P
b0 M
b1111000 O
b0 J
b1111000 K
b0 L
b10 A
b111100010111101101001010001001 ?
b111100010111101101001010001001 E
0!
b0 #
b0 +
b0 8
b0 D
1&
#650000
0&
#655000
b0 A
b111 B
1!
1"
b111100010111101101001010001001 $
b111100010111101101001010001001 (
b111100010111101101001010001001 <
1&
#660000
0&
#665000
b111100110111101101001010001001 :
b111100110111101101001010001001 H
b1111001 P
b110111101101001010001001 R
b110111101101001010001001 M
b0 O
b110111101101001010001001 J
b1000000010000 *
b1111000 L
b1 A
0"
b1000000010000 %
b1000000010000 )
b1000000010000 ;
b111100010111101101001010001001 #
b111100010111101101001010001001 +
b111100010111101101001010001001 8
b111100010111101101001010001001 D
1&
#670000
0&
