Verilog_file/BRAM_Model.v
module bram(
    input  wire            clka,
    input  wire            ena,
    input  wire            wea,
    input  wire  [31:0]    addra,
    input  wire  [31:0]    dina,
    output reg   [31:0]    douta
);

    reg [31:0] mem [0:7999];
    reg [31:0] mem1;
    reg [31:0] mem2;
    reg [31:0] mem3;
    reg [31:0] mem4;
    reg [31:0] mem5;
    reg [31:0] mem6;
    reg [31:0] mem7;
    reg [31:0] mem8;
    reg [31:0] mem9;
    reg [31:0] mem10;
    reg [31:0] mem11;

    // 13비트 주소 인덱스 (0~8191까지 가능, 실제는 0~7999만 사용)
    wire [12:0] addr_index = addra[12:0];

    integer i;

    // 초기화 블록 (시뮬레이션용)
    initial begin
        for (i = 0; i <= 7999; i = i + 1) begin
            mem[i] = 32'd0;
        end
    end

    // 동기식 동작 (읽기/쓰기)
    always @(posedge clka) begin
        if (ena) begin
            if (wea != 1'b0) begin
                mem[addr_index] = dina;
            end
            douta <= mem[addr_index];

            // 디버깅용 특정 위치 레지스터 저장
            mem1 <= mem[0];
            mem2 <= mem[4];
            mem3 <= mem[8];
            mem4 <= mem[12];
            mem5 <= mem[16];
            mem6 <= mem[20];
            mem7 <= mem[24];
            mem8 <= mem[28];
            mem9 <= mem[32];
            mem10 <= mem[36];
            mem11 <= mem[40];

            // 디버깅 출력
            // $display("[READ ] MEM[%0d] [0x%08X] => 0x%08X", addr_index, dina, mem[addr_index]);
        end
    end

endmodule

Verilog_file/PulseGenFin/fp32_adder.v
module fp32_adder (
    input  [31:0] a,
    input  [31:0] b,
    output [31:0] result
);
    wire sign_a = a[31];
    wire sign_b = b[31];
    wire [7:0] exp_a = a[30:23];
    wire [7:0] exp_b = b[30:23];
    wire [23:0] mant_a = (exp_a == 0) ? {1'b0, a[22:0]} : {1'b1, a[22:0]};
    wire [23:0] mant_b = (exp_b == 0) ? {1'b0, b[22:0]} : {1'b1, b[22:0]};

    reg [7:0] exp_diff;
    reg [23:0] aligned_a, aligned_b;
    reg [7:0] exp_res;
    reg [24:0] mant_sum;
    reg sign_res;
    reg [22:0] frac_res;

    always @(*) begin
        // 지수 맞춤
        if (exp_a > exp_b) begin
            exp_diff = exp_a - exp_b;
            aligned_a = mant_a;
            aligned_b = mant_b >> exp_diff;
            exp_res = exp_a;
            sign_res = sign_a;
        end else begin
            exp_diff = exp_b - exp_a;
            aligned_a = mant_a >> exp_diff;
            aligned_b = mant_b;
            exp_res = exp_b;
            sign_res = sign_b;
        end

        // 같은 부호만 지원 (간단 버전)
        if (sign_a == sign_b) begin
            mant_sum = aligned_a + aligned_b;
            if (mant_sum[24]) begin
                mant_sum = mant_sum >> 1;
                exp_res = exp_res + 1;
            end
        end else begin
            // 부호 다르면 뺄셈인데, 여기선 간단히 무시
            mant_sum = 0;
        end

        frac_res = mant_sum[22:0];
    end

    assign result = {sign_res, exp_res, frac_res};
endmodule

Verilog_file/PulseGenFin/PulseGenNut.v
`timescale 1ns / 1ps
`include "./Verilog_file/BRAM_Model.v"
`include "./Verilog_file/fp32_adder.v"

module PulseGenNut(
    input wire clk,
    input wire [31:0] cps,
    output reg [31:0] bram_addr,
    output reg [31:0] bram_data_in,
    output reg ena,
    output reg bram_we,
    input wire [31:0] bram_data_out
);
    // reg [9:0] lfsr = 10'b1010101010;  // 10비트 초기값
    reg [10:0] lfsr = 11'b10101010101;  // 11비트 초기값

    reg [31:0] count = 0;
    reg [31:0] prev_cps = 0;

    reg [31:0] mem_count = 0;

    reg [3:0] mem_control_state = 0;

    // Neutron Pulse Data Table
    reg [31:0] float_data [0:49];

    initial begin
        float_data[0] = 32'h3DA339C1; // 0.0797
        float_data[1] = 32'h3F59AD43; // 0.8503
        float_data[2] = 32'h3F73A29C; // 0.9517
        float_data[3] = 32'h3F652546; // 0.8951
        float_data[4] = 32'h3F4EC56D; // 0.8077
        float_data[5] = 32'h3F388CE7; // 0.7209
        float_data[6] = 32'h3F242C3D; // 0.6413
        float_data[7] = 32'h3F11EB85; // 0.57
        float_data[8] = 32'h3F01A9FC; // 0.5065
        float_data[9] = 32'h3EE67382; // 0.4501
        float_data[10] = 32'h3ECCBFB1; // 0.3999
        float_data[11] = 32'h3EB5F6FD; // 0.3554
        float_data[12] = 32'h3EA1B08A; // 0.3158
        float_data[13] = 32'h3E8FAACE; // 0.2806
        float_data[14] = 32'h3E7F4880; // 0.2493
        float_data[15] = 32'h3E62D0E5; // 0.2215
        float_data[16] = 32'h3E4985F0; // 0.1968
        float_data[17] = 32'h3E3318FC; // 0.1749
        float_data[18] = 32'h3E1F212D; // 0.1554
        float_data[19] = 32'h3E0D6A16; // 0.1381
        float_data[20] = 32'h3DFB4A23; // 0.1227
        float_data[21] = 32'h3DDF3B64; // 0.109
        float_data[22] = 32'h3DC67382; // 0.0969
        float_data[23] = 32'h3DB05532; // 0.0861
        float_data[24] = 32'h3D9CAC08; // 0.0765
        float_data[25] = 32'h3D8B4396; // 0.068
        float_data[26] = 32'h3D7765FE; // 0.0604
        float_data[27] = 32'h3D5B8BAC; // 0.0536
        float_data[28] = 32'h3D436113; // 0.0477
        float_data[29] = 32'h3D2DAB9F; // 0.0424
        float_data[30] = 32'h3D1A0275; // 0.0376
        float_data[31] = 32'h3D08CE70; // 0.0334
        float_data[32] = 32'h3CF34D6A; // 0.0297
        float_data[33] = 32'h3CD844D0; // 0.0264
        float_data[34] = 32'h3CC08312; // 0.0235
        float_data[35] = 32'h3CAA64C3; // 0.0208
        float_data[36] = 32'h3C978D50; // 0.0185
        float_data[37] = 32'h3C872B02; // 0.0165
        float_data[38] = 32'h3C6F34D7; // 0.0146
        float_data[39] = 32'h3C54FDF4; // 0.013
        float_data[40] = 32'h3C3C6A7F; // 0.0115
        float_data[41] = 32'h3C28C155; // 0.0103
        float_data[42] = 32'h3C15182B; // 0.0091
        float_data[43] = 32'h3C04B5DD; // 0.0081
        float_data[44] = 32'h3BEBEDFA; // 0.0072
        float_data[45] = 32'h3BD1B717; // 0.0064
        float_data[46] = 32'h3BBAC711; // 0.0057
        float_data[47] = 32'h3BA3D70A; // 0.005
        float_data[48] = 32'h3B9374BC; // 0.0045
        float_data[49] = 32'h3B83126F; // 0.004
    end

    wire [31:0] fp_add_result;
    reg [31:0] fp_table_input;

    fp32_adder adder_inst (
        .a(bram_data_out),
        .b(fp_table_input),         // IEEE 754
        .result(fp_add_result)
    );

    always @(posedge clk) begin
        if (cps == 0) begin
            // Input/Output Parameter --
            bram_addr <= 0;
            ena <= 0;
            bram_we <= 0;

            // Local Parameter --
            // lfsr <= 10'b1010101010;
            // lfsr <= 11'b10101010101; // 11비트 초기값
            lfsr <= {lfsr[9:0], lfsr[10] ^ lfsr[7]}; // 11비트 LFSR로 변경 (이전 변경 값을 가져다 씀)
            
            count <= 0;
            prev_cps <= 0;

            mem_count <= 0;

            mem_control_state <= 0;
        end else begin
            // cps가 변경되었을 경우 재시작
            if (cps != prev_cps) begin
                // Input/Output Parameter --
                bram_addr <= 0;
                ena <= 0;
                bram_we <= 0;

                // Local Parameter --
                // lfsr <= 10'b1010101010;
                // lfsr <= 11'b10101010101; // 11비트 초기값
                lfsr <= {lfsr[9:0], lfsr[10] ^ lfsr[7]}; // 11비트 LFSR로 변경 (이전 변경 값을 가져다 씀)

                count <= 0;
                prev_cps <= cps;

                mem_count <= 0;

                mem_control_state <= 0;
            end else if (count < cps) begin
                if (mem_count == 0) begin
                    // Input/Output Parameter --
                    // bram_addr <= 32'b100; // lfsr * 4;                // 0 ~ 1023 개 가능
                    bram_addr <= lfsr * 4;                // 11비트 0 ~ 2047 개 가능
                    bram_data_in <= 0;                    // Pulse Initialization
                    ena <= 1;                             // 활성화         
                    bram_we <= 0;                         // 펄스 읽기

                    // Local Parameter --
                    // 10비트 LFSR: x^10 + x^7 + 1
                    // lfsr <= {lfsr[8:0], lfsr[9] ^ lfsr[6]};
                    lfsr <= {lfsr[9:0], lfsr[10] ^ lfsr[7]}; // 11비트 LFSR로 변경
                    
                    // Pulse 메모리에 1 부터 증가하는 값 쓰기
                    mem_count <= 1;                 // 메모리 카운트 증가

                    mem_control_state <= 1;
                end else begin
                    if (mem_count > 50) begin
                        // 메모리 카운트가 50 이상이면 펄스 종료
                        // Input/Output Parameter --
                        ena <= 0;                             // 비횔성화      
                        bram_we <= 0;                         // 펄스 읽기
                        // Local Parameter --
                        mem_count <= 0;                 // 메모리 카운트 초기화

                        mem_control_state <= 0;         // BRAM 제어 상태 초기화
                        count <= count + 1;

                    end else begin
                        case (mem_control_state)
                            0: begin
                                bram_addr <= bram_addr + 4;
                                bram_we <= 0;                   // 펄스 읽기
                                ena <= 1;                       // 활성화
                                // 주소 유지
                                mem_control_state <= 1;
                            end
                            1: begin
                                // 대기 
                                bram_we <= 0;                   // 펄스 읽기
                                ena <= 0;                       // 비활성화
                                //
                                fp_table_input <= float_data[mem_count - 1]; // 0.1 ~ 0.6
                                mem_control_state <= 2;
                            end
                            2: begin
                                // write 완료, 다음 주소로 이동
                                bram_addr <= bram_addr;
                                bram_data_in <= fp_add_result;

                                bram_we <= 1;                   // 펄스 쓰기
                                ena <= 1;                       // 활성화
                                //
                                mem_count <= mem_count + 1;
                                mem_control_state <= 0; // 다음 루프
                            end
                        endcase
                    end
                end

            end else begin
                bram_we <= 0;                   
                ena <= 0;

                mem_count <= 0;
            end 
        end
    end
endmodule


module tb_PulseGenNut();

    // Inputs
    reg clk;
    reg [31:0] cps;

    // Outputs
    wire [31:0] bram_addr;
    wire [31:0] bram_data_in;
    wire ena;
    wire bram_we;
    wire [31:0] bram_data_out;

    // Instantiate the Unit Under Test (UUT)
    PulseGenNut uut (
        .clk(clk),
        .cps(cps),
        .bram_addr(bram_addr),
        .bram_data_in(bram_data_in),
        .ena(ena),
        .bram_we(bram_we),
        .bram_data_out(bram_data_out)
    );

    bram pulse_bram_inst (
        .clka(clk),
        .ena(ena),
        .wea(bram_we),
        .addra(bram_addr),
        .dina(bram_data_in),
        .douta(bram_data_out)  // Read output not used in this test
    );

    // Clock generation: 10ns period
    always #5 clk = ~clk;

    initial begin
        $dumpfile("Verilog_file/PulseGenFin/PulseGenNut.vcd");
        $dumpvars(0, tb_PulseGenNut);
        // Initialize inputs
        clk = 0;
        cps = 0;

        // Wait for global reset
        #20;

        // Test 1: cps = 0 → 모듈 초기화 상태 유지
        cps = 0;
        #50;

        // Test 2: cps = 10 → 10개의 pulse 발생
        cps = 1;
        #2000;

        cps = 0;
        #50

        // Test 2: cps = 10 → 10개의 pulse 발생
        cps = 1;
        #500;

        // // Test 3: cps = 5 → 다시 시작됨 (변경된 cps 값)
        // cps = 5;
        // #500;

        // // Test 4: cps = 0 → 종료
        // cps = 0;
        // #100;

        $finish;
    end

endmodule

Verilog_file/PulseGenFin/PulseGenNut.vcd
$date
	Mon Aug 04 23:49:58 2025
$end
$version
	Icarus Verilog
$end
$timescale
	1ps
$end
$scope module tb_PulseGenNut $end
$var wire 1 ! ena $end
$var wire 1 " bram_we $end
$var wire 32 # bram_data_out [31:0] $end
$var wire 32 $ bram_data_in [31:0] $end
$var wire 32 % bram_addr [31:0] $end
$var reg 1 & clk $end
$var reg 32 ' cps [31:0] $end
$scope module pulse_bram_inst $end
$var wire 1 & clka $end
$var wire 1 " wea $end
$var wire 1 ! ena $end
$var wire 32 ( dina [31:0] $end
$var wire 32 ) addra [31:0] $end
$var wire 13 * addr_index [12:0] $end
$var reg 32 + douta [31:0] $end
$var reg 32 , mem1 [31:0] $end
$var reg 32 - mem10 [31:0] $end
$var reg 32 . mem11 [31:0] $end
$var reg 32 / mem2 [31:0] $end
$var reg 32 0 mem3 [31:0] $end
$var reg 32 1 mem4 [31:0] $end
$var reg 32 2 mem5 [31:0] $end
$var reg 32 3 mem6 [31:0] $end
$var reg 32 4 mem7 [31:0] $end
$var reg 32 5 mem8 [31:0] $end
$var reg 32 6 mem9 [31:0] $end
$var integer 32 7 i [31:0] $end
$upscope $end
$scope module uut $end
$var wire 32 8 bram_data_out [31:0] $end
$var wire 1 & clk $end
$var wire 32 9 cps [31:0] $end
$var wire 32 : fp_add_result [31:0] $end
$var reg 32 ; bram_addr [31:0] $end
$var reg 32 < bram_data_in [31:0] $end
$var reg 1 " bram_we $end
$var reg 32 = count [31:0] $end
$var reg 1 ! ena $end
$var reg 32 > fp_table_input [31:0] $end
$var reg 11 ? lfsr [10:0] $end
$var reg 4 @ mem_control_state [3:0] $end
$var reg 32 A mem_count [31:0] $end
$var reg 32 B prev_cps [31:0] $end
$scope module adder_inst $end
$var wire 32 C a [31:0] $end
$var wire 32 D b [31:0] $end
$var wire 1 E sign_b $end
$var wire 1 F sign_a $end
$var wire 32 G result [31:0] $end
$var wire 24 H mant_b [23:0] $end
$var wire 24 I mant_a [23:0] $end
$var wire 8 J exp_b [7:0] $end
$var wire 8 K exp_a [7:0] $end
$var reg 24 L aligned_a [23:0] $end
$var reg 24 M aligned_b [23:0] $end
$var reg 8 N exp_diff [7:0] $end
$var reg 8 O exp_res [7:0] $end
$var reg 23 P frac_res [22:0] $end
$var reg 25 Q mant_sum [24:0] $end
$var reg 1 R sign_res $end
$upscope $end
$upscope $end
$upscope $end
$enddefinitions $end
$comment Show the parameter values. $end
$dumpall
$end
#0
$dumpvars
xR
b0 Q
b0 P
bx O
bx N
bx M
bx L
bx K
bx J
bx I
bx H
bx00000000000000000000000 G
xF
xE
bx D
bx C
b0 B
b0 A
b0 @
b10101010101 ?
bx >
b0 =
bx <
bx ;
bx00000000000000000000000 :
b0 9
bx 8
b1111101000000 7
bx 6
bx 5
bx 4
bx 3
bx 2
bx 1
bx 0
bx /
bx .
bx -
bx ,
bx +
bx *
bx )
bx (
b0 '
0&
bx %
bx $
bx #
x"
x!
$end
#5000
b0 *
b1010101011 ?
0"
0!
b0 %
b0 )
b0 ;
1&
#10000
0&
#15000
b10101010111 ?
1&
#20000
0&
#25000
b1010101111 ?
1&
#30000
0&
#35000
b10101011111 ?
1&
#40000
0&
#45000
b1010111111 ?
1&
#50000
0&
#55000
b10101111111 ?
1&
#60000
0&
#65000
b1011111111 ?
1&
#70000
0&
b1 '
b1 9
#75000
b1 B
b10111111111 ?
1&
#80000
0&
#85000
b1011111111100 *
b1 @
b1 A
b1111111110 ?
1!
b0 $
b0 (
b0 <
b1011111111100 %
b1011111111100 )
b1011111111100 ;
1&
#90000
0&
#95000
b0 I
b1000110011100111000001 P
b101000110011100111000001 Q
0R
b111101101000110011100111000001 :
b111101101000110011100111000001 G
b1111011 O
b101000110011100111000001 M
b0 L
b1111011 N
b101000110011100111000001 H
0F
b0 K
0E
b1111011 J
b0 .
b0 -
b0 6
b0 5
b0 4
b0 3
b0 2
b0 1
b0 0
b0 /
b0 ,
b0 #
b0 +
b0 8
b0 C
b10 @
b111101101000110011100111000001 >
b111101101000110011100111000001 D
0!
1&
#100000
0&
#105000
b0 @
b10 A
1!
1"
b111101101000110011100111000001 $
b111101101000110011100111000001 (
b111101101000110011100111000001 <
1&
#110000
0&
#115000
b111110001000110011100111000001 :
b111110001000110011100111000001 G
b1111100 O
b101000110011100111000001 Q
b101000110011100111000001 L
b0 N
b101000110011100111000001 I
b1111011 K
b1100000000000 *
b111101101000110011100111000001 #
b111101101000110011100111000001 +
b111101101000110011100111000001 8
b111101101000110011100111000001 C
b1 @
0"
b1100000000000 %
b1100000000000 )
b1100000000000 ;
1&
#120000
0&
#125000
b10110011010110101000011 P
b110110011010110101000011 Q
b110110011010110101000011 M
b110110011010110101000011 H
b111111010110011010110101000011 :
b111111010110011010110101000011 G
b1111110 O
b0 L
b1111110 N
b0 I
b1111110 J
b0 K
b10 @
b111111010110011010110101000011 >
b111111010110011010110101000011 D
0!
b0 #
b0 +
b0 8
b0 C
1&
#130000
0&
#135000
b0 @
b11 A
1!
1"
b111111010110011010110101000011 $
b111111010110011010110101000011 (
b111111010110011010110101000011 <
1&
#140000
0&
#145000
b111111110110011010110101000011 :
b111111110110011010110101000011 G
b1111111 O
b110110011010110101000011 Q
b110110011010110101000011 L
b0 N
b110110011010110101000011 I
b1100000000100 *
b1111110 K
b1 @
0"
b1100000000100 %
b1100000000100 )
b1100000000100 ;
b111111010110011010110101000011 #
b111111010110011010110101000011 +
b111111010110011010110101000011 8
b111111010110011010110101000011 C
1&
#150000
0&
#155000
b11100111010001010011100 P
b111100111010001010011100 Q
b111111011100111010001010011100 :
b111111011100111010001010011100 G
b1111110 O
b111100111010001010011100 M
b0 L
b1111110 N
b0 I
b111100111010001010011100 H
b0 K
b0 #
b0 +
b0 8
b0 C
b10 @
b111111011100111010001010011100 >
b111111011100111010001010011100 D
0!
1&
#160000
0&
#165000
b0 @
b100 A
1!
1"
b111111011100111010001010011100 $
b111111011100111010001010011100 (
b111111011100111010001010011100 <
1&
#170000
0&
#175000
b111111111100111010001010011100 :
b111111111100111010001010011100 G
b1111111 O
b111100111010001010011100 Q
b111100111010001010011100 L
b0 N
b111100111010001010011100 I
b1111110 K
b1100000001000 *
b111111011100111010001010011100 #
b111111011100111010001010011100 +
b111111011100111010001010011100 8
b111111011100111010001010011100 C
b1 @
0"
b1100000001000 %
b1100000001000 )
b1100000001000 ;
1&
#180000
0&
#185000
b11001010010010101000110 P
b111001010010010101000110 Q
b111001010010010101000110 M
b111001010010010101000110 H
b111111011001010010010101000110 :
b111111011001010010010101000110 G
b1111110 O
b0 L
b1111110 N
b0 I
b0 K
b10 @
b111111011001010010010101000110 >
b111111011001010010010101000110 D
0!
b0 #
b0 +
b0 8
b0 C
1&
#190000
0&
#195000
b0 @
b101 A
1!
1"
b111111011001010010010101000110 $
b111111011001010010010101000110 (
b111111011001010010010101000110 <
1&
#200000
0&
#205000
b111111111001010010010101000110 :
b111111111001010010010101000110 G
b1111111 O
b111001010010010101000110 Q
b111001010010010101000110 L
b0 N
b111001010010010101000110 I
b1100000001100 *
b1111110 K
b1 @
0"
b1100000001100 %
b1100000001100 )
b1100000001100 ;
b111111011001010010010101000110 #
b111111011001010010010101000110 +
b111111011001010010010101000110 8
b111111011001010010010101000110 C
1&
#210000
0&
#215000
b10011101100010101101101 P
b110011101100010101101101 Q
b111111010011101100010101101101 :
b111111010011101100010101101101 G
b1111110 O
b110011101100010101101101 M
b0 L
b1111110 N
b0 I
b110011101100010101101101 H
b0 K
b0 #
b0 +
b0 8
b0 C
b10 @
b111111010011101100010101101101 >
b111111010011101100010101101101 D
0!
1&
#220000
0&
#225000
b0 @
b110 A
1!
1"
b111111010011101100010101101101 $
b111111010011101100010101101101 (
b111111010011101100010101101101 <
1&
#230000
0&
#235000
b111111110011101100010101101101 :
b111111110011101100010101101101 G
b1111111 O
b110011101100010101101101 Q
b110011101100010101101101 L
b0 N
b110011101100010101101101 I
b1111110 K
b1100000010000 *
b111111010011101100010101101101 #
b111111010011101100010101101101 +
b111111010011101100010101101101 8
b111111010011101100010101101101 C
b1 @
0"
b1100000010000 %
b1100000010000 )
b1100000010000 ;
1&
#240000
0&
#245000
b1110001000110011100111 P
b101110001000110011100111 Q
b101110001000110011100111 M
b101110001000110011100111 H
b111111001110001000110011100111 :
b111111001110001000110011100111 G
b1111110 O
b0 L
b1111110 N
b0 I
b0 K
b10 @
b111111001110001000110011100111 >
b111111001110001000110011100111 D
0!
b0 #
b0 +
b0 8
b0 C
1&
#250000
0&
#255000
b0 @
b111 A
1!
1"
b111111001110001000110011100111 $
b111111001110001000110011100111 (
b111111001110001000110011100111 <
1&
#260000
0&
#265000
b111111101110001000110011100111 :
b111111101110001000110011100111 G
b1111111 O
b101110001000110011100111 Q
b101110001000110011100111 L
b0 N
b101110001000110011100111 I
b1100000010100 *
b1111110 K
b1 @
0"
b1100000010100 %
b1100000010100 )
b1100000010100 ;
b111111001110001000110011100111 #
b111111001110001000110011100111 +
b111111001110001000110011100111 8
b111111001110001000110011100111 C
1&
#270000
0&
#275000
b1001000010110000111101 P
b101001000010110000111101 Q
b111111001001000010110000111101 :
b111111001001000010110000111101 G
b1111110 O
b101001000010110000111101 M
b0 L
b1111110 N
b0 I
b101001000010110000111101 H
b0 K
b0 #
b0 +
b0 8
b0 C
b10 @
b111111001001000010110000111101 >
b111111001001000010110000111101 D
0!
1&
#280000
0&
#285000
b0 @
b1000 A
1!
1"
b111111001001000010110000111101 $
b111111001001000010110000111101 (
b111111001001000010110000111101 <
1&
#290000
0&
#295000
b111111101001000010110000111101 :
b111111101001000010110000111101 G
b1111111 O
b101001000010110000111101 Q
b101001000010110000111101 L
b0 N
b101001000010110000111101 I
b1111110 K
b1100000011000 *
b111111001001000010110000111101 #
b111111001001000010110000111101 +
b111111001001000010110000111101 8
b111111001001000010110000111101 C
b1 @
0"
b1100000011000 %
b1100000011000 )
b1100000011000 ;
1&
#300000
0&
#305000
b100011110101110000101 P
b100100011110101110000101 Q
b100100011110101110000101 M
b100100011110101110000101 H
b111111000100011110101110000101 :
b111111000100011110101110000101 G
b1111110 O
b0 L
b1111110 N
b0 I
b0 K
b10 @
b111111000100011110101110000101 >
b111111000100011110101110000101 D
0!
b0 #
b0 +
b0 8
b0 C
1&
#310000
0&
#315000
b0 @
b1001 A
1!
1"
b111111000100011110101110000101 $
b111111000100011110101110000101 (
b111111000100011110101110000101 <
1&
#320000
0&
#325000
b111111100100011110101110000101 :
b111111100100011110101110000101 G
b1111111 O
b100100011110101110000101 Q
b100100011110101110000101 L
b0 N
b100100011110101110000101 I
b1100000011100 *
b1111110 K
b1 @
0"
b1100000011100 %
b1100000011100 )
b1100000011100 ;
b111111000100011110101110000101 #
b111111000100011110101110000101 +
b111111000100011110101110000101 8
b111111000100011110101110000101 C
1&
#330000
0&
#335000
b11010100111111100 P
b100000011010100111111100 Q
b111111000000011010100111111100 :
b111111000000011010100111111100 G
b1111110 O
b100000011010100111111100 M
b0 L
b1111110 N
b0 I
b100000011010100111111100 H
b0 K
b0 #
b0 +
b0 8
b0 C
b10 @
b111111000000011010100111111100 >
b111111000000011010100111111100 D
0!
1&
#340000
0&
#345000
b0 @
b1010 A
1!
1"
b111111000000011010100111111100 $
b111111000000011010100111111100 (
b111111000000011010100111111100 <
1&
#350000
0&
#355000
b111111100000011010100111111100 :
b111111100000011010100111111100 G
b1111111 O
b100000011010100111111100 Q
b100000011010100111111100 L
b0 N
b100000011010100111111100 I
b1111110 K
b1100000100000 *
b111111000000011010100111111100 #
b111111000000011010100111111100 +
b111111000000011010100111111100 8
b111111000000011010100111111100 C
b1 @
0"
b1100000100000 %
b1100000100000 )
b1100000100000 ;
1&
#360000
0&
#365000
b11001100111001110000010 P
b111001100111001110000010 Q
b111001100111001110000010 M
b111001100111001110000010 H
b111110111001100111001110000010 :
b111110111001100111001110000010 G
b1111101 O
b0 L
b1111101 N
b0 I
b1111101 J
b0 K
b10 @
b111110111001100111001110000010 >
b111110111001100111001110000010 D
0!
b0 #
b0 +
b0 8
b0 C
1&
#370000
0&
#375000
b0 @
b1011 A
1!
1"
b111110111001100111001110000010 $
b111110111001100111001110000010 (
b111110111001100111001110000010 <
1&
#380000
0&
#385000
b111111011001100111001110000010 :
b111111011001100111001110000010 G
b1111110 O
b111001100111001110000010 Q
b111001100111001110000010 L
b0 N
b111001100111001110000010 I
b1100000100100 *
b1111101 K
b1 @
0"
b1100000100100 %
b1100000100100 )
b1100000100100 ;
b111110111001100111001110000010 #
b111110111001100111001110000010 +
b111110111001100111001110000010 8
b111110111001100111001110000010 C
1&
#390000
0&
#395000
b10011001011111110110001 P
b110011001011111110110001 Q
b111110110011001011111110110001 :
b111110110011001011111110110001 G
b1111101 O
b110011001011111110110001 M
b0 L
b1111101 N
b0 I
b110011001011111110110001 H
b0 K
b0 #
b0 +
b0 8
b0 C
b10 @
b111110110011001011111110110001 >
b111110110011001011111110110001 D
0!
1&
#400000
0&
#405000
b0 @
b1100 A
1!
1"
b111110110011001011111110110001 $
b111110110011001011111110110001 (
b111110110011001011111110110001 <
1&
#410000
0&
#415000
b111111010011001011111110110001 :
b111111010011001011111110110001 G
b1111110 O
b110011001011111110110001 Q
b110011001011111110110001 L
b0 N
b110011001011111110110001 I
b1111101 K
b1100000101000 *
b111110110011001011111110110001 #
b111110110011001011111110110001 +
b111110110011001011111110110001 8
b111110110011001011111110110001 C
b1 @
0"
b1100000101000 %
b1100000101000 )
b1100000101000 ;
1&
#420000
0&
#425000
b1101011111011011111101 P
b101101011111011011111101 Q
b101101011111011011111101 M
b101101011111011011111101 H
b111110101101011111011011111101 :
b111110101101011111011011111101 G
b1111101 O
b0 L
b1111101 N
b0 I
b0 K
b10 @
b111110101101011111011011111101 >
b111110101101011111011011111101 D
0!
b0 #
b0 +
b0 8
b0 C
1&
#430000
0&
#435000
b0 @
b1101 A
1!
1"
b111110101101011111011011111101 $
b111110101101011111011011111101 (
b111110101101011111011011111101 <
1&
#440000
0&
#445000
b111111001101011111011011111101 :
b111111001101011111011011111101 G
b1111110 O
b101101011111011011111101 Q
b101101011111011011111101 L
b0 N
b101101011111011011111101 I
b1100000101100 *
b1111101 K
b1 @
0"
b1100000101100 %
b1100000101100 )
b1100000101100 ;
b111110101101011111011011111101 #
b111110101101011111011011111101 +
b111110101101011111011011111101 8
b111110101101011111011011111101 C
1&
#450000
0&
#455000
b1000011011000010001010 P
b101000011011000010001010 Q
b111110101000011011000010001010 :
b111110101000011011000010001010 G
b1111101 O
b101000011011000010001010 M
b0 L
b1111101 N
b0 I
b101000011011000010001010 H
b0 K
b0 #
b0 +
b0 8
b0 C
b10 @
b111110101000011011000010001010 >
b111110101000011011000010001010 D
0!
1&
#460000
0&
#465000
b0 @
b1110 A
1!
1"
b111110101000011011000010001010 $
b111110101000011011000010001010 (
b111110101000011011000010001010 <
1&
#470000
0&
#475000
b111111001000011011000010001010 :
b111111001000011011000010001010 G
b1111110 O
b101000011011000010001010 Q
b101000011011000010001010 L
b0 N
b101000011011000010001010 I
b1111101 K
b1100000110000 *
b111110101000011011000010001010 #
b111110101000011011000010001010 +
b111110101000011011000010001010 8
b111110101000011011000010001010 C
b1 @
0"
b1100000110000 %
b1100000110000 )
b1100000110000 ;
1&
#480000
0&
#485000
b11111010101011001110 P
b100011111010101011001110 Q
b100011111010101011001110 M
b100011111010101011001110 H
b111110100011111010101011001110 :
b111110100011111010101011001110 G
b1111101 O
b0 L
b1111101 N
b0 I
b0 K
b10 @
b111110100011111010101011001110 >
b111110100011111010101011001110 D
0!
b0 #
b0 +
b0 8
b0 C
1&
#490000
0&
#495000
b0 @
b1111 A
1!
1"
b111110100011111010101011001110 $
b111110100011111010101011001110 (
b111110100011111010101011001110 <
1&
#500000
0&
#505000
b111111000011111010101011001110 :
b111111000011111010101011001110 G
b1111110 O
b100011111010101011001110 Q
b100011111010101011001110 L
b0 N
b100011111010101011001110 I
b1100000110100 *
b1111101 K
b1 @
0"
b1100000110100 %
b1100000110100 )
b1100000110100 ;
b111110100011111010101011001110 #
b111110100011111010101011001110 +
b111110100011111010101011001110 8
b111110100011111010101011001110 C
1&
#510000
0&
#515000
b0 I
b11111110100100010000000 P
b111111110100100010000000 Q
b111110011111110100100010000000 :
b111110011111110100100010000000 G
b1111100 O
b111111110100100010000000 M
b0 L
b1111100 N
b111111110100100010000000 H
b0 K
b1111100 J
b0 #
b0 +
b0 8
b0 C
b10 @
b111110011111110100100010000000 >
b111110011111110100100010000000 D
0!
1&
#520000
0&
#525000
b0 @
b10000 A
1!
1"
b111110011111110100100010000000 $
b111110011111110100100010000000 (
b111110011111110100100010000000 <
1&
#530000
0&
#535000
b111110111111110100100010000000 :
b111110111111110100100010000000 G
b1111101 O
b111111110100100010000000 Q
b111111110100100010000000 L
b0 N
b111111110100100010000000 I
b1111100 K
b1100000111000 *
b111110011111110100100010000000 #
b111110011111110100100010000000 +
b111110011111110100100010000000 8
b111110011111110100100010000000 C
b1 @
0"
b1100000111000 %
b1100000111000 )
b1100000111000 ;
1&
#540000
0&
#545000
b11000101101000011100101 P
b111000101101000011100101 Q
b111000101101000011100101 M
b111000101101000011100101 H
b111110011000101101000011100101 :
b111110011000101101000011100101 G
b1111100 O
b0 L
b1111100 N
b0 I
b0 K
b10 @
b111110011000101101000011100101 >
b111110011000101101000011100101 D
0!
b0 #
b0 +
b0 8
b0 C
1&
#550000
0&
#555000
b0 @
b10001 A
1!
1"
b111110011000101101000011100101 $
b111110011000101101000011100101 (
b111110011000101101000011100101 <
1&
#560000
0&
#565000
b111110111000101101000011100101 :
b111110111000101101000011100101 G
b1111101 O
b111000101101000011100101 Q
b111000101101000011100101 L
b0 N
b111000101101000011100101 I
b1100000111100 *
b1111100 K
b1 @
0"
b1100000111100 %
b1100000111100 )
b1100000111100 ;
b111110011000101101000011100101 #
b111110011000101101000011100101 +
b111110011000101101000011100101 8
b111110011000101101000011100101 C
1&
#570000
0&
#575000
b10010011000010111110000 P
b110010011000010111110000 Q
b111110010010011000010111110000 :
b111110010010011000010111110000 G
b1111100 O
b110010011000010111110000 M
b0 L
b1111100 N
b0 I
b110010011000010111110000 H
b0 K
b0 #
b0 +
b0 8
b0 C
b10 @
b111110010010011000010111110000 >
b111110010010011000010111110000 D
0!
1&
#580000
0&
#585000
b0 @
b10010 A
1!
1"
b111110010010011000010111110000 $
b111110010010011000010111110000 (
b111110010010011000010111110000 <
1&
#590000
0&
#595000
b111110110010011000010111110000 :
b111110110010011000010111110000 G
b1111101 O
b110010011000010111110000 Q
b110010011000010111110000 L
b0 N
b110010011000010111110000 I
b1111100 K
b1100001000000 *
b111110010010011000010111110000 #
b111110010010011000010111110000 +
b111110010010011000010111110000 8
b111110010010011000010111110000 C
b1 @
0"
b1100001000000 %
b1100001000000 )
b1100001000000 ;
1&
#600000
0&
