Verilog_file/BRAM_Model.v
module bram(
    input  wire            clka,
    input  wire            ena,
    input  wire            wea,
    input  wire  [31:0]    addra,
    input  wire  [31:0]    dina,
    output reg   [31:0]    douta
);

    reg [31:0] mem [0:7999];
    reg [31:0] mem1;
    reg [31:0] mem2;
    reg [31:0] mem3;
    reg [31:0] mem4;
    reg [31:0] mem5;
    reg [31:0] mem6;
    reg [31:0] mem7;
    reg [31:0] mem8;
    reg [31:0] mem9;
    reg [31:0] mem10;
    reg [31:0] mem11;

    // 13비트 주소 인덱스 (0~8191까지 가능, 실제는 0~7999만 사용)
    wire [12:0] addr_index = addra[12:0];

    integer i;

    // 초기화 블록 (시뮬레이션용)
    initial begin
        for (i = 0; i <= 7999; i = i + 1) begin
            mem[i] = 32'd0;
        end
    end

    // 동기식 동작 (읽기/쓰기)
    always @(posedge clka) begin
        if (ena) begin
            if (wea != 1'b0) begin
                mem[addr_index] = dina;
            end
            douta <= mem[addr_index];

            // 디버깅용 특정 위치 레지스터 저장
            mem1 <= mem[0];
            mem2 <= mem[4];
            mem3 <= mem[8];
            mem4 <= mem[12];
            mem5 <= mem[16];
            mem6 <= mem[20];
            mem7 <= mem[24];
            mem8 <= mem[28];
            mem9 <= mem[32];
            mem10 <= mem[36];
            mem11 <= mem[40];

            // 디버깅 출력
            // $display("[READ ] MEM[%0d] [0x%08X] => 0x%08X", addr_index, dina, mem[addr_index]);
        end
    end

endmodule

Verilog_file/PulseGenFin/fp32_adder.v
module fp32_adder (
    input  [31:0] a,
    input  [31:0] b,
    output [31:0] result
);
    wire sign_a = a[31];
    wire sign_b = b[31];
    wire [7:0] exp_a = a[30:23];
    wire [7:0] exp_b = b[30:23];
    wire [23:0] mant_a = (exp_a == 0) ? {1'b0, a[22:0]} : {1'b1, a[22:0]};
    wire [23:0] mant_b = (exp_b == 0) ? {1'b0, b[22:0]} : {1'b1, b[22:0]};

    reg [7:0] exp_diff;
    reg [23:0] aligned_a, aligned_b;
    reg [7:0] exp_res;
    reg [24:0] mant_sum;
    reg sign_res;
    reg [22:0] frac_res;

    always @(*) begin
        // 지수 맞춤
        if (exp_a > exp_b) begin
            exp_diff = exp_a - exp_b;
            aligned_a = mant_a;
            aligned_b = mant_b >> exp_diff;
            exp_res = exp_a;
            sign_res = sign_a;
        end else begin
            exp_diff = exp_b - exp_a;
            aligned_a = mant_a >> exp_diff;
            aligned_b = mant_b;
            exp_res = exp_b;
            sign_res = sign_b;
        end

        // 같은 부호만 지원 (간단 버전)
        if (sign_a == sign_b) begin
            mant_sum = aligned_a + aligned_b;
            if (mant_sum[24]) begin
                mant_sum = mant_sum >> 1;
                exp_res = exp_res + 1;
            end
        end else begin
            // 부호 다르면 뺄셈인데, 여기선 간단히 무시
            mant_sum = 0;
        end

        frac_res = mant_sum[22:0];
    end

    assign result = {sign_res, exp_res, frac_res};
endmodule

Verilog_file/PulseGenSpeed(폐기)/PulseGenSpeedGam.v
`timescale 1ns / 1ps
`include "./Verilog_file/PulseGenSpeed/BRAM_Model.v"
`include "./Verilog_file/PulseGenSpeed/fp32_adder.v"

module PulseGenSpeedGam(
    input wire clk,
    input wire [31:0] cps,
    output reg [31:0] bram_addr,
    output reg [31:0] bram_data_in,
    output reg bram_we,
    output reg bram_ena,
    input wire [31:0] bram_data_out
);
    // reg [9:0] lfsr = 10'b1010101010;  // 10비트 초기값
    reg [10:0] lfsr = 11'b10101010101;  // 11비트 초기값
    reg [31:0] count = 0;
    reg [31:0] prev_cps = 0;
    reg [31:0] mem_count = 0;
    reg [1:0]  mem_gam_count = 0;
    reg [3:0]  mem_control_state = 0;

    // Neutron Pulse Data Table
    reg [31:0] float_data [0:12];

    initial begin
        float_data[0] = 32'h3D7C5048; // 0.0616
        float_data[1] = 32'h3E99652C; // 0.2996
        float_data[2] = 32'h3E0E3BCD; // 0.1389
        float_data[3] = 32'h3D83126F; // 0.0640
        float_data[4] = 32'h3CF1A9FC; // 0.0295
        float_data[5] = 32'h3C5ED289; // 0.0136
        float_data[6] = 32'h3BCE703B; // 0.0063
        float_data[7] = 32'h3B3E0DED; // 0.0029
        float_data[8] = 32'h3AAA64C3; // 0.0013
        float_data[9] = 32'h3A1D4952; // 0.0006
        float_data[10] = 32'h399D4952; // 0.0003
        float_data[11] = 32'h38D1B717; // 0.0001
        float_data[12] = 32'h38D1B717; // 0.0001
    end

    reg [31:0] save_data [0:12];
    initial begin
        save_data[0] = 32'd0;
        save_data[1] = 32'd0;
        save_data[2] = 32'd0;
        save_data[3] = 32'd0;
        save_data[4] = 32'd0;
        save_data[5] = 32'd0;
        save_data[6] = 32'd0;
        save_data[7] = 32'd0;
        save_data[8] = 32'd0;
        save_data[9] = 32'd0;
        save_data[10] = 32'd0;
        save_data[11] = 32'd0;
        save_data[12] = 32'd0;
    end
    
    reg [2:0] state;

    wire [31:0] float_in_0;
    wire [31:0] float_in_1;
    wire [31:0] float_in_2;
    wire [31:0] float_in_3;
    wire [31:0] float_in_4;
    wire [31:0] float_in_5;
    wire [31:0] float_in_6;
    wire [31:0] float_in_7;
    wire [31:0] float_in_8;
    wire [31:0] float_in_9;
    wire [31:0] float_in_10;
    wire [31:0] float_in_11;
    wire [31:0] float_in_12;

    wire [31:0] float_add_result_0;
    wire [31:0] float_add_result_1;
    wire [31:0] float_add_result_2;
    wire [31:0] float_add_result_3;
    wire [31:0] float_add_result_4;
    wire [31:0] float_add_result_5;
    wire [31:0] float_add_result_6;
    wire [31:0] float_add_result_7;
    wire [31:0] float_add_result_8;
    wire [31:0] float_add_result_9;
    wire [31:0] float_add_result_10;
    wire [31:0] float_add_result_11;
    wire [31:0] float_add_result_12;
    // fp32_adder 모듈 인스턴스화
    fp32_adder adder0 (
        .a(float_in_0),
        .b(float_data[0]),
        .result(float_add_result_0)
    );
    fp32_adder adder1 (
        .a(float_in_1),
        .b(float_data[1]),
        .result(float_add_result_1)
    );
    fp32_adder adder2 (
        .a(float_in_2),
        .b(float_data[2]),
        .result(float_add_result_2)
    );
    fp32_adder adder3 (
        .a(float_in_3),
        .b(float_data[3]),
        .result(float_add_result_3)
    );
    fp32_adder adder4 (
        .a(float_in_4),
        .b(float_data[4]),
        .result(float_add_result_4)
    );
    fp32_adder adder5 (
        .a(float_in_5),
        .b(float_data[5]),
        .result(float_add_result_5)
    );
    fp32_adder adder6 (
        .a(float_in_6),
        .b(float_data[6]),
        .result(float_add_result_6)
    );
    fp32_adder adder7 (
        .a(float_in_7),
        .b(float_data[7]),
        .result(float_add_result_7)
    );
    fp32_adder adder8 (
        .a(float_in_8),
        .b(float_data[8]),
        .result(float_add_result_8)
    );
    fp32_adder adder9 (
        .a(float_in_9),
        .b(float_data[9]),
        .result(float_add_result_9)
    );
    fp32_adder adder10 (
        .a(float_in_10),
        .b(float_data[10]),
        .result(float_add_result_10)
    );
    fp32_adder adder11 (
        .a(float_in_11),
        .b(float_data[11]),
        .result(float_add_result_11)
    );
    fp32_adder adder12 (
        .a(float_in_12),
        .b(float_data[12]),
        .result(float_add_result_12)
    );
    

    always @(posedge clk) begin
        if (cps == 0) begin
            // Module Input Section
            bram_addr <= 0;         // Bram 주소 초기화
            bram_we <= 0;           // Bram 쓰기 비활성화
            bram_ena <= 0;          // Bram 비활성화

            // Module Local Variables
            // lfsr <= 10'b1010101010;
            // lfsr <= 11'b10101010101; // 11비트 초기값
            lfsr <= {lfsr[9:0], lfsr[10] ^ lfsr[7]}; // 11비트 LFSR로 변경 (이전 변경 값을 가져다 씀)
            count <= 0;
            prev_cps <= 0;

            mem_count <= 0;
            mem_control_state <= 0;

        end else begin
            // cps가 변경되었을 경우 재시작
            if (cps != prev_cps) begin
                // Module Input Section
                bram_addr <= 0;         // Bram 주소 초기화
                bram_we <= 0;           // Bram 쓰기 비활성화
                bram_ena <= 1;          // Bram 활성화

                // Module Local Variables
                // lfsr <= 10'b1010101010;
                // lfsr <= 11'b10101010101; // 11비트 초기값
                lfsr <= {lfsr[9:0], lfsr[10] ^ lfsr[7]}; // 11비트 LFSR로 변경 (이전 변경 값을 가져다 씀)

                count <= 0;
                prev_cps <= cps;

                mem_count <= 0;
                mem_gam_count <= 0;     // 감마의 경우 2배
                mem_control_state <= 0;

            end else if (count < cps) begin
                case (mem_control_state)
                    0: begin
                        // 읽기 상태: Bram에서 데이터 읽기
                        // Module Input Section
                        // bram_addr <= lfsr * 4 + mem_count * 4; // 주소 설정 [0]
                        bram_addr <= mem_count * 4; // 주소 설정 [0]
                        bram_we <= 0;               // Bram 쓰기 비활성화
                        bram_ena <= 1;              // Bram 활성화
                        // Module Local Variables
                        mem_count <= mem_count + 1; // 다음 인덱스로 이동
                        mem_control_state <= 1; // 다음 상태로 전환
                    end

                    1: begin
                        // 저장 상태: Bram에서 읽은 데이터 저장
                        // bram_addr <= lfsr * 4 + mem_count * 4; // 주소 설정 [1]
                        bram_addr <= mem_count * 4; // 주소 설정 [1]
                        bram_we <= 0;               // Bram 쓰기 비활성화
                        bram_ena <= 1;              // Bram 활성화

                        // Module Local Variables
                        save_data[mem_count] <= bram_data_out; // 데이터 입력

                        if (mem_count < 13) begin
                            mem_count <= mem_count + 1; // 다음 인덱스로 이동
                        end else begin
                            mem_control_state <= 2; // 다음 상태로 전환
                            mem_count <= 0; // 인덱스 초기화
                        end
                    end

                    2: begin
                        // 계산 상태: 저장된 데이터와 Neutron Pulse Data Table의 데이터 더하기
                        save_data[0] <= float_add_result_0;
                        save_data[1] <= float_add_result_1;
                        save_data[2] <= float_add_result_2;
                        save_data[3] <= float_add_result_3;
                        save_data[4] <= float_add_result_4;
                        save_data[5] <= float_add_result_5;
                        save_data[6] <= float_add_result_6;
                        save_data[7] <= float_add_result_7;
                        save_data[8] <= float_add_result_8;
                        save_data[9] <= float_add_result_9;
                        save_data[10] <= float_add_result_10;
                        save_data[11] <= float_add_result_11;
                        save_data[12] <= float_add_result_12;
                        mem_control_state <= 3; // 다음 상태로 전환
                    end

                    3: begin
                        // 쓰기 상태: 계산된 데이터를 Bram에 쓰기
                        // bram_addr <= lfsr * 4 + mem_count * 4; // 주소 설정 [1]
                        bram_addr <= mem_count * 4; // 주소 설정 [1]
                        bram_we <= 1;               // Bram 쓰기 활성화
                        bram_ena <= 1;              // Bram 활성화
                        // Module Local Variables
                        bram_data_in <= save_data[mem_count]; // 저장된 데이터 쓰기

                        if (mem_count < 13) begin
                            mem_count <= mem_count + 1; // 다음 인덱스로 이동
                        end else begin
                            mem_count <= 0; // 인덱스 초기화
                            mem_control_state <= 4; // 다음 상태로 전환
                        end
                    end

                    4: begin
                        // 완료 상태: 모든 작업 완료 후 초기화
                        bram_we <= 0;               // Bram 쓰기 비활성화
                        bram_ena <= 0;              // Bram 비활성화

                        lfsr <= {lfsr[9:0], lfsr[10] ^ lfsr[7]}; // 11비트 LFSR로 변경 (이전 변경 값을 가져다 씀)

                        count <= count + 1;         // CPS 카운트 증가
                        // if (mem_gam_count == 1) begin
                        //     count <= count + 1;         // CPS 카운트 증가
                        //     mem_gam_count <= 0;
                        // end else begin
                        //     mem_gam_count <= mem_gam_count + 1;
                        // end
                        
                        mem_control_state <= 0;     // 상태 초기화
                    end
                endcase
            end
        end
    end
endmodule


module tb_PulseGenSpeedGam();

    // Inputs
    reg clk;
    reg [31:0] cps;

    // Outputs
    wire [31:0] bram_addr;
    wire [31:0] bram_data_in;
    wire bram_we;
    wire bram_ena;

    wire [31:0] bram_data_out;

    // Instantiate the Unit Under Test (UUT)
    PulseGenSpeedGam uut (
        .clk(clk),
        .cps(cps),
        .bram_addr(bram_addr),
        .bram_data_in(bram_data_in),
        .bram_we(bram_we),
        .bram_ena(bram_ena),
        .bram_data_out(bram_data_out)
    );

    bram pulse_bram_inst (
        .clka(clk),
        .ena(bram_ena),
        .wea(bram_we),
        .addra(bram_addr),
        .dina(bram_data_in),
        .douta(bram_data_out)
    );

    // Clock generation: 10ns period
    always #5 clk = ~clk;

    initial begin
        $dumpfile("Verilog_file/PulseGenSpeed/PulseGenSpeedGam.vcd");
        $dumpvars(0, tb_PulseGenSpeedGam);
        // Initialize inputs
        clk = 0;
        cps = 0;

        // Wait for global reset
        #20;

        // Test 1: cps = 0 → 모듈 초기화 상태 유지
        cps = 0;
        #50;

        // Test 2: cps = 10 → 10개의 pulse 발생
        cps = 1;
        #500;

        cps = 0;
        #50

        // Test 2: cps = 10 → 10개의 pulse 발생
        cps = 1;
        #500;

        cps = 0;
        #50

        // // Test 2: cps = 10 → 10개의 pulse 발생
        // cps = 1;
        // #1000;

        // // Test 3: cps = 5 → 다시 시작됨 (변경된 cps 값)
        // cps = 5;
        // #500;

        // // Test 4: cps = 0 → 종료
        // cps = 0;
        // #100;

        $finish;
    end

endmodule

Verilog_file/PulseGenSpeed(폐기)/PulseGenSpeedGam.vcd
$date
	Mon Aug 04 22:10:26 2025
$end
$version
	Icarus Verilog
$end
$timescale
	1ps
$end
$scope module tb_PulseGenSpeedGam $end
$var wire 1 ! bram_we $end
$var wire 1 " bram_ena $end
$var wire 32 # bram_data_out [31:0] $end
$var wire 32 $ bram_data_in [31:0] $end
$var wire 32 % bram_addr [31:0] $end
$var reg 1 & clk $end
$var reg 32 ' cps [31:0] $end
$scope module pulse_bram_inst $end
$var wire 1 & clka $end
$var wire 1 ! wea $end
$var wire 1 " ena $end
$var wire 32 ( dina [31:0] $end
$var wire 32 ) addra [31:0] $end
$var wire 13 * addr_index [12:0] $end
$var reg 32 + douta [31:0] $end
$var reg 32 , mem1 [31:0] $end
$var reg 32 - mem10 [31:0] $end
$var reg 32 . mem11 [31:0] $end
$var reg 32 / mem2 [31:0] $end
$var reg 32 0 mem3 [31:0] $end
$var reg 32 1 mem4 [31:0] $end
$var reg 32 2 mem5 [31:0] $end
$var reg 32 3 mem6 [31:0] $end
$var reg 32 4 mem7 [31:0] $end
$var reg 32 5 mem8 [31:0] $end
$var reg 32 6 mem9 [31:0] $end
$var integer 32 7 i [31:0] $end
$upscope $end
$scope module uut $end
$var wire 32 8 bram_data_out [31:0] $end
$var wire 1 & clk $end
$var wire 32 9 cps [31:0] $end
$var wire 32 : float_in_0 [31:0] $end
$var wire 32 ; float_in_1 [31:0] $end
$var wire 32 < float_in_10 [31:0] $end
$var wire 32 = float_in_11 [31:0] $end
$var wire 32 > float_in_12 [31:0] $end
$var wire 32 ? float_in_2 [31:0] $end
$var wire 32 @ float_in_3 [31:0] $end
$var wire 32 A float_in_4 [31:0] $end
$var wire 32 B float_in_5 [31:0] $end
$var wire 32 C float_in_6 [31:0] $end
$var wire 32 D float_in_7 [31:0] $end
$var wire 32 E float_in_8 [31:0] $end
$var wire 32 F float_in_9 [31:0] $end
$var wire 32 G float_add_result_9 [31:0] $end
$var wire 32 H float_add_result_8 [31:0] $end
$var wire 32 I float_add_result_7 [31:0] $end
$var wire 32 J float_add_result_6 [31:0] $end
$var wire 32 K float_add_result_5 [31:0] $end
$var wire 32 L float_add_result_4 [31:0] $end
$var wire 32 M float_add_result_3 [31:0] $end
$var wire 32 N float_add_result_2 [31:0] $end
$var wire 32 O float_add_result_12 [31:0] $end
$var wire 32 P float_add_result_11 [31:0] $end
$var wire 32 Q float_add_result_10 [31:0] $end
$var wire 32 R float_add_result_1 [31:0] $end
$var wire 32 S float_add_result_0 [31:0] $end
$var reg 32 T bram_addr [31:0] $end
$var reg 32 U bram_data_in [31:0] $end
$var reg 1 " bram_ena $end
$var reg 1 ! bram_we $end
$var reg 32 V count [31:0] $end
$var reg 11 W lfsr [10:0] $end
$var reg 4 X mem_control_state [3:0] $end
$var reg 32 Y mem_count [31:0] $end
$var reg 2 Z mem_gam_count [1:0] $end
$var reg 32 [ prev_cps [31:0] $end
$scope module adder0 $end
$var wire 32 \ a [31:0] $end
$var wire 32 ] b [31:0] $end
$var wire 1 ^ sign_b $end
$var wire 1 _ sign_a $end
$var wire 32 ` result [31:0] $end
$var wire 24 a mant_b [23:0] $end
$var wire 24 b mant_a [23:0] $end
$var wire 8 c exp_b [7:0] $end
$var wire 8 d exp_a [7:0] $end
$var reg 24 e aligned_a [23:0] $end
$var reg 24 f aligned_b [23:0] $end
$var reg 8 g exp_diff [7:0] $end
$var reg 8 h exp_res [7:0] $end
$var reg 23 i frac_res [22:0] $end
$var reg 25 j mant_sum [24:0] $end
$var reg 1 k sign_res $end
$upscope $end
$scope module adder1 $end
$var wire 32 l a [31:0] $end
$var wire 32 m b [31:0] $end
$var wire 1 n sign_b $end
$var wire 1 o sign_a $end
$var wire 32 p result [31:0] $end
$var wire 24 q mant_b [23:0] $end
$var wire 24 r mant_a [23:0] $end
$var wire 8 s exp_b [7:0] $end
$var wire 8 t exp_a [7:0] $end
$var reg 24 u aligned_a [23:0] $end
$var reg 24 v aligned_b [23:0] $end
$var reg 8 w exp_diff [7:0] $end
$var reg 8 x exp_res [7:0] $end
$var reg 23 y frac_res [22:0] $end
$var reg 25 z mant_sum [24:0] $end
$var reg 1 { sign_res $end
$upscope $end
$scope module adder10 $end
$var wire 32 | a [31:0] $end
$var wire 32 } b [31:0] $end
$var wire 1 ~ sign_b $end
$var wire 1 !" sign_a $end
$var wire 32 "" result [31:0] $end
$var wire 24 #" mant_b [23:0] $end
$var wire 24 $" mant_a [23:0] $end
$var wire 8 %" exp_b [7:0] $end
$var wire 8 &" exp_a [7:0] $end
$var reg 24 '" aligned_a [23:0] $end
$var reg 24 (" aligned_b [23:0] $end
$var reg 8 )" exp_diff [7:0] $end
$var reg 8 *" exp_res [7:0] $end
$var reg 23 +" frac_res [22:0] $end
$var reg 25 ," mant_sum [24:0] $end
$var reg 1 -" sign_res $end
$upscope $end
$scope module adder11 $end
$var wire 32 ." a [31:0] $end
$var wire 32 /" b [31:0] $end
$var wire 1 0" sign_b $end
$var wire 1 1" sign_a $end
$var wire 32 2" result [31:0] $end
$var wire 24 3" mant_b [23:0] $end
$var wire 24 4" mant_a [23:0] $end
$var wire 8 5" exp_b [7:0] $end
$var wire 8 6" exp_a [7:0] $end
$var reg 24 7" aligned_a [23:0] $end
$var reg 24 8" aligned_b [23:0] $end
$var reg 8 9" exp_diff [7:0] $end
$var reg 8 :" exp_res [7:0] $end
$var reg 23 ;" frac_res [22:0] $end
$var reg 25 <" mant_sum [24:0] $end
$var reg 1 =" sign_res $end
$upscope $end
$scope module adder12 $end
$var wire 32 >" a [31:0] $end
$var wire 32 ?" b [31:0] $end
$var wire 1 @" sign_b $end
$var wire 1 A" sign_a $end
$var wire 32 B" result [31:0] $end
$var wire 24 C" mant_b [23:0] $end
$var wire 24 D" mant_a [23:0] $end
$var wire 8 E" exp_b [7:0] $end
$var wire 8 F" exp_a [7:0] $end
$var reg 24 G" aligned_a [23:0] $end
$var reg 24 H" aligned_b [23:0] $end
$var reg 8 I" exp_diff [7:0] $end
$var reg 8 J" exp_res [7:0] $end
$var reg 23 K" frac_res [22:0] $end
$var reg 25 L" mant_sum [24:0] $end
$var reg 1 M" sign_res $end
$upscope $end
$scope module adder2 $end
$var wire 32 N" a [31:0] $end
$var wire 32 O" b [31:0] $end
$var wire 1 P" sign_b $end
$var wire 1 Q" sign_a $end
$var wire 32 R" result [31:0] $end
$var wire 24 S" mant_b [23:0] $end
$var wire 24 T" mant_a [23:0] $end
$var wire 8 U" exp_b [7:0] $end
$var wire 8 V" exp_a [7:0] $end
$var reg 24 W" aligned_a [23:0] $end
$var reg 24 X" aligned_b [23:0] $end
$var reg 8 Y" exp_diff [7:0] $end
$var reg 8 Z" exp_res [7:0] $end
$var reg 23 [" frac_res [22:0] $end
$var reg 25 \" mant_sum [24:0] $end
$var reg 1 ]" sign_res $end
$upscope $end
$scope module adder3 $end
$var wire 32 ^" a [31:0] $end
$var wire 32 _" b [31:0] $end
$var wire 1 `" sign_b $end
$var wire 1 a" sign_a $end
$var wire 32 b" result [31:0] $end
$var wire 24 c" mant_b [23:0] $end
$var wire 24 d" mant_a [23:0] $end
$var wire 8 e" exp_b [7:0] $end
$var wire 8 f" exp_a [7:0] $end
$var reg 24 g" aligned_a [23:0] $end
$var reg 24 h" aligned_b [23:0] $end
$var reg 8 i" exp_diff [7:0] $end
$var reg 8 j" exp_res [7:0] $end
$var reg 23 k" frac_res [22:0] $end
$var reg 25 l" mant_sum [24:0] $end
$var reg 1 m" sign_res $end
$upscope $end
$scope module adder4 $end
$var wire 32 n" a [31:0] $end
$var wire 32 o" b [31:0] $end
$var wire 1 p" sign_b $end
$var wire 1 q" sign_a $end
$var wire 32 r" result [31:0] $end
$var wire 24 s" mant_b [23:0] $end
$var wire 24 t" mant_a [23:0] $end
$var wire 8 u" exp_b [7:0] $end
$var wire 8 v" exp_a [7:0] $end
$var reg 24 w" aligned_a [23:0] $end
$var reg 24 x" aligned_b [23:0] $end
$var reg 8 y" exp_diff [7:0] $end
$var reg 8 z" exp_res [7:0] $end
$var reg 23 {" frac_res [22:0] $end
$var reg 25 |" mant_sum [24:0] $end
$var reg 1 }" sign_res $end
$upscope $end
$scope module adder5 $end
$var wire 32 ~" a [31:0] $end
$var wire 32 !# b [31:0] $end
$var wire 1 "# sign_b $end
$var wire 1 ## sign_a $end
$var wire 32 $# result [31:0] $end
$var wire 24 %# mant_b [23:0] $end
$var wire 24 &# mant_a [23:0] $end
$var wire 8 '# exp_b [7:0] $end
$var wire 8 (# exp_a [7:0] $end
$var reg 24 )# aligned_a [23:0] $end
$var reg 24 *# aligned_b [23:0] $end
$var reg 8 +# exp_diff [7:0] $end
$var reg 8 ,# exp_res [7:0] $end
$var reg 23 -# frac_res [22:0] $end
$var reg 25 .# mant_sum [24:0] $end
$var reg 1 /# sign_res $end
$upscope $end
$scope module adder6 $end
$var wire 32 0# a [31:0] $end
$var wire 32 1# b [31:0] $end
$var wire 1 2# sign_b $end
$var wire 1 3# sign_a $end
$var wire 32 4# result [31:0] $end
$var wire 24 5# mant_b [23:0] $end
$var wire 24 6# mant_a [23:0] $end
$var wire 8 7# exp_b [7:0] $end
$var wire 8 8# exp_a [7:0] $end
$var reg 24 9# aligned_a [23:0] $end
$var reg 24 :# aligned_b [23:0] $end
$var reg 8 ;# exp_diff [7:0] $end
$var reg 8 <# exp_res [7:0] $end
$var reg 23 =# frac_res [22:0] $end
$var reg 25 ># mant_sum [24:0] $end
$var reg 1 ?# sign_res $end
$upscope $end
$scope module adder7 $end
$var wire 32 @# a [31:0] $end
$var wire 32 A# b [31:0] $end
$var wire 1 B# sign_b $end
$var wire 1 C# sign_a $end
$var wire 32 D# result [31:0] $end
$var wire 24 E# mant_b [23:0] $end
$var wire 24 F# mant_a [23:0] $end
$var wire 8 G# exp_b [7:0] $end
$var wire 8 H# exp_a [7:0] $end
$var reg 24 I# aligned_a [23:0] $end
$var reg 24 J# aligned_b [23:0] $end
$var reg 8 K# exp_diff [7:0] $end
$var reg 8 L# exp_res [7:0] $end
$var reg 23 M# frac_res [22:0] $end
$var reg 25 N# mant_sum [24:0] $end
$var reg 1 O# sign_res $end
$upscope $end
$scope module adder8 $end
$var wire 32 P# a [31:0] $end
$var wire 32 Q# b [31:0] $end
$var wire 1 R# sign_b $end
$var wire 1 S# sign_a $end
$var wire 32 T# result [31:0] $end
$var wire 24 U# mant_b [23:0] $end
$var wire 24 V# mant_a [23:0] $end
$var wire 8 W# exp_b [7:0] $end
$var wire 8 X# exp_a [7:0] $end
$var reg 24 Y# aligned_a [23:0] $end
$var reg 24 Z# aligned_b [23:0] $end
$var reg 8 [# exp_diff [7:0] $end
$var reg 8 \# exp_res [7:0] $end
$var reg 23 ]# frac_res [22:0] $end
$var reg 25 ^# mant_sum [24:0] $end
$var reg 1 _# sign_res $end
$upscope $end
$scope module adder9 $end
$var wire 32 `# a [31:0] $end
$var wire 32 a# b [31:0] $end
$var wire 1 b# sign_b $end
$var wire 1 c# sign_a $end
$var wire 32 d# result [31:0] $end
$var wire 24 e# mant_b [23:0] $end
$var wire 24 f# mant_a [23:0] $end
$var wire 8 g# exp_b [7:0] $end
$var wire 8 h# exp_a [7:0] $end
$var reg 24 i# aligned_a [23:0] $end
$var reg 24 j# aligned_b [23:0] $end
$var reg 8 k# exp_diff [7:0] $end
$var reg 8 l# exp_res [7:0] $end
$var reg 23 m# frac_res [22:0] $end
$var reg 25 n# mant_sum [24:0] $end
$var reg 1 o# sign_res $end
$upscope $end
$upscope $end
$upscope $end
$enddefinitions $end
$comment Show the parameter values. $end
$dumpall
$end
#0
$dumpvars
0o#
b0 n#
b0 m#
b1110100 l#
bx k#
b100111010100100101010010 j#
bx i#
bz h#
b1110100 g#
bxzzzzzzzzzzzzzzzzzzzzzzz f#
b100111010100100101010010 e#
b111010000000000000000000000000 d#
zc#
0b#
b111010000111010100100101010010 a#
bz `#
0_#
b0 ^#
b0 ]#
b1110101 \#
bx [#
b101010100110010011000011 Z#
bx Y#
bz X#
b1110101 W#
bxzzzzzzzzzzzzzzzzzzzzzzz V#
b101010100110010011000011 U#
b111010100000000000000000000000 T#
zS#
0R#
b111010101010100110010011000011 Q#
bz P#
0O#
b0 N#
b0 M#
b1110110 L#
bx K#
b101111100000110111101101 J#
bx I#
bz H#
b1110110 G#
bxzzzzzzzzzzzzzzzzzzzzzzz F#
b101111100000110111101101 E#
b111011000000000000000000000000 D#
zC#
0B#
b111011001111100000110111101101 A#
bz @#
0?#
b0 >#
b0 =#
b1110111 <#
bx ;#
b110011100111000000111011 :#
bx 9#
bz 8#
b1110111 7#
bxzzzzzzzzzzzzzzzzzzzzzzz 6#
b110011100111000000111011 5#
b111011100000000000000000000000 4#
z3#
02#
b111011110011100111000000111011 1#
bz 0#
0/#
b0 .#
b0 -#
b1111000 ,#
bx +#
b110111101101001010001001 *#
bx )#
bz (#
b1111000 '#
bxzzzzzzzzzzzzzzzzzzzzzzz &#
b110111101101001010001001 %#
b111100000000000000000000000000 $#
z##
0"#
b111100010111101101001010001001 !#
bz ~"
0}"
b0 |"
b0 {"
b1111001 z"
bx y"
b111100011010100111111100 x"
bx w"
bz v"
b1111001 u"
bxzzzzzzzzzzzzzzzzzzzzzzz t"
b111100011010100111111100 s"
b111100100000000000000000000000 r"
zq"
0p"
b111100111100011010100111111100 o"
bz n"
0m"
b0 l"
b0 k"
b1111011 j"
bx i"
b100000110001001001101111 h"
bx g"
bz f"
b1111011 e"
bxzzzzzzzzzzzzzzzzzzzzzzz d"
b100000110001001001101111 c"
b111101100000000000000000000000 b"
za"
0`"
b111101100000110001001001101111 _"
bz ^"
0]"
b0 \"
b0 ["
b1111100 Z"
bx Y"
b100011100011101111001101 X"
bx W"
bz V"
b1111100 U"
bxzzzzzzzzzzzzzzzzzzzzzzz T"
b100011100011101111001101 S"
b111110000000000000000000000000 R"
zQ"
0P"
b111110000011100011101111001101 O"
bz N"
0M"
b0 L"
b0 K"
b1110001 J"
bx I"
b110100011011011100010111 H"
bx G"
bz F"
b1110001 E"
bxzzzzzzzzzzzzzzzzzzzzzzz D"
b110100011011011100010111 C"
b111000100000000000000000000000 B"
zA"
0@"
b111000110100011011011100010111 ?"
bz >"
0="
b0 <"
b0 ;"
b1110001 :"
bx 9"
b110100011011011100010111 8"
bx 7"
bz 6"
b1110001 5"
bxzzzzzzzzzzzzzzzzzzzzzzz 4"
b110100011011011100010111 3"
b111000100000000000000000000000 2"
z1"
00"
b111000110100011011011100010111 /"
bz ."
0-"
b0 ,"
b0 +"
b1110011 *"
bx )"
b100111010100100101010010 ("
bx '"
bz &"
b1110011 %"
bxzzzzzzzzzzzzzzzzzzzzzzz $"
b100111010100100101010010 #"
b111001100000000000000000000000 ""
z!"
0~
b111001100111010100100101010010 }
bz |
0{
b0 z
b0 y
b1111101 x
bx w
b100110010110010100101100 v
bx u
bz t
b1111101 s
bxzzzzzzzzzzzzzzzzzzzzzzz r
b100110010110010100101100 q
b111110100000000000000000000000 p
zo
0n
b111110100110010110010100101100 m
bz l
0k
b0 j
b0 i
b1111010 h
bx g
b111111000101000001001000 f
bx e
bz d
b1111010 c
bxzzzzzzzzzzzzzzzzzzzzzzz b
b111111000101000001001000 a
b111101000000000000000000000000 `
z_
0^
b111101011111000101000001001000 ]
bz \
b0 [
b0 Z
b0 Y
b0 X
b10101010101 W
b0 V
bx U
bx T
b111101000000000000000000000000 S
b111110100000000000000000000000 R
b111001100000000000000000000000 Q
b111000100000000000000000000000 P
b111000100000000000000000000000 O
b111110000000000000000000000000 N
b111101100000000000000000000000 M
b111100100000000000000000000000 L
b111100000000000000000000000000 K
b111011100000000000000000000000 J
b111011000000000000000000000000 I
b111010100000000000000000000000 H
b111010000000000000000000000000 G
bz F
bz E
bz D
bz C
bz B
bz A
bz @
bz ?
bz >
bz =
bz <
bz ;
bz :
b0 9
bx 8
b1111101000000 7
bx 6
bx 5
bx 4
bx 3
bx 2
bx 1
bx 0
bx /
bx .
bx -
bx ,
bx +
bx *
bx )
bx (
b0 '
0&
bx %
bx $
bx #
x"
x!
$end
#5000
b0 *
b1010101011 W
0"
0!
b0 %
b0 )
b0 T
1&
#10000
0&
#15000
b10101010111 W
1&
#20000
0&
#25000
b1010101111 W
1&
#30000
0&
#35000
b10101011111 W
1&
#40000
0&
#45000
b1010111111 W
1&
#50000
0&
#55000
b10101111111 W
1&
#60000
0&
#65000
b1011111111 W
1&
#70000
0&
b1 '
b1 9
#75000
b1 [
b10111111111 W
1"
1&
#80000
0&
#85000
b1 X
b1 Y
b0 .
b0 -
b0 6
b0 5
b0 4
b0 3
b0 2
b0 1
b0 0
b0 /
b0 ,
b0 #
b0 +
b0 8
1&
#90000
0&
#95000
b100 *
b10 Y
b100 %
b100 )
b100 T
1&
#100000
0&
#105000
b1000 *
b11 Y
b1000 %
b1000 )
b1000 T
1&
#110000
0&
#115000
b1100 *
b100 Y
b1100 %
b1100 )
b1100 T
1&
#120000
0&
