Verilog_file/BRAM_Model.v
module bram(
    input  wire            clka,
    input  wire            ena,
    input  wire            wea,
    input  wire  [31:0]    addra,
    input  wire  [31:0]    dina,
    output reg   [31:0]    douta
);

    reg [31:0] mem [0:7999];
    reg [31:0] mem1;
    reg [31:0] mem2;
    reg [31:0] mem3;
    reg [31:0] mem4;
    reg [31:0] mem5;
    reg [31:0] mem6;
    reg [31:0] mem7;
    reg [31:0] mem8;
    reg [31:0] mem9;
    reg [31:0] mem10;
    reg [31:0] mem11;

    // 13비트 주소 인덱스 (0~8191까지 가능, 실제는 0~7999만 사용)
    wire [12:0] addr_index = addra[12:0];

    integer i;

    // 초기화 블록 (시뮬레이션용)
    initial begin
        for (i = 0; i <= 7999; i = i + 1) begin
            mem[i] = 32'd0;
        end
    end

    // 동기식 동작 (읽기/쓰기)
    always @(posedge clka) begin
        if (ena) begin
            if (wea != 1'b0) begin
                mem[addr_index] = dina;
            end
            douta <= mem[addr_index];

            // 디버깅용 특정 위치 레지스터 저장
            mem1 <= mem[0];
            mem2 <= mem[4];
            mem3 <= mem[8];
            mem4 <= mem[12];
            mem5 <= mem[16];
            mem6 <= mem[20];
            mem7 <= mem[24];
            mem8 <= mem[28];
            mem9 <= mem[32];
            mem10 <= mem[36];
            mem11 <= mem[40];

            // 디버깅 출력
            // $display("[READ ] MEM[%0d] [0x%08X] => 0x%08X", addr_index, dina, mem[addr_index]);
        end
    end

endmodule

Verilog_file/BRAMDumpData.v
`timescale 1ns / 1ps
`include "./Verilog_file/BRAM_Model.v"

module BRAMDumpData (
    input wire clk,
    input wire [31:0] cps,
    output reg [31:0] bram_addr,
    output reg [31:0] bram_data_in,
    output reg bram_we,
    output reg ena_pin,
    input wire [31:0] bram_data_out
);

    reg [31:0] save_data [0:9];
    initial begin
        save_data[0] = 32'd0;
        save_data[1] = 32'd0;
        save_data[2] = 32'd0;
        save_data[3] = 32'd0;
        save_data[4] = 32'd0;
        save_data[5] = 32'd0;
        save_data[6] = 32'd0;
        save_data[7] = 32'd0;
        save_data[8] = 32'd0;
        save_data[9] = 32'd0;
    end

    reg [2:0] state;
    // localparam READ = 2'd0, CALC = 2'd1, WRITE = 2'd2, DONE = 2'd3;

    reg [3:0] index;

    reg [31:0] prev_cps = 0;
    reg [31:0] count = 0;

    reg [31:0] mem_val = 0;

    always @(posedge clk) begin
        if (cps == 0) begin
            prev_cps <= 0;          // cps가 0이면 이전 값을 초기화
            count <= 0;             // 카운트 초기화 (cps 요구사항 도달 용)

            ena_pin <= 0;           // Bram 비활성화
            bram_we <= 0;           // Bram 쓰기 비활성화
            state <= 0;             // 초기 상태
            index <= 0;             // save_data 인덱스 초기화
        end else begin
            // cps가 변경되면 상태 머신 작동
            if (cps != prev_cps) begin
                prev_cps <= cps;    // 이전 cps 값 저장
                count <= 0;         // 카운트 초기화 (cps 요구사항 도달 용)

                ena_pin <= 1;       // Bram 활성화
                bram_we <= 0;       // Bram 쓰기 비활성화
                state <= 0;         // 초기 상태

                bram_addr <= 0;     // Bram 0번 주소 읽기 요청
                index <= 0;         // 인덱스 초기화
            end else if (count < cps) begin
                case (state)
                    0: begin
                        // 읽기 상태: Bram에서 데이터 읽기
                        ena_pin <= 1;                   // Bram 활성화
                        bram_we <= 0;                   // Bram 쓰기 비활성화
                        bram_addr <= index * 4;   // 다음 주소 읽기 요청 (1번 주소)
                        index <= index + 1; // 다음 인덱스로 이동
                        state <= 1; // 다음 상태로 전환
                    end

                    1: begin
                        // 읽기 상태: Bram에서 데이터 읽기
                        ena_pin <= 1;                   // Bram 활성화
                        bram_we <= 0;                   // Bram 쓰기 비활성화
                        bram_addr <= index * 4;   // 다음 주소 읽기 요청 (1번 주소)

                        save_data[index] <= bram_data_out; // 데이터 저장 (0번 주소)
                        mem_val <= bram_data_out; // 읽은 데이터 저장

                        if (index < 10) begin
                            index <= index + 1; // 다음 인덱스로 이동
                        end else begin
                            state <= 2; // 다음 상태로 전환
                            index <= 0; // 인덱스 초기화
                        end
                    end

                    2: begin
                        // 계산 상태: 예시로 각 데이터를 증가시키는 연산 수행
                        save_data[0] <= save_data[0] + 1;
                        save_data[1] <= save_data[1] + 2;
                        save_data[2] <= save_data[2] + 3;
                        save_data[3] <= save_data[3] + 4;
                        save_data[4] <= save_data[4] + 5;
                        save_data[5] <= save_data[5] + 6;
                        save_data[6] <= save_data[6] + 7;
                        save_data[7] <= save_data[7] + 8;
                        save_data[8] <= save_data[8] + 9;
                        save_data[9] <= save_data[9] + 10;
                        state <= 3; // 다음 상태로 전환
                    end

                    3: begin
                        // 쓰기 상태: 계산된 데이터를 Bram에 쓰기
                        ena_pin <= 1;                   // Bram 활성화
                        bram_we <= 1;                   // Bram 쓰기 활성화
                        bram_addr <= index * 4;         // 현재 인덱스 주소로 쓰기 요청
                        bram_data_in <= save_data[index]; // 저장된 데이터 쓰기

                        if (index < 10) begin
                            index <= index + 1; // 다음 인덱스로 이동
                        end else begin
                            state <= 4; // 다음 상태로 전환
                            index <= 0; // 인덱스 초기화
                        end
                    end

                    4: begin
                        // 완료 상태: 모든 작업이 완료되었음을 나타냄
                        ena_pin <= 0;                   // Bram 비활성화
                        bram_we <= 0;                   // Bram 쓰기 비활성화
                        state <= 0;                     // 상태 초기화
                        count <= count + 1;             // 카운트 증가
                    end
                endcase
            end
        end
    end
endmodule



module BRAMDumpData_tb;

    // 클럭 및 제어 신호
    reg clk;
    reg [31:0] cps;
    wire [31:0] bram_addr;
    wire [31:0] bram_data_in;
    wire [31:0] bram_data_out;
    wire bram_we;
    wire ena_pin;

    // BRAM 인스턴스
    BRAMDumpData uut (
        .clk(clk),
        .cps(cps),
        .bram_addr(bram_addr),
        .bram_data_in(bram_data_in),
        .bram_we(bram_we),
        .ena_pin(ena_pin),
        .bram_data_out(bram_data_out)
    );
    // BRAM 모델 인스턴스
    bram pin_bram_inst (
        .clka(clk),
        .ena(ena_pin),
        .wea(bram_we),
        .addra(bram_addr),
        .dina(bram_data_in),
        .douta(bram_data_out)  // Read output not used in this test
    );

      // Clock generation: 10ns period
    always #5 clk = ~clk;

    // 시뮬레이션 초기화 및 종료
    initial begin
        $dumpfile("Verilog_file/BRAMDumpData.vcd");
        $dumpvars(0, BRAMDumpData_tb);

        // 초기화
        clk = 0;
        cps = 0;
        #10;
        // Test 2: cps = 10 → 10개의 pulse 발생
        cps = 1;
        #500;
        cps = 0;
        #10;
        // Test 2: cps = 10 → 10개의 pulse 발생
        cps = 1;
        #500;

        $finish;
    end

endmodule

Verilog_file/BRAMDumpData.vcd
$date
	Mon Aug 04 01:39:49 2025
$end
$version
	Icarus Verilog
$end
$timescale
	1ps
$end
$scope module BRAMDumpData_tb $end
$var wire 1 ! ena_pin $end
$var wire 1 " bram_we $end
$var wire 32 # bram_data_out [31:0] $end
$var wire 32 $ bram_data_in [31:0] $end
$var wire 32 % bram_addr [31:0] $end
$var reg 1 & clk $end
$var reg 32 ' cps [31:0] $end
$scope module pin_bram_inst $end
$var wire 1 & clka $end
$var wire 1 " wea $end
$var wire 1 ! ena $end
$var wire 32 ( dina [31:0] $end
$var wire 32 ) addra [31:0] $end
$var wire 13 * addr_index [12:0] $end
$var reg 32 + douta [31:0] $end
$var reg 32 , mem1 [31:0] $end
$var reg 32 - mem10 [31:0] $end
$var reg 32 . mem11 [31:0] $end
$var reg 32 / mem2 [31:0] $end
$var reg 32 0 mem3 [31:0] $end
$var reg 32 1 mem4 [31:0] $end
$var reg 32 2 mem5 [31:0] $end
$var reg 32 3 mem6 [31:0] $end
$var reg 32 4 mem7 [31:0] $end
$var reg 32 5 mem8 [31:0] $end
$var reg 32 6 mem9 [31:0] $end
$var integer 32 7 i [31:0] $end
$upscope $end
$scope module uut $end
$var wire 32 8 bram_data_out [31:0] $end
$var wire 1 & clk $end
$var wire 32 9 cps [31:0] $end
$var reg 32 : bram_addr [31:0] $end
$var reg 32 ; bram_data_in [31:0] $end
$var reg 1 " bram_we $end
$var reg 32 < count [31:0] $end
$var reg 1 ! ena_pin $end
$var reg 4 = index [3:0] $end
$var reg 32 > mem_val [31:0] $end
$var reg 32 ? prev_cps [31:0] $end
$var reg 3 @ state [2:0] $end
$upscope $end
$upscope $end
$enddefinitions $end
$comment Show the parameter values. $end
$dumpall
$end
#0
$dumpvars
bx @
b0 ?
b0 >
bx =
b0 <
bx ;
bx :
b0 9
bx 8
b1111101000000 7
bx 6
bx 5
bx 4
bx 3
bx 2
bx 1
bx 0
bx /
bx .
bx -
bx ,
bx +
bx *
bx )
bx (
b0 '
0&
bx %
bx $
bx #
x"
x!
$end
#5000
b0 =
b0 @
0"
0!
1&
#10000
0&
b1 '
b1 9
#15000
b0 *
b0 %
b0 )
b0 :
1!
b1 ?
1&
#20000
0&
#25000
b1 @
b1 =
b0 .
b0 -
b0 6
b0 5
b0 4
b0 3
b0 2
b0 1
b0 0
b0 /
b0 ,
b0 #
b0 +
b0 8
1&
#30000
0&
#35000
b100 *
b10 =
b100 %
b100 )
b100 :
1&
#40000
0&
#45000
b1000 *
b11 =
b1000 %
b1000 )
b1000 :
1&
#50000
0&
#55000
b1100 *
b100 =
b1100 %
b1100 )
b1100 :
1&
#60000
0&
#65000
b10000 *
b101 =
b10000 %
b10000 )
b10000 :
1&
#70000
0&
#75000
b10100 *
b110 =
b10100 %
b10100 )
b10100 :
1&
#80000
0&
#85000
b11000 *
b111 =
b11000 %
b11000 )
b11000 :
1&
#90000
0&
#95000
b11100 *
b1000 =
b11100 %
b11100 )
b11100 :
1&
#100000
0&
#105000
b100000 *
b1001 =
b100000 %
b100000 )
b100000 :
1&
#110000
0&
#115000
b100100 *
b1010 =
b100100 %
b100100 )
b100100 :
1&
#120000
0&
#125000
b101000 *
b0 =
b10 @
b101000 %
b101000 )
b101000 :
1&
#130000
0&
#135000
b11 @
1&
#140000
0&
#145000
b0 *
b1 =
b1 $
b1 (
b1 ;
b0 %
b0 )
b0 :
1"
1&
#150000
0&
#155000
b100 *
b1 ,
b1 #
b1 +
b1 8
b10 =
b10 $
b10 (
b10 ;
b100 %
b100 )
b100 :
1&
#160000
0&
#165000
b1000 *
b11 =
b11 $
b11 (
b11 ;
b1000 %
b1000 )
b1000 :
b10 /
b10 #
b10 +
b10 8
1&
#170000
0&
#175000
b1100 *
b11 0
b11 #
b11 +
b11 8
b100 =
b100 $
b100 (
b100 ;
b1100 %
b1100 )
b1100 :
1&
#180000
0&
#185000
b10000 *
b101 =
b101 $
b101 (
b101 ;
b10000 %
b10000 )
b10000 :
b100 1
b100 #
b100 +
b100 8
1&
#190000
0&
#195000
b10100 *
b101 2
b101 #
b101 +
b101 8
b110 =
b110 $
b110 (
b110 ;
b10100 %
b10100 )
b10100 :
1&
#200000
0&
#205000
b11000 *
b111 =
b111 $
b111 (
b111 ;
b11000 %
b11000 )
b11000 :
b110 3
b110 #
b110 +
b110 8
1&
#210000
0&
#215000
b11100 *
b111 4
b111 #
b111 +
b111 8
b1000 =
b1000 $
b1000 (
b1000 ;
b11100 %
b11100 )
b11100 :
1&
#220000
0&
#225000
b100000 *
b1001 =
b1001 $
b1001 (
b1001 ;
b100000 %
b100000 )
b100000 :
b1000 5
b1000 #
b1000 +
b1000 8
1&
#230000
0&
#235000
b100100 *
b1001 6
b1001 #
b1001 +
b1001 8
b1010 =
b1010 $
b1010 (
b1010 ;
b100100 %
b100100 )
b100100 :
1&
#240000
0&
#245000
b101000 *
b0 =
b100 @
bx $
bx (
bx ;
b101000 %
b101000 )
b101000 :
b1010 -
b1010 #
b1010 +
b1010 8
1&
#250000
0&
#255000
bx .
bx #
bx +
bx 8
b1 <
b0 @
0"
0!
1&
