Verilog_file/BRAM_Model.v
module bram(
    input  wire            clka,
    input  wire            ena,
    input  wire            wea,
    input  wire  [31:0]    addra,
    input  wire  [31:0]    dina,
    output reg   [31:0]    douta
);

    reg [31:0] mem [0:7999];
    reg [31:0] mem1;
    reg [31:0] mem2;
    reg [31:0] mem3;
    reg [31:0] mem4;
    reg [31:0] mem5;
    reg [31:0] mem6;

    // 13비트 주소 인덱스 (0~8191까지 가능, 실제는 0~7999만 사용)
    wire [12:0] addr_index = addra[12:0];

    integer i;

    // 초기화 블록 (시뮬레이션용)
    initial begin
        for (i = 0; i <= 7999; i = i + 1) begin
            mem[i] = 32'd0;
        end
    end

    // 동기식 동작 (읽기/쓰기)
    always @(posedge clka) begin
        if (ena) begin
            if (wea != 1'b0) begin
                mem[addr_index] = dina;
            end
            douta <= mem[addr_index];

            // 디버깅용 특정 위치 레지스터 저장
            mem1 <= mem[0];
            mem2 <= mem[4];
            mem3 <= mem[8];
            mem4 <= mem[12];
            mem5 <= mem[16];
            mem6 <= mem[20];

            // 디버깅 출력
            // $display("[READ ] MEM[%0d] [0x%08X] => 0x%08X", addr_index, dina, mem[addr_index]);
        end
    end

endmodule

Verilog_file/PulseGenFin/fp32_adder.v
module fp32_adder (
    input  [31:0] a,
    input  [31:0] b,
    output [31:0] result
);
    wire sign_a = a[31];
    wire sign_b = b[31];
    wire [7:0] exp_a = a[30:23];
    wire [7:0] exp_b = b[30:23];
    wire [23:0] mant_a = (exp_a == 0) ? {1'b0, a[22:0]} : {1'b1, a[22:0]};
    wire [23:0] mant_b = (exp_b == 0) ? {1'b0, b[22:0]} : {1'b1, b[22:0]};

    reg [7:0] exp_diff;
    reg [23:0] aligned_a, aligned_b;
    reg [7:0] exp_res;
    reg [24:0] mant_sum;
    reg sign_res;
    reg [22:0] frac_res;

    always @(*) begin
        // 지수 맞춤
        if (exp_a > exp_b) begin
            exp_diff = exp_a - exp_b;
            aligned_a = mant_a;
            aligned_b = mant_b >> exp_diff;
            exp_res = exp_a;
            sign_res = sign_a;
        end else begin
            exp_diff = exp_b - exp_a;
            aligned_a = mant_a >> exp_diff;
            aligned_b = mant_b;
            exp_res = exp_b;
            sign_res = sign_b;
        end

        // 같은 부호만 지원 (간단 버전)
        if (sign_a == sign_b) begin
            mant_sum = aligned_a + aligned_b;
            if (mant_sum[24]) begin
                mant_sum = mant_sum >> 1;
                exp_res = exp_res + 1;
            end
        end else begin
            // 부호 다르면 뺄셈인데, 여기선 간단히 무시
            mant_sum = 0;
        end

        frac_res = mant_sum[22:0];
    end

    assign result = {sign_res, exp_res, frac_res};
endmodule

Verilog_file/FinPulseGenNut.v
`timescale 1ns / 1ps
`include "./Verilog_file/BRAM_Model.v"
`include "./Verilog_file/fp32_adder.v"

module FinPulseGenNut(
    input wire clk,
    input wire [31:0] cps,
    output reg [31:0] bram_addr,
    output reg [31:0] bram_data_in,
    output reg bram_we_pin,
    output reg ena_pin,

    output reg [31:0] bram_addr_pulse,
    output reg [31:0] bram_data_in_pulse,
    output reg bram_we_pulse,
    output reg ena_pulse,

    output reg [1:0] finish_pulse_gen,

    input wire [31:0] bram_data_out_pulse
);
    // reg [9:0] lfsr = 10'b1010101010;  // 10비트 초기값
    reg [10:0] lfsr = 11'b10101010101;  // 11비트 초기값

    reg [31:0] count = 0;
    reg [31:0] prev_cps = 0;

    reg [31:0] mem_count = 0;

    reg [3:0] mem_control_state = 0;
    reg [31:0] prev_mem_val = 0;

    // Neutron Pulse Data Table
    reg [31:0] float_data [0:49];

    initial begin
        float_data[0] = 32'h3DA339C1; // 0.0797
        float_data[1] = 32'h3F59AD43; // 0.8503
        float_data[2] = 32'h3F73A29C; // 0.9517
        float_data[3] = 32'h3F652546; // 0.8951
        float_data[4] = 32'h3F4EC56D; // 0.8077
        float_data[5] = 32'h3F388CE7; // 0.7209
        float_data[6] = 32'h3F242C3D; // 0.6413
        float_data[7] = 32'h3F11EB85; // 0.57
        float_data[8] = 32'h3F01A9FC; // 0.5065
        float_data[9] = 32'h3EE67382; // 0.4501
        float_data[10] = 32'h3ECCBFB1; // 0.3999
        float_data[11] = 32'h3EB5F6FD; // 0.3554
        float_data[12] = 32'h3EA1B08A; // 0.3158
        float_data[13] = 32'h3E8FAACE; // 0.2806
        float_data[14] = 32'h3E7F4880; // 0.2493
        float_data[15] = 32'h3E62D0E5; // 0.2215
        float_data[16] = 32'h3E4985F0; // 0.1968
        float_data[17] = 32'h3E3318FC; // 0.1749
        float_data[18] = 32'h3E1F212D; // 0.1554
        float_data[19] = 32'h3E0D6A16; // 0.1381
        float_data[20] = 32'h3DFB4A23; // 0.1227
        float_data[21] = 32'h3DDF3B64; // 0.109
        float_data[22] = 32'h3DC67382; // 0.0969
        float_data[23] = 32'h3DB05532; // 0.0861
        float_data[24] = 32'h3D9CAC08; // 0.0765
        float_data[25] = 32'h3D8B4396; // 0.068
        float_data[26] = 32'h3D7765FE; // 0.0604
        float_data[27] = 32'h3D5B8BAC; // 0.0536
        float_data[28] = 32'h3D436113; // 0.0477
        float_data[29] = 32'h3D2DAB9F; // 0.0424
        float_data[30] = 32'h3D1A0275; // 0.0376
        float_data[31] = 32'h3D08CE70; // 0.0334
        float_data[32] = 32'h3CF34D6A; // 0.0297
        float_data[33] = 32'h3CD844D0; // 0.0264
        float_data[34] = 32'h3CC08312; // 0.0235
        float_data[35] = 32'h3CAA64C3; // 0.0208
        float_data[36] = 32'h3C978D50; // 0.0185
        float_data[37] = 32'h3C872B02; // 0.0165
        float_data[38] = 32'h3C6F34D7; // 0.0146
        float_data[39] = 32'h3C54FDF4; // 0.013
        float_data[40] = 32'h3C3C6A7F; // 0.0115
        float_data[41] = 32'h3C28C155; // 0.0103
        float_data[42] = 32'h3C15182B; // 0.0091
        float_data[43] = 32'h3C04B5DD; // 0.0081
        float_data[44] = 32'h3BEBEDFA; // 0.0072
        float_data[45] = 32'h3BD1B717; // 0.0064
        float_data[46] = 32'h3BBAC711; // 0.0057
        float_data[47] = 32'h3BA3D70A; // 0.005
        float_data[48] = 32'h3B9374BC; // 0.0045
        float_data[49] = 32'h3B83126F; // 0.004
    end

    wire [31:0] fp_add_result;
    reg [31:0] fp_table_input;

    fp32_adder adder_inst (
        .a(bram_data_out_pulse),
        .b(fp_table_input),         // IEEE 754
        .result(fp_add_result)
    );

    always @(posedge clk) begin
        if (cps == 0) begin
            bram_addr <= 0;
            // lfsr <= 10'b1010101010;
            // lfsr <= 11'b10101010101; // 11비트 초기값
            lfsr <= {lfsr[9:0], lfsr[10] ^ lfsr[7]}; // 11비트 LFSR로 변경 (이전 변경 값을 가져다 씀)
            count <= 0;
            prev_cps <= 0;
            bram_we_pin <= 0;
            ena_pin <= 0;

            bram_we_pulse <= 0;
            ena_pulse <= 0;
            bram_addr_pulse <= 0;

            mem_count <= 0;
            mem_control_state <= 0;

            finish_pulse_gen <= 2'b00; // 초기화 상태

        end else begin
            // cps가 변경되었을 경우 재시작
            if (cps != prev_cps) begin
                count <= 0;
                // lfsr <= 10'b1010101010;
                // lfsr <= 11'b10101010101; // 11비트 초기값
                lfsr <= {lfsr[9:0], lfsr[10] ^ lfsr[7]}; // 11비트 LFSR로 변경 (이전 변경 값을 가져다 씀)

                prev_cps <= cps;
                ena_pin <= 0;
                bram_we_pin <= 0;

                bram_we_pulse <= 0;
                ena_pulse <= 0;
                mem_count <= 0;
                mem_control_state <= 0;

                finish_pulse_gen <= 2'b01;

            end else if (count < cps) begin
                if (mem_count == 0) begin
                    // 10비트 LFSR: x^10 + x^7 + 1
                    // lfsr <= {lfsr[8:0], lfsr[9] ^ lfsr[6]};

                    lfsr <= {lfsr[9:0], lfsr[10] ^ lfsr[7]}; // 11비트 LFSR로 변경

                    bram_data_in <= 1;                    // 펄스 발생 시점 값
                    bram_addr <= 32'b100; // lfsr * 4;                // 0 ~ 1023 개 가능
                    // bram_addr <= lfsr * 4;                // 11비트 0 ~ 2047 개 가능

                    bram_data_in_pulse <= 1;              // 펄스 값
                    bram_addr_pulse <= 32'b100; //lfsr * 4;          // 0 ~ 1023 개 가능
                    // bram_addr_pulse <= lfsr * 4;                // 11비트 0 ~ 2047 개 가능

                    // Pin 메모리에 1 값 쓰기.
                    bram_we_pin <= 1;
                    ena_pin <= 1;
                    
                    // Pulse 메모리에 1 부터 증가하는 값 쓰기
                    bram_we_pulse <= 0;             // 펄스 읽기
                    ena_pulse <= 1;                 // 활성화
                    mem_count <= 1;                 // 메모리 카운트 증가

                    mem_control_state <= 1;

                end else begin
                    if (mem_count > 50) begin
                        // 메모리 카운트가 50 이상이면 펄스 종료
                        bram_we_pulse <= 0;             // 펄스 종료
                        ena_pulse <= 0;                 // 비활성화
                        mem_count <= 0;                 // 메모리 카운트 초기화

                        mem_control_state <= 0;         // BRAM 제어 상태 초기화

                        // Pin 메모리 정지
                        bram_we_pin <= 0;
                        ena_pin <= 0;
                        count <= count + 1;

                    end else begin
                        case (mem_control_state)
                            0: begin
                                bram_addr_pulse <= bram_addr_pulse + 4;
                                bram_we_pulse <= 0;     // 펄스 읽기
                                ena_pulse <= 1;
                                // 주소 유지
                                mem_control_state <= 1;
                            end
                            1: begin
                                // 대기 
                                bram_we_pulse <= 0;     // 펄스 읽기
                                ena_pulse <= 0;

                                fp_table_input <= float_data[mem_count - 1]; // 0.1 ~ 0.6

                                mem_control_state <= 2;
                            end
                            2: begin
                                // write 완료, 다음 주소로 이동
                                bram_we_pulse <= 1;     // 펄스 쓰기
                                ena_pulse <= 1;
                                
                                bram_data_in_pulse <= fp_add_result;

                                bram_addr_pulse <= bram_addr_pulse;

                                mem_count <= mem_count + 1;
                                mem_control_state <= 0; // 다음 루프
                            end
                        endcase
                    end
                end

            end else begin
                bram_we_pin <= 0;
                ena_pin <= 0;

                bram_we_pulse <= 0;
                ena_pulse <= 0;
                mem_count <= 0;

                finish_pulse_gen <= 2'b11;
            end 
        end
    end
endmodule


module tb_FinPulseGenNut();

    // Inputs
    reg clk;
    reg [31:0] cps;

    // Outputs
    wire [31:0] bram_addr;
    wire [31:0] bram_data_in;
    wire bram_we_pin;
    wire ena_pin;

    wire [31:0] bram_addr_pulse;
    wire [31:0] bram_data_in_pulse;
    wire bram_we_pulse;
    wire ena_pin_pulse;

    wire [1:0] finish_pulse_gen;

    wire [31:0] bram_data_out_pulse;

    // Instantiate the Unit Under Test (UUT)
    FinPulseGenNut uut (
        .clk(clk),
        .cps(cps),
        .bram_addr(bram_addr),
        .bram_data_in(bram_data_in),
        .bram_we_pin(bram_we_pin),
        .ena_pin(ena_pin),
        .bram_addr_pulse(bram_addr_pulse),
        .bram_data_in_pulse(bram_data_in_pulse),
        .bram_we_pulse(bram_we_pulse),
        .ena_pulse(ena_pulse),
        .finish_pulse_gen(finish_pulse_gen),
        .bram_data_out_pulse(bram_data_out_pulse)
    );

    bram pin_bram_inst (
        .clka(clk),
        .ena(ena_pin),
        .wea(bram_we_pin),
        .addra(bram_addr),
        .dina(bram_data_in),
        .douta()  // Read output not used in this test
    );

    bram pulse_bram_inst (
        .clka(clk),
        .ena(ena_pulse),
        .wea(bram_we_pulse),
        .addra(bram_addr_pulse),
        .dina(bram_data_in_pulse),
        .douta(bram_data_out_pulse)  // Read output not used in this test
    );

    // Clock generation: 10ns period
    always #5 clk = ~clk;

    initial begin
        $dumpfile("Verilog_file/FinPulseGenNut.vcd");
        $dumpvars(0, tb_FinPulseGenNut);
        // Initialize inputs
        clk = 0;
        cps = 0;

        // Wait for global reset
        #20;

        // Test 1: cps = 0 → 모듈 초기화 상태 유지
        cps = 0;
        #50;

        // Test 2: cps = 10 → 10개의 pulse 발생
        cps = 2;
        #5000;

        cps = 0;
        #50

        // Test 2: cps = 10 → 10개의 pulse 발생
        cps = 1;
        #500;

        // // Test 3: cps = 5 → 다시 시작됨 (변경된 cps 값)
        // cps = 5;
        // #500;

        // // Test 4: cps = 0 → 종료
        // cps = 0;
        // #100;

        $finish;
    end

endmodule

Verilog_file/FinPulseGenNut.vcd
$date
	Sun Aug 03 19:35:28 2025
$end
$version
	Icarus Verilog
$end
$timescale
	1ps
$end
$scope module tb_FinPulseGenNut $end
$var wire 2 ! finish_pulse_gen [1:0] $end
$var wire 1 " ena_pulse $end
$var wire 1 # ena_pin $end
$var wire 1 $ bram_we_pulse $end
$var wire 1 % bram_we_pin $end
$var wire 32 & bram_data_out_pulse [31:0] $end
$var wire 32 ' bram_data_in_pulse [31:0] $end
$var wire 32 ( bram_data_in [31:0] $end
$var wire 32 ) bram_addr_pulse [31:0] $end
$var wire 32 * bram_addr [31:0] $end
$var reg 1 + clk $end
$var reg 32 , cps [31:0] $end
$scope module pin_bram_inst $end
$var wire 1 + clka $end
$var wire 1 % wea $end
$var wire 1 # ena $end
$var wire 32 - dina [31:0] $end
$var wire 32 . addra [31:0] $end
$var wire 13 / addr_index [12:0] $end
$var reg 32 0 douta [31:0] $end
$var reg 32 1 mem1 [31:0] $end
$var reg 32 2 mem2 [31:0] $end
$var reg 32 3 mem3 [31:0] $end
$var reg 32 4 mem4 [31:0] $end
$var reg 32 5 mem5 [31:0] $end
$var reg 32 6 mem6 [31:0] $end
$var integer 32 7 i [31:0] $end
$upscope $end
$scope module pulse_bram_inst $end
$var wire 1 + clka $end
$var wire 1 $ wea $end
$var wire 1 " ena $end
$var wire 32 8 dina [31:0] $end
$var wire 32 9 addra [31:0] $end
$var wire 13 : addr_index [12:0] $end
$var reg 32 ; douta [31:0] $end
$var reg 32 < mem1 [31:0] $end
$var reg 32 = mem2 [31:0] $end
$var reg 32 > mem3 [31:0] $end
$var reg 32 ? mem4 [31:0] $end
$var reg 32 @ mem5 [31:0] $end
$var reg 32 A mem6 [31:0] $end
$var integer 32 B i [31:0] $end
$upscope $end
$scope module uut $end
$var wire 32 C bram_data_out_pulse [31:0] $end
$var wire 1 + clk $end
$var wire 32 D cps [31:0] $end
$var wire 32 E fp_add_result [31:0] $end
$var reg 32 F bram_addr [31:0] $end
$var reg 32 G bram_addr_pulse [31:0] $end
$var reg 32 H bram_data_in [31:0] $end
$var reg 32 I bram_data_in_pulse [31:0] $end
$var reg 1 % bram_we_pin $end
$var reg 1 $ bram_we_pulse $end
$var reg 32 J count [31:0] $end
$var reg 1 # ena_pin $end
$var reg 1 " ena_pulse $end
$var reg 2 K finish_pulse_gen [1:0] $end
$var reg 32 L fp_table_input [31:0] $end
$var reg 11 M lfsr [10:0] $end
$var reg 4 N mem_control_state [3:0] $end
$var reg 32 O mem_count [31:0] $end
$var reg 32 P prev_cps [31:0] $end
$var reg 32 Q prev_mem_val [31:0] $end
$scope module adder_inst $end
$var wire 32 R a [31:0] $end
$var wire 32 S b [31:0] $end
$var wire 1 T sign_b $end
$var wire 1 U sign_a $end
$var wire 32 V result [31:0] $end
$var wire 24 W mant_b [23:0] $end
$var wire 24 X mant_a [23:0] $end
$var wire 8 Y exp_b [7:0] $end
$var wire 8 Z exp_a [7:0] $end
$var reg 24 [ aligned_a [23:0] $end
$var reg 24 \ aligned_b [23:0] $end
$var reg 8 ] exp_diff [7:0] $end
$var reg 8 ^ exp_res [7:0] $end
$var reg 23 _ frac_res [22:0] $end
$var reg 25 ` mant_sum [24:0] $end
$var reg 1 a sign_res $end
$upscope $end
$upscope $end
$upscope $end
$enddefinitions $end
$comment Show the parameter values. $end
$dumpall
$end
#0
$dumpvars
xa
b0 `
b0 _
bx ^
bx ]
bx \
bx [
bx Z
bx Y
bx X
bx W
bx00000000000000000000000 V
xU
xT
bx S
bx R
b0 Q
b0 P
b0 O
b0 N
b10101010101 M
bx L
bx K
b0 J
bx I
bx H
bx G
bx F
bx00000000000000000000000 E
b0 D
bx C
b1111101000000 B
bx A
bx @
bx ?
bx >
bx =
bx <
bx ;
bx :
bx 9
bx 8
b1111101000000 7
bx 6
bx 5
bx 4
bx 3
bx 2
bx 1
bx 0
bx /
bx .
bx -
b0 ,
0+
bx *
bx )
bx (
bx '
bx &
x%
x$
x#
x"
bx !
$end
#5000
b0 :
b0 /
b0 !
b0 K
b0 )
b0 9
b0 G
0"
0$
0#
0%
b1010101011 M
b0 *
b0 .
b0 F
1+
#10000
0+
#15000
b10101010111 M
1+
#20000
0+
#25000
b1010101111 M
1+
#30000
0+
#35000
b10101011111 M
1+
#40000
0+
#45000
b1010111111 M
1+
#50000
0+
#55000
b10101111111 M
1+
#60000
0+
#65000
b1011111111 M
1+
#70000
0+
b10 ,
b10 D
#75000
b1 !
b1 K
b10 P
b10111111111 M
1+
#80000
0+
#85000
b100 :
b100 /
b1 N
b1 O
1"
1#
1%
b100 )
b100 9
b100 G
b1 '
b1 8
b1 I
b100 *
b100 .
b100 F
b1 (
b1 -
b1 H
b1111111110 M
1+
#90000
0+
#95000
b0 X
b1000110011100111000001 _
b101000110011100111000001 `
0a
b111101101000110011100111000001 E
b111101101000110011100111000001 V
b1111011 ^
b101000110011100111000001 \
b0 [
b1111011 ]
b101000110011100111000001 W
0U
b0 Z
0T
b1111011 Y
b0 A
b0 @
b0 ?
b0 >
b0 =
b0 <
b0 &
b0 ;
b0 C
b0 R
b0 6
b0 5
b0 4
b0 3
b1 2
b0 1
b1 0
b10 N
b111101101000110011100111000001 L
b111101101000110011100111000001 S
0"
1+
#100000
0+
#105000
b0 N
b10 O
b111101101000110011100111000001 '
b111101101000110011100111000001 8
b111101101000110011100111000001 I
1"
1$
1+
#110000
0+
#115000
b111110001000110011100111000001 E
b111110001000110011100111000001 V
b1111100 ^
b101000110011100111000001 `
b101000110011100111000001 [
b0 ]
b101000110011100111000001 X
b1111011 Z
b1000 :
b111101101000110011100111000001 =
b111101101000110011100111000001 &
b111101101000110011100111000001 ;
b111101101000110011100111000001 C
b111101101000110011100111000001 R
b1 N
0$
b1000 )
b1000 9
b1000 G
1+
#120000
0+
#125000
b10110011010110101000011 _
b110110011010110101000011 `
b110110011010110101000011 \
b110110011010110101000011 W
b111111010110011010110101000011 E
b111111010110011010110101000011 V
b1111110 ^
b0 [
b1111110 ]
b0 X
b1111110 Y
b0 Z
b10 N
b111111010110011010110101000011 L
b111111010110011010110101000011 S
0"
b0 &
b0 ;
b0 C
b0 R
1+
#130000
0+
#135000
b0 N
b11 O
b111111010110011010110101000011 '
b111111010110011010110101000011 8
b111111010110011010110101000011 I
1"
1$
1+
#140000
0+
#145000
b111111110110011010110101000011 E
b111111110110011010110101000011 V
b1111111 ^
b110110011010110101000011 `
b110110011010110101000011 [
b0 ]
b110110011010110101000011 X
b1100 :
b1111110 Z
b1 N
0$
b1100 )
b1100 9
b1100 G
b111111010110011010110101000011 >
b111111010110011010110101000011 &
b111111010110011010110101000011 ;
b111111010110011010110101000011 C
b111111010110011010110101000011 R
1+
#150000
0+
#155000
b11100111010001010011100 _
b111100111010001010011100 `
b111111011100111010001010011100 E
b111111011100111010001010011100 V
b1111110 ^
b111100111010001010011100 \
b0 [
b1111110 ]
b0 X
b111100111010001010011100 W
b0 Z
b0 &
b0 ;
b0 C
b0 R
b10 N
b111111011100111010001010011100 L
b111111011100111010001010011100 S
0"
1+
#160000
0+
#165000
b0 N
b100 O
b111111011100111010001010011100 '
b111111011100111010001010011100 8
b111111011100111010001010011100 I
1"
1$
1+
#170000
0+
#175000
b111111111100111010001010011100 E
b111111111100111010001010011100 V
b1111111 ^
b111100111010001010011100 `
b111100111010001010011100 [
b0 ]
b111100111010001010011100 X
b1111110 Z
b10000 :
b111111011100111010001010011100 ?
b111111011100111010001010011100 &
b111111011100111010001010011100 ;
b111111011100111010001010011100 C
b111111011100111010001010011100 R
b1 N
0$
b10000 )
b10000 9
b10000 G
1+
#180000
0+
#185000
b11001010010010101000110 _
b111001010010010101000110 `
b111001010010010101000110 \
b111001010010010101000110 W
b111111011001010010010101000110 E
b111111011001010010010101000110 V
b1111110 ^
b0 [
b1111110 ]
b0 X
b0 Z
b10 N
b111111011001010010010101000110 L
b111111011001010010010101000110 S
0"
b0 &
b0 ;
b0 C
b0 R
1+
#190000
0+
#195000
b0 N
b101 O
b111111011001010010010101000110 '
b111111011001010010010101000110 8
b111111011001010010010101000110 I
1"
1$
1+
#200000
0+
#205000
b111111111001010010010101000110 E
b111111111001010010010101000110 V
b1111111 ^
b111001010010010101000110 `
b111001010010010101000110 [
b0 ]
b111001010010010101000110 X
b10100 :
b1111110 Z
b1 N
0$
b10100 )
b10100 9
b10100 G
b111111011001010010010101000110 @
b111111011001010010010101000110 &
b111111011001010010010101000110 ;
b111111011001010010010101000110 C
b111111011001010010010101000110 R
1+
#210000
0+
#215000
b10011101100010101101101 _
b110011101100010101101101 `
b111111010011101100010101101101 E
b111111010011101100010101101101 V
b1111110 ^
b110011101100010101101101 \
b0 [
b1111110 ]
b0 X
b110011101100010101101101 W
b0 Z
b0 &
b0 ;
b0 C
b0 R
b10 N
b111111010011101100010101101101 L
b111111010011101100010101101101 S
0"
1+
#220000
0+
#225000
b0 N
b110 O
b111111010011101100010101101101 '
b111111010011101100010101101101 8
b111111010011101100010101101101 I
1"
1$
1+
#230000
0+
#235000
b111111110011101100010101101101 E
b111111110011101100010101101101 V
b1111111 ^
b110011101100010101101101 `
b110011101100010101101101 [
b0 ]
b110011101100010101101101 X
b1111110 Z
b11000 :
b111111010011101100010101101101 A
b111111010011101100010101101101 &
b111111010011101100010101101101 ;
b111111010011101100010101101101 C
b111111010011101100010101101101 R
b1 N
0$
b11000 )
b11000 9
b11000 G
1+
#240000
0+
#245000
b1110001000110011100111 _
b101110001000110011100111 `
b101110001000110011100111 \
b101110001000110011100111 W
b111111001110001000110011100111 E
b111111001110001000110011100111 V
b1111110 ^
b0 [
b1111110 ]
b0 X
b0 Z
b10 N
b111111001110001000110011100111 L
b111111001110001000110011100111 S
0"
b0 &
b0 ;
b0 C
b0 R
1+
#250000
0+
#255000
b0 N
b111 O
b111111001110001000110011100111 '
b111111001110001000110011100111 8
b111111001110001000110011100111 I
1"
1$
1+
#260000
0+
#265000
b111111101110001000110011100111 E
b111111101110001000110011100111 V
b1111111 ^
b101110001000110011100111 `
b101110001000110011100111 [
b0 ]
b101110001000110011100111 X
b11100 :
b1111110 Z
b1 N
0$
b11100 )
b11100 9
b11100 G
b111111001110001000110011100111 &
b111111001110001000110011100111 ;
b111111001110001000110011100111 C
b111111001110001000110011100111 R
1+
#270000
0+
#275000
b1001000010110000111101 _
b101001000010110000111101 `
b111111001001000010110000111101 E
b111111001001000010110000111101 V
b1111110 ^
b101001000010110000111101 \
b0 [
b1111110 ]
b0 X
b101001000010110000111101 W
b0 Z
b0 &
b0 ;
b0 C
b0 R
b10 N
b111111001001000010110000111101 L
b111111001001000010110000111101 S
0"
1+
#280000
0+
#285000
b0 N
b1000 O
b111111001001000010110000111101 '
b111111001001000010110000111101 8
b111111001001000010110000111101 I
1"
1$
1+
#290000
0+
#295000
b111111101001000010110000111101 E
b111111101001000010110000111101 V
b1111111 ^
b101001000010110000111101 `
b101001000010110000111101 [
b0 ]
b101001000010110000111101 X
b1111110 Z
b100000 :
b111111001001000010110000111101 &
b111111001001000010110000111101 ;
b111111001001000010110000111101 C
b111111001001000010110000111101 R
b1 N
0$
b100000 )
b100000 9
b100000 G
1+
#300000
0+
#305000
b100011110101110000101 _
b100100011110101110000101 `
b100100011110101110000101 \
b100100011110101110000101 W
b111111000100011110101110000101 E
b111111000100011110101110000101 V
b1111110 ^
b0 [
b1111110 ]
b0 X
b0 Z
b10 N
b111111000100011110101110000101 L
b111111000100011110101110000101 S
0"
b0 &
b0 ;
b0 C
b0 R
1+
#310000
0+
#315000
b0 N
b1001 O
b111111000100011110101110000101 '
b111111000100011110101110000101 8
b111111000100011110101110000101 I
1"
1$
1+
#320000
0+
#325000
b111111100100011110101110000101 E
b111111100100011110101110000101 V
b1111111 ^
b100100011110101110000101 `
b100100011110101110000101 [
b0 ]
b100100011110101110000101 X
b100100 :
b1111110 Z
b1 N
0$
b100100 )
b100100 9
b100100 G
b111111000100011110101110000101 &
b111111000100011110101110000101 ;
b111111000100011110101110000101 C
b111111000100011110101110000101 R
1+
#330000
0+
#335000
b11010100111111100 _
b100000011010100111111100 `
b111111000000011010100111111100 E
b111111000000011010100111111100 V
b1111110 ^
b100000011010100111111100 \
b0 [
b1111110 ]
b0 X
b100000011010100111111100 W
b0 Z
b0 &
b0 ;
b0 C
b0 R
b10 N
b111111000000011010100111111100 L
b111111000000011010100111111100 S
0"
1+
#340000
0+
#345000
b0 N
b1010 O
b111111000000011010100111111100 '
b111111000000011010100111111100 8
b111111000000011010100111111100 I
1"
1$
1+
#350000
0+
#355000
b111111100000011010100111111100 E
b111111100000011010100111111100 V
b1111111 ^
b100000011010100111111100 `
b100000011010100111111100 [
b0 ]
b100000011010100111111100 X
b1111110 Z
b101000 :
b111111000000011010100111111100 &
b111111000000011010100111111100 ;
b111111000000011010100111111100 C
b111111000000011010100111111100 R
b1 N
0$
b101000 )
b101000 9
b101000 G
1+
#360000
0+
#365000
b11001100111001110000010 _
b111001100111001110000010 `
b111001100111001110000010 \
b111001100111001110000010 W
b111110111001100111001110000010 E
b111110111001100111001110000010 V
b1111101 ^
b0 [
b1111101 ]
b0 X
b1111101 Y
b0 Z
b10 N
b111110111001100111001110000010 L
b111110111001100111001110000010 S
0"
b0 &
b0 ;
b0 C
b0 R
1+
#370000
0+
#375000
b0 N
b1011 O
b111110111001100111001110000010 '
b111110111001100111001110000010 8
b111110111001100111001110000010 I
1"
1$
1+
#380000
0+
#385000
b111111011001100111001110000010 E
b111111011001100111001110000010 V
b1111110 ^
b111001100111001110000010 `
b111001100111001110000010 [
b0 ]
b111001100111001110000010 X
b101100 :
b1111101 Z
b1 N
0$
b101100 )
b101100 9
b101100 G
b111110111001100111001110000010 &
b111110111001100111001110000010 ;
b111110111001100111001110000010 C
b111110111001100111001110000010 R
1+
#390000
0+
#395000
b10011001011111110110001 _
b110011001011111110110001 `
b111110110011001011111110110001 E
b111110110011001011111110110001 V
b1111101 ^
b110011001011111110110001 \
b0 [
b1111101 ]
b0 X
b110011001011111110110001 W
b0 Z
b0 &
b0 ;
b0 C
b0 R
b10 N
b111110110011001011111110110001 L
b111110110011001011111110110001 S
0"
1+
#400000
0+
#405000
b0 N
b1100 O
b111110110011001011111110110001 '
b111110110011001011111110110001 8
b111110110011001011111110110001 I
1"
1$
1+
#410000
0+
#415000
b111111010011001011111110110001 E
b111111010011001011111110110001 V
b1111110 ^
b110011001011111110110001 `
b110011001011111110110001 [
b0 ]
b110011001011111110110001 X
b1111101 Z
b110000 :
b111110110011001011111110110001 &
b111110110011001011111110110001 ;
b111110110011001011111110110001 C
b111110110011001011111110110001 R
b1 N
0$
b110000 )
b110000 9
b110000 G
1+
#420000
0+
#425000
b1101011111011011111101 _
b101101011111011011111101 `
b101101011111011011111101 \
b101101011111011011111101 W
b111110101101011111011011111101 E
b111110101101011111011011111101 V
b1111101 ^
b0 [
b1111101 ]
b0 X
b0 Z
b10 N
b111110101101011111011011111101 L
b111110101101011111011011111101 S
0"
b0 &
b0 ;
b0 C
b0 R
1+
#430000
0+
#435000
b0 N
b1101 O
b111110101101011111011011111101 '
b111110101101011111011011111101 8
b111110101101011111011011111101 I
1"
1$
1+
#440000
0+
#445000
b111111001101011111011011111101 E
b111111001101011111011011111101 V
b1111110 ^
b101101011111011011111101 `
b101101011111011011111101 [
b0 ]
b101101011111011011111101 X
b110100 :
b1111101 Z
b1 N
0$
b110100 )
b110100 9
b110100 G
b111110101101011111011011111101 &
b111110101101011111011011111101 ;
b111110101101011111011011111101 C
b111110101101011111011011111101 R
1+
#450000
0+
#455000
b1000011011000010001010 _
b101000011011000010001010 `
b111110101000011011000010001010 E
b111110101000011011000010001010 V
b1111101 ^
b101000011011000010001010 \
b0 [
b1111101 ]
b0 X
b101000011011000010001010 W
b0 Z
b0 &
b0 ;
b0 C
b0 R
b10 N
b111110101000011011000010001010 L
b111110101000011011000010001010 S
0"
1+
#460000
0+
#465000
b0 N
b1110 O
b111110101000011011000010001010 '
b111110101000011011000010001010 8
b111110101000011011000010001010 I
1"
1$
1+
#470000
0+
#475000
b111111001000011011000010001010 E
b111111001000011011000010001010 V
b1111110 ^
b101000011011000010001010 `
b101000011011000010001010 [
b0 ]
b101000011011000010001010 X
b1111101 Z
b111000 :
b111110101000011011000010001010 &
b111110101000011011000010001010 ;
b111110101000011011000010001010 C
b111110101000011011000010001010 R
b1 N
0$
b111000 )
b111000 9
b111000 G
1+
#480000
0+
#485000
b11111010101011001110 _
b100011111010101011001110 `
b100011111010101011001110 \
b100011111010101011001110 W
b111110100011111010101011001110 E
b111110100011111010101011001110 V
b1111101 ^
b0 [
b1111101 ]
b0 X
b0 Z
b10 N
b111110100011111010101011001110 L
b111110100011111010101011001110 S
0"
b0 &
b0 ;
b0 C
b0 R
1+
#490000
0+
#495000
b0 N
b1111 O
b111110100011111010101011001110 '
b111110100011111010101011001110 8
b111110100011111010101011001110 I
1"
1$
1+
#500000
0+
#505000
b111111000011111010101011001110 E
b111111000011111010101011001110 V
b1111110 ^
b100011111010101011001110 `
b100011111010101011001110 [
b0 ]
b100011111010101011001110 X
b111100 :
b1111101 Z
b1 N
0$
b111100 )
b111100 9
b111100 G
b111110100011111010101011001110 &
b111110100011111010101011001110 ;
b111110100011111010101011001110 C
b111110100011111010101011001110 R
1+
#510000
0+
#515000
b0 X
b11111110100100010000000 _
b111111110100100010000000 `
b111110011111110100100010000000 E
b111110011111110100100010000000 V
b1111100 ^
b111111110100100010000000 \
b0 [
b1111100 ]
b111111110100100010000000 W
b0 Z
b1111100 Y
b0 &
b0 ;
b0 C
b0 R
b10 N
b111110011111110100100010000000 L
b111110011111110100100010000000 S
0"
1+
#520000
0+
