Verilog_file/BRAM_Model.v
module bram(
    input  wire            clka,
    input  wire            ena,
    input  wire            wea,
    input  wire  [31:0]    addra,
    input  wire  [31:0]    dina,
    output reg   [31:0]    douta
);

    reg [31:0] mem [0:7999];
    reg [31:0] mem1;
    reg [31:0] mem2;
    reg [31:0] mem3;
    reg [31:0] mem4;
    reg [31:0] mem5;
    reg [31:0] mem6;

    // 13비트 주소 인덱스 (0~8191까지 가능, 실제는 0~7999만 사용)
    wire [12:0] addr_index = addra[12:0];

    integer i;

    // 초기화 블록 (시뮬레이션용)
    initial begin
        for (i = 0; i <= 7999; i = i + 1) begin
            mem[i] = 32'd0;
        end
    end

    // 동기식 동작 (읽기/쓰기)
    always @(posedge clka) begin
        if (ena) begin
            if (wea != 1'b0) begin
                mem[addr_index] = dina;
            end
            douta <= mem[addr_index];

            // 디버깅용 특정 위치 레지스터 저장
            mem1 <= mem[0];
            mem2 <= mem[4];
            mem3 <= mem[8];
            mem4 <= mem[12];
            mem5 <= mem[16];
            mem6 <= mem[20];

            // 디버깅 출력
            // $display("[READ ] MEM[%0d] [0x%08X] => 0x%08X", addr_index, dina, mem[addr_index]);
        end
    end

endmodule

Verilog_file/PulseGenFin/fp32_adder.v
module fp32_adder (
    input  [31:0] a,
    input  [31:0] b,
    output [31:0] result
);
    wire sign_a = a[31];
    wire sign_b = b[31];
    wire [7:0] exp_a = a[30:23];
    wire [7:0] exp_b = b[30:23];
    wire [23:0] mant_a = (exp_a == 0) ? {1'b0, a[22:0]} : {1'b1, a[22:0]};
    wire [23:0] mant_b = (exp_b == 0) ? {1'b0, b[22:0]} : {1'b1, b[22:0]};

    reg [7:0] exp_diff;
    reg [23:0] aligned_a, aligned_b;
    reg [7:0] exp_res;
    reg [24:0] mant_sum;
    reg sign_res;
    reg [22:0] frac_res;

    always @(*) begin
        // 지수 맞춤
        if (exp_a > exp_b) begin
            exp_diff = exp_a - exp_b;
            aligned_a = mant_a;
            aligned_b = mant_b >> exp_diff;
            exp_res = exp_a;
            sign_res = sign_a;
        end else begin
            exp_diff = exp_b - exp_a;
            aligned_a = mant_a >> exp_diff;
            aligned_b = mant_b;
            exp_res = exp_b;
            sign_res = sign_b;
        end

        // 같은 부호만 지원 (간단 버전)
        if (sign_a == sign_b) begin
            mant_sum = aligned_a + aligned_b;
            if (mant_sum[24]) begin
                mant_sum = mant_sum >> 1;
                exp_res = exp_res + 1;
            end
        end else begin
            // 부호 다르면 뺄셈인데, 여기선 간단히 무시
            mant_sum = 0;
        end

        frac_res = mant_sum[22:0];
    end

    assign result = {sign_res, exp_res, frac_res};
endmodule

Verilog_file/FinPulseGenGam.v
`timescale 1ns / 1ps
`include "./Verilog_file/BRAM_Model.v"
`include "./Verilog_file/fp32_adder.v"

module FinPulseGenGam(
    input wire clk,
    input wire [31:0] cps,
    output reg [31:0] bram_addr,
    output reg [31:0] bram_data_in,
    output reg bram_we_pin,
    output reg ena_pin,

    output reg [31:0] bram_addr_pulse,
    output reg [31:0] bram_data_in_pulse,
    output reg bram_we_pulse,
    output reg ena_pulse,

    output reg [1:0] finish_pulse_gen,

    input wire [31:0] bram_data_out_pulse
);
    // reg [9:0] lfsr = 10'b1010101010;  // 10비트 초기값
    reg [10:0] lfsr = 11'b10101010101;  // 11비트 초기값

    reg [31:0] count = 0;
    reg [31:0] prev_cps = 0;

    reg [31:0] mem_count = 0;
    reg [31:0] count_gam = 0;

    reg [3:0] mem_control_state = 0;
    reg [31:0] prev_mem_val = 0;

    // Gamma Pulse Data Table
    reg [31:0] float_data [0:12];

    initial begin
        float_data[0] = 32'h3D7C5048; // 0.0616
        float_data[1] = 32'h3E99652C; // 0.2996
        float_data[2] = 32'h3E0E3BCD; // 0.1389
        float_data[3] = 32'h3D83126F; // 0.0640
        float_data[4] = 32'h3CF1A9FC; // 0.0295
        float_data[5] = 32'h3C5ED289; // 0.0136
        float_data[6] = 32'h3BCE703B; // 0.0063
        float_data[7] = 32'h3B3E0DED; // 0.0029
        float_data[8] = 32'h3AAA64C3; // 0.0013
        float_data[9] = 32'h3A1D4952; // 0.0006
        float_data[10] = 32'h399D4952; // 0.0003
        float_data[11] = 32'h38D1B717; // 0.0001
        float_data[12] = 32'h38D1B717; // 0.0001
    end

    wire [31:0] fp_add_result;
    reg [31:0] fp_table_input;

    fp32_adder adder_inst (
        .a(bram_data_out_pulse),
        .b(fp_table_input),         // IEEE 754
        .result(fp_add_result)
    );

    always @(posedge clk) begin
        if (cps == 0) begin
            bram_addr <= 0;
            // lfsr <= 10'b1010101010;
            // lfsr <= 11'b10101010101; // 11비트 초기값
            lfsr <= {lfsr[9:0], lfsr[10] ^ lfsr[7]}; // 11비트 LFSR로 변경 (이전 변경 값을 가져다 씀)
            count <= 0;
            count_gam <= 0;
            prev_cps <= 0;
            bram_we_pin <= 0;
            ena_pin <= 0;

            bram_we_pulse <= 0;
            ena_pulse <= 0;
            bram_addr_pulse <= 0;

            mem_count <= 0;
            mem_control_state <= 0;

            finish_pulse_gen <= 2'b00; // 초기화 상태

        end else begin
            // cps가 변경되었을 경우 재시작
            if (cps != prev_cps) begin
                count <= 0;
                count_gam <= 0;
                // lfsr <= 10'b1010101010;
                // lfsr <= 11'b10101010101; // 11비트 초기값
                lfsr <= {lfsr[9:0], lfsr[10] ^ lfsr[7]}; // 11비트 LFSR로 변경 (이전 변경 값을 가져다 씀)

                prev_cps <= cps;
                ena_pin <= 0;
                bram_we_pin <= 0;

                bram_we_pulse <= 0;
                ena_pulse <= 0;
                mem_count <= 0;
                mem_control_state <= 0;

                finish_pulse_gen <= 2'b01;

            end else if (count < cps) begin
                if (mem_count == 0) begin
                    // 10비트 LFSR: x^10 + x^7 + 1
                    // lfsr <= {lfsr[8:0], lfsr[9] ^ lfsr[6]};

                    lfsr <= {lfsr[9:0], lfsr[10] ^ lfsr[7]}; // 11비트 LFSR로 변경

                    bram_data_in <= 1;                    // 펄스 발생 시점 값
                    // bram_addr <= 32'b100; // lfsr * 4;                // 0 ~ 1023 개 가능
                    bram_addr <= lfsr * 4;                // 11비트 0 ~ 2047 개 가능

                    bram_data_in_pulse <= 1;              // 펄스 값
                    // bram_addr_pulse <= 32'b100; //lfsr * 4;          // 0 ~ 1023 개 가능
                    bram_addr_pulse <= lfsr * 4;                // 11비트 0 ~ 2047 개 가능

                    // Pin 메모리에 1 값 쓰기.
                    bram_we_pin <= 1;
                    ena_pin <= 1;
                    
                    // Pulse 메모리에 1 부터 증가하는 값 쓰기
                    bram_we_pulse <= 0;             // 펄스 읽기
                    ena_pulse <= 1;                 // 활성화
                    mem_count <= 1;                 // 메모리 카운트 증가

                    mem_control_state <= 1;

                end else begin
                    if (mem_count > 13) begin
                        // 메모리 카운트가 13 이상이면 펄스 종료
                        bram_we_pulse <= 0;             // 펄스 종료
                        ena_pulse <= 0;                 // 비활성화
                        mem_count <= 0;                 // 메모리 카운트 초기화

                        mem_control_state <= 0;         // BRAM 제어 상태 초기화

                        // Pin 메모리 정지
                        bram_we_pin <= 0;
                        ena_pin <= 0;
                        
                        if (count_gam == 1) begin
                            count <= count + 1;
                            count_gam <= 0;
                        end else begin
                            count_gam <= count_gam + 1;
                        end
                        
                        // count <= count + 1;

                    end else begin
                        case (mem_control_state)
                            0: begin
                                bram_addr_pulse <= bram_addr_pulse + 4;
                                bram_we_pulse <= 0;     // 펄스 읽기
                                ena_pulse <= 1;
                                // 주소 유지
                                mem_control_state <= 1;
                            end
                            1: begin
                                // 대기 
                                bram_we_pulse <= 0;     // 펄스 읽기
                                ena_pulse <= 0;

                                fp_table_input <= float_data[mem_count - 1]; // 0.1 ~ 0.6

                                mem_control_state <= 2;
                            end
                            2: begin
                                // write 완료, 다음 주소로 이동
                                bram_we_pulse <= 1;     // 펄스 쓰기
                                ena_pulse <= 1;
                                
                                bram_data_in_pulse <= fp_add_result;

                                bram_addr_pulse <= bram_addr_pulse;

                                mem_count <= mem_count + 1;
                                mem_control_state <= 0; // 다음 루프
                            end
                        endcase
                    end
                end

            end else begin
                bram_we_pin <= 0;
                ena_pin <= 0;

                bram_we_pulse <= 0;
                ena_pulse <= 0;
                mem_count <= 0;

                finish_pulse_gen <= 2'b11;
            end 
        end
    end
endmodule


module tb_FinPulseGenGam();

    // Inputs
    reg clk;
    reg [31:0] cps;

    // Outputs
    wire [31:0] bram_addr;
    wire [31:0] bram_data_in;
    wire bram_we_pin;
    wire ena_pin;

    wire [31:0] bram_addr_pulse;
    wire [31:0] bram_data_in_pulse;
    wire bram_we_pulse;
    wire ena_pin_pulse;

    wire [1:0] finish_pulse_gen;

    wire [31:0] bram_data_out_pulse;

    // Instantiate the Unit Under Test (UUT)
    FinPulseGenGam uut (
        .clk(clk),
        .cps(cps),
        .bram_addr(bram_addr),
        .bram_data_in(bram_data_in),
        .bram_we_pin(bram_we_pin),
        .ena_pin(ena_pin),
        .bram_addr_pulse(bram_addr_pulse),
        .bram_data_in_pulse(bram_data_in_pulse),
        .bram_we_pulse(bram_we_pulse),
        .ena_pulse(ena_pulse),
        .finish_pulse_gen(finish_pulse_gen),
        .bram_data_out_pulse(bram_data_out_pulse)
    );

    bram pin_bram_inst (
        .clka(clk),
        .ena(ena_pin),
        .wea(bram_we_pin),
        .addra(bram_addr),
        .dina(bram_data_in),
        .douta()  // Read output not used in this test
    );

    bram pulse_bram_inst (
        .clka(clk),
        .ena(ena_pulse),
        .wea(bram_we_pulse),
        .addra(bram_addr_pulse),
        .dina(bram_data_in_pulse),
        .douta(bram_data_out_pulse)  // Read output not used in this test
    );

    // Clock generation: 10ns period
    always #5 clk = ~clk;

    initial begin
        $dumpfile("Verilog_file/FinPulseGenGam.vcd");
        $dumpvars(0, tb_FinPulseGenGam);
        // Initialize inputs
        clk = 0;
        cps = 0;

        // Wait for global reset
        #20;

        // Test 1: cps = 0 → 모듈 초기화 상태 유지
        cps = 0;
        #50;

        // Test 2: cps = 10 → 10개의 pulse 발생
        cps = 2;
        #5000;

        cps = 0;
        #50

        // Test 2: cps = 10 → 10개의 pulse 발생
        cps = 1;
        #500;

        // // Test 3: cps = 5 → 다시 시작됨 (변경된 cps 값)
        // cps = 5;
        // #500;

        // // Test 4: cps = 0 → 종료
        // cps = 0;
        // #100;

        $finish;
    end

endmodule

Verilog_file/FinPulseGenGam.vcd
$date
	Sun Aug 03 19:20:10 2025
$end
$version
	Icarus Verilog
$end
$timescale
	1ps
$end
$scope module tb_FinPulseGenGam $end
$var wire 2 ! finish_pulse_gen [1:0] $end
$var wire 1 " ena_pulse $end
$var wire 1 # ena_pin $end
$var wire 1 $ bram_we_pulse $end
$var wire 1 % bram_we_pin $end
$var wire 32 & bram_data_out_pulse [31:0] $end
$var wire 32 ' bram_data_in_pulse [31:0] $end
$var wire 32 ( bram_data_in [31:0] $end
$var wire 32 ) bram_addr_pulse [31:0] $end
$var wire 32 * bram_addr [31:0] $end
$var reg 1 + clk $end
$var reg 32 , cps [31:0] $end
$scope module pin_bram_inst $end
$var wire 1 + clka $end
$var wire 1 % wea $end
$var wire 1 # ena $end
$var wire 32 - dina [31:0] $end
$var wire 32 . addra [31:0] $end
$var wire 13 / addr_index [12:0] $end
$var reg 32 0 douta [31:0] $end
$var reg 32 1 mem1 [31:0] $end
$var reg 32 2 mem2 [31:0] $end
$var reg 32 3 mem3 [31:0] $end
$var reg 32 4 mem4 [31:0] $end
$var reg 32 5 mem5 [31:0] $end
$var reg 32 6 mem6 [31:0] $end
$var integer 32 7 i [31:0] $end
$upscope $end
$scope module pulse_bram_inst $end
$var wire 1 + clka $end
$var wire 1 $ wea $end
$var wire 1 " ena $end
$var wire 32 8 dina [31:0] $end
$var wire 32 9 addra [31:0] $end
$var wire 13 : addr_index [12:0] $end
$var reg 32 ; douta [31:0] $end
$var reg 32 < mem1 [31:0] $end
$var reg 32 = mem2 [31:0] $end
$var reg 32 > mem3 [31:0] $end
$var reg 32 ? mem4 [31:0] $end
$var reg 32 @ mem5 [31:0] $end
$var reg 32 A mem6 [31:0] $end
$var integer 32 B i [31:0] $end
$upscope $end
$scope module uut $end
$var wire 32 C bram_data_out_pulse [31:0] $end
$var wire 1 + clk $end
$var wire 32 D cps [31:0] $end
$var wire 32 E fp_add_result [31:0] $end
$var reg 32 F bram_addr [31:0] $end
$var reg 32 G bram_addr_pulse [31:0] $end
$var reg 32 H bram_data_in [31:0] $end
$var reg 32 I bram_data_in_pulse [31:0] $end
$var reg 1 % bram_we_pin $end
$var reg 1 $ bram_we_pulse $end
$var reg 32 J count [31:0] $end
$var reg 32 K count_gam [31:0] $end
$var reg 1 # ena_pin $end
$var reg 1 " ena_pulse $end
$var reg 2 L finish_pulse_gen [1:0] $end
$var reg 32 M fp_table_input [31:0] $end
$var reg 11 N lfsr [10:0] $end
$var reg 4 O mem_control_state [3:0] $end
$var reg 32 P mem_count [31:0] $end
$var reg 32 Q prev_cps [31:0] $end
$var reg 32 R prev_mem_val [31:0] $end
$scope module adder_inst $end
$var wire 32 S a [31:0] $end
$var wire 32 T b [31:0] $end
$var wire 1 U sign_b $end
$var wire 1 V sign_a $end
$var wire 32 W result [31:0] $end
$var wire 24 X mant_b [23:0] $end
$var wire 24 Y mant_a [23:0] $end
$var wire 8 Z exp_b [7:0] $end
$var wire 8 [ exp_a [7:0] $end
$var reg 24 \ aligned_a [23:0] $end
$var reg 24 ] aligned_b [23:0] $end
$var reg 8 ^ exp_diff [7:0] $end
$var reg 8 _ exp_res [7:0] $end
$var reg 23 ` frac_res [22:0] $end
$var reg 25 a mant_sum [24:0] $end
$var reg 1 b sign_res $end
$upscope $end
$upscope $end
$upscope $end
$enddefinitions $end
$comment Show the parameter values. $end
$dumpall
$end
#0
$dumpvars
xb
b0 a
b0 `
bx _
bx ^
bx ]
bx \
bx [
bx Z
bx Y
bx X
bx00000000000000000000000 W
xV
xU
bx T
bx S
b0 R
b0 Q
b0 P
b0 O
b10101010101 N
bx M
bx L
b0 K
b0 J
bx I
bx H
bx G
bx F
bx00000000000000000000000 E
b0 D
bx C
b1111101000000 B
bx A
bx @
bx ?
bx >
bx =
bx <
bx ;
bx :
bx 9
bx 8
b1111101000000 7
bx 6
bx 5
bx 4
bx 3
bx 2
bx 1
bx 0
bx /
bx .
bx -
b0 ,
0+
bx *
bx )
bx (
bx '
bx &
x%
x$
x#
x"
bx !
$end
#5000
b0 :
b0 /
b0 !
b0 L
b0 )
b0 9
b0 G
0"
0$
0#
0%
b1010101011 N
b0 *
b0 .
b0 F
1+
#10000
0+
#15000
b10101010111 N
1+
#20000
0+
#25000
b1010101111 N
1+
#30000
0+
#35000
b10101011111 N
1+
#40000
0+
#45000
b1010111111 N
1+
#50000
0+
#55000
b10101111111 N
1+
#60000
0+
#65000
b1011111111 N
1+
#70000
0+
b10 ,
b10 D
#75000
b1 !
b1 L
b10 Q
b10111111111 N
1+
#80000
0+
#85000
b1011111111100 :
b1011111111100 /
b1 O
b1 P
1"
1#
1%
b1011111111100 )
b1011111111100 9
b1011111111100 G
b1 '
b1 8
b1 I
b1011111111100 *
b1011111111100 .
b1011111111100 F
b1 (
b1 -
b1 H
b1111111110 N
1+
#90000
0+
#95000
b0 Y
b11111000101000001001000 `
b111111000101000001001000 a
0b
b111101011111000101000001001000 E
b111101011111000101000001001000 W
b1111010 _
b111111000101000001001000 ]
b0 \
b1111010 ^
b111111000101000001001000 X
0V
b0 [
0U
b1111010 Z
b0 A
b0 @
b0 ?
b0 >
b0 =
b0 <
b0 &
b0 ;
b0 C
b0 S
b0 6
b0 5
b0 4
b0 3
b0 2
b0 1
b1 0
b10 O
b111101011111000101000001001000 M
b111101011111000101000001001000 T
0"
1+
#100000
0+
#105000
b0 O
b10 P
b111101011111000101000001001000 '
b111101011111000101000001001000 8
b111101011111000101000001001000 I
1"
1$
1+
#110000
0+
#115000
b111101111111000101000001001000 E
b111101111111000101000001001000 W
b1111011 _
b111111000101000001001000 a
b111111000101000001001000 \
b0 ^
b111111000101000001001000 Y
b1111010 [
b1100000000000 :
b111101011111000101000001001000 &
b111101011111000101000001001000 ;
b111101011111000101000001001000 C
b111101011111000101000001001000 S
b1 O
0$
b1100000000000 )
b1100000000000 9
b1100000000000 G
1+
#120000
0+
#125000
b110010110010100101100 `
b100110010110010100101100 a
b100110010110010100101100 ]
b100110010110010100101100 X
b111110100110010110010100101100 E
b111110100110010110010100101100 W
b1111101 _
b0 \
b1111101 ^
b0 Y
b1111101 Z
b0 [
b10 O
b111110100110010110010100101100 M
b111110100110010110010100101100 T
0"
b0 &
b0 ;
b0 C
b0 S
1+
#130000
0+
#135000
b0 O
b11 P
b111110100110010110010100101100 '
b111110100110010110010100101100 8
b111110100110010110010100101100 I
1"
1$
1+
#140000
0+
#145000
b111111000110010110010100101100 E
b111111000110010110010100101100 W
b1111110 _
b100110010110010100101100 a
b100110010110010100101100 \
b0 ^
b100110010110010100101100 Y
b1100000000100 :
b1111101 [
b1 O
0$
b1100000000100 )
b1100000000100 9
b1100000000100 G
b111110100110010110010100101100 &
b111110100110010110010100101100 ;
b111110100110010110010100101100 C
b111110100110010110010100101100 S
1+
#150000
0+
#155000
b0 Y
b11100011101111001101 `
b100011100011101111001101 a
b111110000011100011101111001101 E
b111110000011100011101111001101 W
b1111100 _
b100011100011101111001101 ]
b0 \
b1111100 ^
b100011100011101111001101 X
b0 [
b1111100 Z
b0 &
b0 ;
b0 C
b0 S
b10 O
b111110000011100011101111001101 M
b111110000011100011101111001101 T
0"
1+
#160000
0+
#165000
b0 O
b100 P
b111110000011100011101111001101 '
b111110000011100011101111001101 8
b111110000011100011101111001101 I
1"
1$
1+
#170000
0+
#175000
b111110100011100011101111001101 E
b111110100011100011101111001101 W
b1111101 _
b100011100011101111001101 a
b100011100011101111001101 \
b0 ^
b100011100011101111001101 Y
b1111100 [
b1100000001000 :
b111110000011100011101111001101 &
b111110000011100011101111001101 ;
b111110000011100011101111001101 C
b111110000011100011101111001101 S
b1 O
0$
b1100000001000 )
b1100000001000 9
b1100000001000 G
1+
#180000
0+
#185000
b110001001001101111 `
b100000110001001001101111 a
b100000110001001001101111 ]
b100000110001001001101111 X
b111101100000110001001001101111 E
b111101100000110001001001101111 W
b1111011 _
b0 \
b1111011 ^
b0 Y
b1111011 Z
b0 [
b10 O
b111101100000110001001001101111 M
b111101100000110001001001101111 T
0"
b0 &
b0 ;
b0 C
b0 S
1+
#190000
0+
#195000
b0 O
b101 P
b111101100000110001001001101111 '
b111101100000110001001001101111 8
b111101100000110001001001101111 I
1"
1$
1+
#200000
0+
#205000
b111110000000110001001001101111 E
b111110000000110001001001101111 W
b1111100 _
b100000110001001001101111 a
b100000110001001001101111 \
b0 ^
b100000110001001001101111 Y
b1100000001100 :
b1111011 [
b1 O
0$
b1100000001100 )
b1100000001100 9
b1100000001100 G
b111101100000110001001001101111 &
b111101100000110001001001101111 ;
b111101100000110001001001101111 C
b111101100000110001001001101111 S
1+
#210000
0+
#215000
b0 Y
b11100011010100111111100 `
b111100011010100111111100 a
b111100111100011010100111111100 E
b111100111100011010100111111100 W
b1111001 _
b111100011010100111111100 ]
b0 \
b1111001 ^
b111100011010100111111100 X
b0 [
b1111001 Z
b0 &
b0 ;
b0 C
b0 S
b10 O
b111100111100011010100111111100 M
b111100111100011010100111111100 T
0"
1+
#220000
0+
#225000
b0 O
b110 P
b111100111100011010100111111100 '
b111100111100011010100111111100 8
b111100111100011010100111111100 I
1"
1$
1+
#230000
0+
#235000
b111101011100011010100111111100 E
b111101011100011010100111111100 W
b1111010 _
b111100011010100111111100 a
b111100011010100111111100 \
b0 ^
b111100011010100111111100 Y
b1111001 [
b1100000010000 :
b111100111100011010100111111100 &
b111100111100011010100111111100 ;
b111100111100011010100111111100 C
b111100111100011010100111111100 S
b1 O
0$
b1100000010000 )
b1100000010000 9
b1100000010000 G
1+
#240000
0+
#245000
b10111101101001010001001 `
b110111101101001010001001 a
b110111101101001010001001 ]
b110111101101001010001001 X
b111100010111101101001010001001 E
b111100010111101101001010001001 W
b1111000 _
b0 \
b1111000 ^
b0 Y
b1111000 Z
b0 [
b10 O
b111100010111101101001010001001 M
b111100010111101101001010001001 T
0"
b0 &
b0 ;
b0 C
b0 S
1+
#250000
0+
#255000
b0 O
b111 P
b111100010111101101001010001001 '
b111100010111101101001010001001 8
b111100010111101101001010001001 I
1"
1$
1+
#260000
0+
#265000
b111100110111101101001010001001 E
b111100110111101101001010001001 W
b1111001 _
b110111101101001010001001 a
b110111101101001010001001 \
b0 ^
b110111101101001010001001 Y
b1100000010100 :
b1111000 [
b1 O
0$
b1100000010100 )
b1100000010100 9
b1100000010100 G
b111100010111101101001010001001 &
b111100010111101101001010001001 ;
b111100010111101101001010001001 C
b111100010111101101001010001001 S
1+
#270000
0+
#275000
b0 Y
b10011100111000000111011 `
b110011100111000000111011 a
b111011110011100111000000111011 E
b111011110011100111000000111011 W
b1110111 _
b110011100111000000111011 ]
b0 \
b1110111 ^
b110011100111000000111011 X
b0 [
b1110111 Z
b0 &
b0 ;
b0 C
b0 S
b10 O
b111011110011100111000000111011 M
b111011110011100111000000111011 T
0"
1+
#280000
0+
#285000
b0 O
b1000 P
b111011110011100111000000111011 '
b111011110011100111000000111011 8
b111011110011100111000000111011 I
1"
1$
1+
#290000
0+
#295000
b111100010011100111000000111011 E
b111100010011100111000000111011 W
b1111000 _
b110011100111000000111011 a
b110011100111000000111011 \
b0 ^
b110011100111000000111011 Y
b1110111 [
b1100000011000 :
b111011110011100111000000111011 &
b111011110011100111000000111011 ;
b111011110011100111000000111011 C
b111011110011100111000000111011 S
b1 O
0$
b1100000011000 )
b1100000011000 9
b1100000011000 G
1+
#300000
0+
#305000
b1111100000110111101101 `
b101111100000110111101101 a
b101111100000110111101101 ]
b101111100000110111101101 X
b111011001111100000110111101101 E
b111011001111100000110111101101 W
b1110110 _
b0 \
b1110110 ^
b0 Y
b1110110 Z
b0 [
b10 O
b111011001111100000110111101101 M
b111011001111100000110111101101 T
0"
b0 &
b0 ;
b0 C
b0 S
1+
#310000
0+
#315000
b0 O
b1001 P
b111011001111100000110111101101 '
b111011001111100000110111101101 8
b111011001111100000110111101101 I
1"
1$
1+
#320000
0+
#325000
b111011101111100000110111101101 E
b111011101111100000110111101101 W
b1110111 _
b101111100000110111101101 a
b101111100000110111101101 \
b0 ^
b101111100000110111101101 Y
b1100000011100 :
b1110110 [
b1 O
0$
b1100000011100 )
b1100000011100 9
b1100000011100 G
b111011001111100000110111101101 &
b111011001111100000110111101101 ;
b111011001111100000110111101101 C
b111011001111100000110111101101 S
1+
#330000
0+
#335000
b0 Y
b1010100110010011000011 `
b101010100110010011000011 a
b111010101010100110010011000011 E
b111010101010100110010011000011 W
b1110101 _
b101010100110010011000011 ]
b0 \
b1110101 ^
b101010100110010011000011 X
b0 [
b1110101 Z
b0 &
b0 ;
b0 C
b0 S
b10 O
b111010101010100110010011000011 M
b111010101010100110010011000011 T
0"
1+
#340000
0+
#345000
b0 O
b1010 P
b111010101010100110010011000011 '
b111010101010100110010011000011 8
b111010101010100110010011000011 I
1"
1$
1+
#350000
0+
#355000
b111011001010100110010011000011 E
b111011001010100110010011000011 W
b1110110 _
b101010100110010011000011 a
b101010100110010011000011 \
b0 ^
b101010100110010011000011 Y
b1110101 [
b1100000100000 :
b111010101010100110010011000011 &
b111010101010100110010011000011 ;
b111010101010100110010011000011 C
b111010101010100110010011000011 S
b1 O
0$
b1100000100000 )
b1100000100000 9
b1100000100000 G
1+
#360000
0+
#365000
b111010100100101010010 `
b100111010100100101010010 a
b100111010100100101010010 ]
b100111010100100101010010 X
b111010000111010100100101010010 E
b111010000111010100100101010010 W
b1110100 _
b0 \
b1110100 ^
b0 Y
b1110100 Z
b0 [
b10 O
b111010000111010100100101010010 M
b111010000111010100100101010010 T
0"
b0 &
b0 ;
b0 C
b0 S
1+
#370000
0+
#375000
b0 O
b1011 P
b111010000111010100100101010010 '
b111010000111010100100101010010 8
b111010000111010100100101010010 I
1"
1$
1+
#380000
0+
#385000
b111010100111010100100101010010 E
b111010100111010100100101010010 W
b1110101 _
b100111010100100101010010 a
b100111010100100101010010 \
b0 ^
b100111010100100101010010 Y
b1100000100100 :
b1110100 [
b1 O
0$
b1100000100100 )
b1100000100100 9
b1100000100100 G
b111010000111010100100101010010 &
b111010000111010100100101010010 ;
b111010000111010100100101010010 C
b111010000111010100100101010010 S
1+
#390000
0+
#395000
b0 Y
b111001100111010100100101010010 E
b111001100111010100100101010010 W
b1110011 _
b0 \
b1110011 ^
b0 [
b1110011 Z
b0 &
b0 ;
b0 C
b0 S
b10 O
b111001100111010100100101010010 M
b111001100111010100100101010010 T
0"
1+
#400000
0+
#405000
b0 O
b1100 P
b111001100111010100100101010010 '
b111001100111010100100101010010 8
b111001100111010100100101010010 I
1"
1$
1+
#410000
0+
#415000
b111010000111010100100101010010 E
b111010000111010100100101010010 W
b1110100 _
b100111010100100101010010 a
b100111010100100101010010 \
b0 ^
b100111010100100101010010 Y
b1110011 [
b1100000101000 :
b111001100111010100100101010010 &
b111001100111010100100101010010 ;
b111001100111010100100101010010 C
b111001100111010100100101010010 S
b1 O
0$
b1100000101000 )
b1100000101000 9
b1100000101000 G
1+
#420000
0+
#425000
b10100011011011100010111 `
b110100011011011100010111 a
b110100011011011100010111 ]
b110100011011011100010111 X
b111000110100011011011100010111 E
b111000110100011011011100010111 W
b1110001 _
b0 \
b1110001 ^
b0 Y
b1110001 Z
b0 [
b10 O
b111000110100011011011100010111 M
b111000110100011011011100010111 T
0"
b0 &
b0 ;
b0 C
b0 S
1+
#430000
0+
#435000
b0 O
b1101 P
b111000110100011011011100010111 '
b111000110100011011011100010111 8
b111000110100011011011100010111 I
1"
1$
1+
#440000
0+
#445000
b111001010100011011011100010111 E
b111001010100011011011100010111 W
b1110010 _
b110100011011011100010111 a
b110100011011011100010111 \
b0 ^
b110100011011011100010111 Y
b1100000101100 :
b1110001 [
b1 O
0$
b1100000101100 )
b1100000101100 9
b1100000101100 G
b111000110100011011011100010111 &
b111000110100011011011100010111 ;
b111000110100011011011100010111 C
b111000110100011011011100010111 S
1+
#450000
0+
#455000
b111000110100011011011100010111 E
b111000110100011011011100010111 W
b1110001 _
b0 \
b1110001 ^
b0 Y
b0 [
b0 &
b0 ;
b0 C
b0 S
b10 O
0"
1+
#460000
0+
#465000
b0 O
b1110 P
1"
1$
1+
#470000
0+
#475000
b111001010100011011011100010111 E
b111001010100011011011100010111 W
b1110010 _
b110100011011011100010111 a
b110100011011011100010111 \
b0 ^
b110100011011011100010111 Y
b1110001 [
b111000110100011011011100010111 &
b111000110100011011011100010111 ;
b111000110100011011011100010111 C
b111000110100011011011100010111 S
b1 K
0#
0%
b0 P
0"
0$
1+
#480000
0+
#485000
b111111111000 :
b111111111000 /
b1 O
b1 P
1"
1#
1%
b111111111000 )
b111111111000 9
b111111111000 G
b1 '
b1 8
b1 I
b111111111000 *
b111111111000 .
b111111111000 F
b11111111101 N
1+
#490000
0+
#495000
b0 Y
b11111000101000001001000 `
b111111000101000001001000 a
b111101011111000101000001001000 E
b111101011111000101000001001000 W
b1111010 _
b111111000101000001001000 ]
b0 \
b1111010 ^
b111111000101000001001000 X
b0 [
b1111010 Z
b0 &
b0 ;
b0 C
b0 S
b10 O
b111101011111000101000001001000 M
b111101011111000101000001001000 T
0"
1+
#500000
0+
#505000
b0 O
b10 P
b111101011111000101000001001000 '
b111101011111000101000001001000 8
b111101011111000101000001001000 I
1"
1$
1+
#510000
0+
#515000
b111101111111000101000001001000 E
b111101111111000101000001001000 W
b1111011 _
b111111000101000001001000 a
b111111000101000001001000 \
b0 ^
b111111000101000001001000 Y
b1111010 [
b111111111100 :
b111101011111000101000001001000 &
b111101011111000101000001001000 ;
b111101011111000101000001001000 C
b111101011111000101000001001000 S
b1 O
0$
b111111111100 )
b111111111100 9
b111111111100 G
1+
#520000
0+
#525000
b110010110010100101100 `
b100110010110010100101100 a
b100110010110010100101100 ]
b100110010110010100101100 X
b111110100110010110010100101100 E
b111110100110010110010100101100 W
b1111101 _
b0 \
b1111101 ^
b0 Y
b1111101 Z
b0 [
b10 O
b111110100110010110010100101100 M
b111110100110010110010100101100 T
0"
b0 &
b0 ;
b0 C
b0 S
1+
#530000
0+
#535000
b0 O
b11 P
b111110100110010110010100101100 '
b111110100110010110010100101100 8
b111110100110010110010100101100 I
1"
1$
1+
#540000
0+
#545000
b111111000110010110010100101100 E
b111111000110010110010100101100 W
b1111110 _
b100110010110010100101100 a
b100110010110010100101100 \
b0 ^
b100110010110010100101100 Y
b1000000000000 :
b1111101 [
b1 O
0$
b1000000000000 )
b1000000000000 9
b1000000000000 G
b111110100110010110010100101100 &
b111110100110010110010100101100 ;
b111110100110010110010100101100 C
b111110100110010110010100101100 S
1+
#550000
0+
#555000
b0 Y
b11100011101111001101 `
b100011100011101111001101 a
b111110000011100011101111001101 E
b111110000011100011101111001101 W
b1111100 _
b100011100011101111001101 ]
b0 \
b1111100 ^
b100011100011101111001101 X
b0 [
b1111100 Z
b0 &
b0 ;
b0 C
b0 S
b10 O
b111110000011100011101111001101 M
b111110000011100011101111001101 T
0"
1+
#560000
0+
#565000
b0 O
b100 P
b111110000011100011101111001101 '
b111110000011100011101111001101 8
b111110000011100011101111001101 I
1"
1$
1+
#570000
0+
#575000
b111110100011100011101111001101 E
b111110100011100011101111001101 W
b1111101 _
b100011100011101111001101 a
b100011100011101111001101 \
b0 ^
b100011100011101111001101 Y
b1111100 [
b1000000000100 :
b111110000011100011101111001101 &
b111110000011100011101111001101 ;
b111110000011100011101111001101 C
b111110000011100011101111001101 S
b1 O
0$
b1000000000100 )
b1000000000100 9
b1000000000100 G
1+
#580000
0+
