Verilog_file/BRAM_Model.v
module bram(
    input  wire            clka,
    input  wire            ena,
    input  wire            wea,
    input  wire  [31:0]    addra,
    input  wire  [31:0]    dina,
    output reg   [31:0]    douta
);

    reg [31:0] mem [0:7999];
    reg [31:0] mem1;
    reg [31:0] mem2;
    reg [31:0] mem3;
    reg [31:0] mem4;
    reg [31:0] mem5;
    reg [31:0] mem6;
    reg [31:0] mem7;
    reg [31:0] mem8;
    reg [31:0] mem9;
    reg [31:0] mem10;
    reg [31:0] mem11;

    // 13비트 주소 인덱스 (0~8191까지 가능, 실제는 0~7999만 사용)
    wire [12:0] addr_index = addra[12:0];

    integer i;

    // 초기화 블록 (시뮬레이션용)
    initial begin
        for (i = 0; i <= 7999; i = i + 1) begin
            mem[i] = 32'd0;
        end
    end

    // 동기식 동작 (읽기/쓰기)
    always @(posedge clka) begin
        if (ena) begin
            if (wea != 1'b0) begin
                mem[addr_index] = dina;
            end
            douta <= mem[addr_index];

            // 디버깅용 특정 위치 레지스터 저장
            mem1 <= mem[0];
            mem2 <= mem[4];
            mem3 <= mem[8];
            mem4 <= mem[12];
            mem5 <= mem[16];
            mem6 <= mem[20];
            mem7 <= mem[24];
            mem8 <= mem[28];
            mem9 <= mem[32];
            mem10 <= mem[36];
            mem11 <= mem[40];

            // 디버깅 출력
            // $display("[READ ] MEM[%0d] [0x%08X] => 0x%08X", addr_index, dina, mem[addr_index]);
        end
    end

endmodule

Verilog_file/PulseGenFin/fp32_adder.v
module fp32_adder (
    input  [31:0] a,
    input  [31:0] b,
    output [31:0] result
);
    wire sign_a = a[31];
    wire sign_b = b[31];
    wire [7:0] exp_a = a[30:23];
    wire [7:0] exp_b = b[30:23];
    wire [23:0] mant_a = (exp_a == 0) ? {1'b0, a[22:0]} : {1'b1, a[22:0]};
    wire [23:0] mant_b = (exp_b == 0) ? {1'b0, b[22:0]} : {1'b1, b[22:0]};

    reg [7:0] exp_diff;
    reg [23:0] aligned_a, aligned_b;
    reg [7:0] exp_res;
    reg [24:0] mant_sum;
    reg sign_res;
    reg [22:0] frac_res;

    always @(*) begin
        // 지수 맞춤
        if (exp_a > exp_b) begin
            exp_diff = exp_a - exp_b;
            aligned_a = mant_a;
            aligned_b = mant_b >> exp_diff;
            exp_res = exp_a;
            sign_res = sign_a;
        end else begin
            exp_diff = exp_b - exp_a;
            aligned_a = mant_a >> exp_diff;
            aligned_b = mant_b;
            exp_res = exp_b;
            sign_res = sign_b;
        end

        // 같은 부호만 지원 (간단 버전)
        if (sign_a == sign_b) begin
            mant_sum = aligned_a + aligned_b;
            if (mant_sum[24]) begin
                mant_sum = mant_sum >> 1;
                exp_res = exp_res + 1;
            end
        end else begin
            // 부호 다르면 뺄셈인데, 여기선 간단히 무시
            mant_sum = 0;
        end

        frac_res = mant_sum[22:0];
    end

    assign result = {sign_res, exp_res, frac_res};
endmodule

Verilog_file/FinPulseGenNut.v
`timescale 1ns / 1ps
`include "./Verilog_file/BRAM_Model.v"
`include "./Verilog_file/fp32_adder.v"

module FinPulseGenNut(
    input wire clk,
    input wire [31:0] cps,
    output reg [31:0] bram_addr,
    output reg [31:0] bram_data_in,
    output reg bram_we_pin,
    output reg ena_pin,

    output reg [31:0] bram_addr_pulse,
    output reg [31:0] bram_data_in_pulse,
    output reg bram_we_pulse,
    output reg ena_pulse,

    output reg [1:0] finish_pulse_gen,

    input wire [31:0] bram_data_out_pulse
);
    // reg [9:0] lfsr = 10'b1010101010;  // 10비트 초기값
    reg [10:0] lfsr = 11'b10101010101;  // 11비트 초기값

    reg [31:0] count = 0;
    reg [31:0] prev_cps = 0;

    reg [31:0] mem_count = 0;

    reg [3:0] mem_control_state = 0;
    reg [31:0] prev_mem_val = 0;

    // Neutron Pulse Data Table
    reg [31:0] float_data [0:49];

    initial begin
        float_data[0] = 32'h3DA339C1; // 0.0797
        float_data[1] = 32'h3F59AD43; // 0.8503
        float_data[2] = 32'h3F73A29C; // 0.9517
        float_data[3] = 32'h3F652546; // 0.8951
        float_data[4] = 32'h3F4EC56D; // 0.8077
        float_data[5] = 32'h3F388CE7; // 0.7209
        float_data[6] = 32'h3F242C3D; // 0.6413
        float_data[7] = 32'h3F11EB85; // 0.57
        float_data[8] = 32'h3F01A9FC; // 0.5065
        float_data[9] = 32'h3EE67382; // 0.4501
        float_data[10] = 32'h3ECCBFB1; // 0.3999
        float_data[11] = 32'h3EB5F6FD; // 0.3554
        float_data[12] = 32'h3EA1B08A; // 0.3158
        float_data[13] = 32'h3E8FAACE; // 0.2806
        float_data[14] = 32'h3E7F4880; // 0.2493
        float_data[15] = 32'h3E62D0E5; // 0.2215
        float_data[16] = 32'h3E4985F0; // 0.1968
        float_data[17] = 32'h3E3318FC; // 0.1749
        float_data[18] = 32'h3E1F212D; // 0.1554
        float_data[19] = 32'h3E0D6A16; // 0.1381
        float_data[20] = 32'h3DFB4A23; // 0.1227
        float_data[21] = 32'h3DDF3B64; // 0.109
        float_data[22] = 32'h3DC67382; // 0.0969
        float_data[23] = 32'h3DB05532; // 0.0861
        float_data[24] = 32'h3D9CAC08; // 0.0765
        float_data[25] = 32'h3D8B4396; // 0.068
        float_data[26] = 32'h3D7765FE; // 0.0604
        float_data[27] = 32'h3D5B8BAC; // 0.0536
        float_data[28] = 32'h3D436113; // 0.0477
        float_data[29] = 32'h3D2DAB9F; // 0.0424
        float_data[30] = 32'h3D1A0275; // 0.0376
        float_data[31] = 32'h3D08CE70; // 0.0334
        float_data[32] = 32'h3CF34D6A; // 0.0297
        float_data[33] = 32'h3CD844D0; // 0.0264
        float_data[34] = 32'h3CC08312; // 0.0235
        float_data[35] = 32'h3CAA64C3; // 0.0208
        float_data[36] = 32'h3C978D50; // 0.0185
        float_data[37] = 32'h3C872B02; // 0.0165
        float_data[38] = 32'h3C6F34D7; // 0.0146
        float_data[39] = 32'h3C54FDF4; // 0.013
        float_data[40] = 32'h3C3C6A7F; // 0.0115
        float_data[41] = 32'h3C28C155; // 0.0103
        float_data[42] = 32'h3C15182B; // 0.0091
        float_data[43] = 32'h3C04B5DD; // 0.0081
        float_data[44] = 32'h3BEBEDFA; // 0.0072
        float_data[45] = 32'h3BD1B717; // 0.0064
        float_data[46] = 32'h3BBAC711; // 0.0057
        float_data[47] = 32'h3BA3D70A; // 0.005
        float_data[48] = 32'h3B9374BC; // 0.0045
        float_data[49] = 32'h3B83126F; // 0.004
    end

    wire [31:0] fp_add_result;
    reg [31:0] fp_table_input;

    fp32_adder adder_inst (
        .a(bram_data_out_pulse),
        .b(fp_table_input),         // IEEE 754
        .result(fp_add_result)
    );

    always @(posedge clk) begin
        if (cps == 0) begin
            bram_addr <= 0;
            // lfsr <= 10'b1010101010;
            // lfsr <= 11'b10101010101; // 11비트 초기값
            lfsr <= {lfsr[9:0], lfsr[10] ^ lfsr[7]}; // 11비트 LFSR로 변경 (이전 변경 값을 가져다 씀)
            count <= 0;
            prev_cps <= 0;
            bram_we_pin <= 0;
            ena_pin <= 0;

            bram_we_pulse <= 0;
            ena_pulse <= 0;
            bram_addr_pulse <= 0;

            mem_count <= 0;
            mem_control_state <= 0;

            finish_pulse_gen <= 2'b00; // 초기화 상태

        end else begin
            // cps가 변경되었을 경우 재시작
            if (cps != prev_cps) begin
                count <= 0;
                // lfsr <= 10'b1010101010;
                // lfsr <= 11'b10101010101; // 11비트 초기값
                lfsr <= {lfsr[9:0], lfsr[10] ^ lfsr[7]}; // 11비트 LFSR로 변경 (이전 변경 값을 가져다 씀)

                prev_cps <= cps;
                ena_pin <= 0;
                bram_we_pin <= 0;

                bram_we_pulse <= 0;
                ena_pulse <= 0;
                mem_count <= 0;
                mem_control_state <= 0;

                finish_pulse_gen <= 2'b01;

            end else if (count < cps) begin
                if (mem_count == 0) begin
                    // 10비트 LFSR: x^10 + x^7 + 1
                    // lfsr <= {lfsr[8:0], lfsr[9] ^ lfsr[6]};

                    lfsr <= {lfsr[9:0], lfsr[10] ^ lfsr[7]}; // 11비트 LFSR로 변경

                    bram_data_in <= 1;                    // 펄스 발생 시점 값
                    bram_addr <= 32'b100; // lfsr * 4;                // 0 ~ 1023 개 가능
                    // bram_addr <= lfsr * 4;                // 11비트 0 ~ 2047 개 가능

                    bram_data_in_pulse <= 1;              // 펄스 값
                    bram_addr_pulse <= 32'b100; //lfsr * 4;          // 0 ~ 1023 개 가능
                    // bram_addr_pulse <= lfsr * 4;                // 11비트 0 ~ 2047 개 가능

                    // Pin 메모리에 1 값 쓰기.
                    bram_we_pin <= 1;
                    ena_pin <= 1;
                    
                    // Pulse 메모리에 1 부터 증가하는 값 쓰기
                    bram_we_pulse <= 0;             // 펄스 읽기
                    ena_pulse <= 1;                 // 활성화
                    mem_count <= 1;                 // 메모리 카운트 증가

                    mem_control_state <= 1;

                end else begin
                    if (mem_count > 50) begin
                        // 메모리 카운트가 50 이상이면 펄스 종료
                        bram_we_pulse <= 0;             // 펄스 종료
                        ena_pulse <= 0;                 // 비활성화
                        mem_count <= 0;                 // 메모리 카운트 초기화

                        mem_control_state <= 0;         // BRAM 제어 상태 초기화

                        // Pin 메모리 정지
                        bram_we_pin <= 0;
                        ena_pin <= 0;
                        count <= count + 1;

                    end else begin
                        case (mem_control_state)
                            0: begin
                                bram_addr_pulse <= bram_addr_pulse + 4;
                                bram_we_pulse <= 0;     // 펄스 읽기
                                ena_pulse <= 1;
                                // 주소 유지
                                mem_control_state <= 1;
                            end
                            1: begin
                                // 대기 
                                bram_we_pulse <= 0;     // 펄스 읽기
                                ena_pulse <= 0;

                                fp_table_input <= float_data[mem_count - 1]; // 0.1 ~ 0.6

                                mem_control_state <= 2;
                            end
                            2: begin
                                // write 완료, 다음 주소로 이동
                                bram_we_pulse <= 1;     // 펄스 쓰기
                                ena_pulse <= 1;
                                
                                bram_data_in_pulse <= fp_add_result;

                                bram_addr_pulse <= bram_addr_pulse;

                                mem_count <= mem_count + 1;
                                mem_control_state <= 0; // 다음 루프
                            end
                        endcase
                    end
                end

            end else begin
                bram_we_pin <= 0;
                ena_pin <= 0;

                bram_we_pulse <= 0;
                ena_pulse <= 0;
                mem_count <= 0;

                finish_pulse_gen <= 2'b11;
            end 
        end
    end
endmodule


module tb_FinPulseGenNut();

    // Inputs
    reg clk;
    reg [31:0] cps;

    // Outputs
    wire [31:0] bram_addr;
    wire [31:0] bram_data_in;
    wire bram_we_pin;
    wire ena_pin;

    wire [31:0] bram_addr_pulse;
    wire [31:0] bram_data_in_pulse;
    wire bram_we_pulse;
    wire ena_pin_pulse;

    wire [1:0] finish_pulse_gen;

    wire [31:0] bram_data_out_pulse;

    // Instantiate the Unit Under Test (UUT)
    FinPulseGenNut uut (
        .clk(clk),
        .cps(cps),
        .bram_addr(bram_addr),
        .bram_data_in(bram_data_in),
        .bram_we_pin(bram_we_pin),
        .ena_pin(ena_pin),
        .bram_addr_pulse(bram_addr_pulse),
        .bram_data_in_pulse(bram_data_in_pulse),
        .bram_we_pulse(bram_we_pulse),
        .ena_pulse(ena_pulse),
        .finish_pulse_gen(finish_pulse_gen),
        .bram_data_out_pulse(bram_data_out_pulse)
    );

    bram pin_bram_inst (
        .clka(clk),
        .ena(ena_pin),
        .wea(bram_we_pin),
        .addra(bram_addr),
        .dina(bram_data_in),
        .douta()  // Read output not used in this test
    );

    bram pulse_bram_inst (
        .clka(clk),
        .ena(ena_pulse),
        .wea(bram_we_pulse),
        .addra(bram_addr_pulse),
        .dina(bram_data_in_pulse),
        .douta(bram_data_out_pulse)  // Read output not used in this test
    );

    // Clock generation: 10ns period
    always #5 clk = ~clk;

    initial begin
        $dumpfile("Verilog_file/FinPulseGenNut.vcd");
        $dumpvars(0, tb_FinPulseGenNut);
        // Initialize inputs
        clk = 0;
        cps = 0;

        // Wait for global reset
        #20;

        // Test 1: cps = 0 → 모듈 초기화 상태 유지
        cps = 0;
        #50;

        // Test 2: cps = 10 → 10개의 pulse 발생
        cps = 2;
        #5000;

        cps = 0;
        #50

        // Test 2: cps = 10 → 10개의 pulse 발생
        cps = 1;
        #500;

        // // Test 3: cps = 5 → 다시 시작됨 (변경된 cps 값)
        // cps = 5;
        // #500;

        // // Test 4: cps = 0 → 종료
        // cps = 0;
        // #100;

        $finish;
    end

endmodule

Verilog_file/FinPulseGenNut.vcd
$date
	Mon Aug 04 22:18:10 2025
$end
$version
	Icarus Verilog
$end
$timescale
	1ps
$end
$scope module tb_FinPulseGenNut $end
$var wire 2 ! finish_pulse_gen [1:0] $end
$var wire 1 " ena_pulse $end
$var wire 1 # ena_pin $end
$var wire 1 $ bram_we_pulse $end
$var wire 1 % bram_we_pin $end
$var wire 32 & bram_data_out_pulse [31:0] $end
$var wire 32 ' bram_data_in_pulse [31:0] $end
$var wire 32 ( bram_data_in [31:0] $end
$var wire 32 ) bram_addr_pulse [31:0] $end
$var wire 32 * bram_addr [31:0] $end
$var reg 1 + clk $end
$var reg 32 , cps [31:0] $end
$scope module pin_bram_inst $end
$var wire 1 + clka $end
$var wire 1 % wea $end
$var wire 1 # ena $end
$var wire 32 - dina [31:0] $end
$var wire 32 . addra [31:0] $end
$var wire 13 / addr_index [12:0] $end
$var reg 32 0 douta [31:0] $end
$var reg 32 1 mem1 [31:0] $end
$var reg 32 2 mem10 [31:0] $end
$var reg 32 3 mem11 [31:0] $end
$var reg 32 4 mem2 [31:0] $end
$var reg 32 5 mem3 [31:0] $end
$var reg 32 6 mem4 [31:0] $end
$var reg 32 7 mem5 [31:0] $end
$var reg 32 8 mem6 [31:0] $end
$var reg 32 9 mem7 [31:0] $end
$var reg 32 : mem8 [31:0] $end
$var reg 32 ; mem9 [31:0] $end
$var integer 32 < i [31:0] $end
$upscope $end
$scope module pulse_bram_inst $end
$var wire 1 + clka $end
$var wire 1 $ wea $end
$var wire 1 " ena $end
$var wire 32 = dina [31:0] $end
$var wire 32 > addra [31:0] $end
$var wire 13 ? addr_index [12:0] $end
$var reg 32 @ douta [31:0] $end
$var reg 32 A mem1 [31:0] $end
$var reg 32 B mem10 [31:0] $end
$var reg 32 C mem11 [31:0] $end
$var reg 32 D mem2 [31:0] $end
$var reg 32 E mem3 [31:0] $end
$var reg 32 F mem4 [31:0] $end
$var reg 32 G mem5 [31:0] $end
$var reg 32 H mem6 [31:0] $end
$var reg 32 I mem7 [31:0] $end
$var reg 32 J mem8 [31:0] $end
$var reg 32 K mem9 [31:0] $end
$var integer 32 L i [31:0] $end
$upscope $end
$scope module uut $end
$var wire 32 M bram_data_out_pulse [31:0] $end
$var wire 1 + clk $end
$var wire 32 N cps [31:0] $end
$var wire 32 O fp_add_result [31:0] $end
$var reg 32 P bram_addr [31:0] $end
$var reg 32 Q bram_addr_pulse [31:0] $end
$var reg 32 R bram_data_in [31:0] $end
$var reg 32 S bram_data_in_pulse [31:0] $end
$var reg 1 % bram_we_pin $end
$var reg 1 $ bram_we_pulse $end
$var reg 32 T count [31:0] $end
$var reg 1 # ena_pin $end
$var reg 1 " ena_pulse $end
$var reg 2 U finish_pulse_gen [1:0] $end
$var reg 32 V fp_table_input [31:0] $end
$var reg 11 W lfsr [10:0] $end
$var reg 4 X mem_control_state [3:0] $end
$var reg 32 Y mem_count [31:0] $end
$var reg 32 Z prev_cps [31:0] $end
$var reg 32 [ prev_mem_val [31:0] $end
$scope module adder_inst $end
$var wire 32 \ a [31:0] $end
$var wire 32 ] b [31:0] $end
$var wire 1 ^ sign_b $end
$var wire 1 _ sign_a $end
$var wire 32 ` result [31:0] $end
$var wire 24 a mant_b [23:0] $end
$var wire 24 b mant_a [23:0] $end
$var wire 8 c exp_b [7:0] $end
$var wire 8 d exp_a [7:0] $end
$var reg 24 e aligned_a [23:0] $end
$var reg 24 f aligned_b [23:0] $end
$var reg 8 g exp_diff [7:0] $end
$var reg 8 h exp_res [7:0] $end
$var reg 23 i frac_res [22:0] $end
$var reg 25 j mant_sum [24:0] $end
$var reg 1 k sign_res $end
$upscope $end
$upscope $end
$upscope $end
$enddefinitions $end
$comment Show the parameter values. $end
$dumpall
$end
#0
$dumpvars
xk
b0 j
b0 i
bx h
bx g
bx f
bx e
bx d
bx c
bx b
bx a
bx00000000000000000000000 `
x_
x^
bx ]
bx \
b0 [
b0 Z
b0 Y
b0 X
b10101010101 W
bx V
bx U
b0 T
bx S
bx R
bx Q
bx P
bx00000000000000000000000 O
b0 N
bx M
b1111101000000 L
bx K
bx J
bx I
bx H
bx G
bx F
bx E
bx D
bx C
bx B
bx A
bx @
bx ?
bx >
bx =
b1111101000000 <
bx ;
bx :
bx 9
bx 8
bx 7
bx 6
bx 5
bx 4
bx 3
bx 2
bx 1
bx 0
bx /
bx .
bx -
b0 ,
0+
bx *
bx )
bx (
bx '
bx &
x%
x$
x#
x"
bx !
$end
#5000
b0 ?
b0 /
b0 !
b0 U
b0 )
b0 >
b0 Q
0"
0$
0#
0%
b1010101011 W
b0 *
b0 .
b0 P
1+
#10000
0+
#15000
b10101010111 W
1+
#20000
0+
#25000
b1010101111 W
1+
#30000
0+
#35000
b10101011111 W
1+
#40000
0+
#45000
b1010111111 W
1+
#50000
0+
#55000
b10101111111 W
1+
#60000
0+
#65000
b1011111111 W
1+
#70000
0+
b10 ,
b10 N
#75000
b1 !
b1 U
b10 Z
b10111111111 W
1+
#80000
0+
#85000
b100 ?
b100 /
b1 X
b1 Y
1"
1#
1%
b100 )
b100 >
b100 Q
b1 '
b1 =
b1 S
b100 *
b100 .
b100 P
b1 (
b1 -
b1 R
b1111111110 W
1+
#90000
0+
#95000
b0 b
b1000110011100111000001 i
b101000110011100111000001 j
0k
b111101101000110011100111000001 O
b111101101000110011100111000001 `
b1111011 h
b101000110011100111000001 f
b0 e
b1111011 g
b101000110011100111000001 a
0_
b0 d
0^
b1111011 c
b0 C
b0 B
b0 K
b0 J
b0 I
b0 H
b0 G
b0 F
b0 E
b0 D
b0 A
b0 &
b0 @
b0 M
b0 \
b0 3
b0 2
b0 ;
b0 :
b0 9
b0 8
b0 7
b0 6
b0 5
b1 4
b0 1
b1 0
b10 X
b111101101000110011100111000001 V
b111101101000110011100111000001 ]
0"
1+
#100000
0+
#105000
b0 X
b10 Y
b111101101000110011100111000001 '
b111101101000110011100111000001 =
b111101101000110011100111000001 S
1"
1$
1+
#110000
0+
#115000
b111110001000110011100111000001 O
b111110001000110011100111000001 `
b1111100 h
b101000110011100111000001 j
b101000110011100111000001 e
b0 g
b101000110011100111000001 b
b1111011 d
b1000 ?
b111101101000110011100111000001 D
b111101101000110011100111000001 &
b111101101000110011100111000001 @
b111101101000110011100111000001 M
b111101101000110011100111000001 \
b1 X
0$
b1000 )
b1000 >
b1000 Q
1+
#120000
0+
#125000
b10110011010110101000011 i
b110110011010110101000011 j
b110110011010110101000011 f
b110110011010110101000011 a
b111111010110011010110101000011 O
b111111010110011010110101000011 `
b1111110 h
b0 e
b1111110 g
b0 b
b1111110 c
b0 d
b10 X
b111111010110011010110101000011 V
b111111010110011010110101000011 ]
0"
b0 &
b0 @
b0 M
b0 \
1+
#130000
0+
#135000
b0 X
b11 Y
b111111010110011010110101000011 '
b111111010110011010110101000011 =
b111111010110011010110101000011 S
1"
1$
1+
#140000
0+
#145000
b111111110110011010110101000011 O
b111111110110011010110101000011 `
b1111111 h
b110110011010110101000011 j
b110110011010110101000011 e
b0 g
b110110011010110101000011 b
b1100 ?
b1111110 d
b1 X
0$
b1100 )
b1100 >
b1100 Q
b111111010110011010110101000011 E
b111111010110011010110101000011 &
b111111010110011010110101000011 @
b111111010110011010110101000011 M
b111111010110011010110101000011 \
1+
#150000
0+
#155000
b11100111010001010011100 i
b111100111010001010011100 j
b111111011100111010001010011100 O
b111111011100111010001010011100 `
b1111110 h
b111100111010001010011100 f
b0 e
b1111110 g
b0 b
b111100111010001010011100 a
b0 d
b0 &
b0 @
b0 M
b0 \
b10 X
b111111011100111010001010011100 V
b111111011100111010001010011100 ]
0"
1+
#160000
0+
#165000
b0 X
b100 Y
b111111011100111010001010011100 '
b111111011100111010001010011100 =
b111111011100111010001010011100 S
1"
1$
1+
#170000
0+
#175000
b111111111100111010001010011100 O
b111111111100111010001010011100 `
b1111111 h
b111100111010001010011100 j
b111100111010001010011100 e
b0 g
b111100111010001010011100 b
b1111110 d
b10000 ?
b111111011100111010001010011100 F
b111111011100111010001010011100 &
b111111011100111010001010011100 @
b111111011100111010001010011100 M
b111111011100111010001010011100 \
b1 X
0$
b10000 )
b10000 >
b10000 Q
1+
#180000
0+
#185000
b11001010010010101000110 i
b111001010010010101000110 j
b111001010010010101000110 f
b111001010010010101000110 a
b111111011001010010010101000110 O
b111111011001010010010101000110 `
b1111110 h
b0 e
b1111110 g
b0 b
b0 d
b10 X
b111111011001010010010101000110 V
b111111011001010010010101000110 ]
0"
b0 &
b0 @
b0 M
b0 \
1+
#190000
0+
#195000
b0 X
b101 Y
b111111011001010010010101000110 '
b111111011001010010010101000110 =
b111111011001010010010101000110 S
1"
1$
1+
#200000
0+
#205000
b111111111001010010010101000110 O
b111111111001010010010101000110 `
b1111111 h
b111001010010010101000110 j
b111001010010010101000110 e
b0 g
b111001010010010101000110 b
b10100 ?
b1111110 d
b1 X
0$
b10100 )
b10100 >
b10100 Q
b111111011001010010010101000110 G
b111111011001010010010101000110 &
b111111011001010010010101000110 @
b111111011001010010010101000110 M
b111111011001010010010101000110 \
1+
#210000
0+
#215000
b10011101100010101101101 i
b110011101100010101101101 j
b111111010011101100010101101101 O
b111111010011101100010101101101 `
b1111110 h
b110011101100010101101101 f
b0 e
b1111110 g
b0 b
b110011101100010101101101 a
b0 d
b0 &
b0 @
b0 M
b0 \
b10 X
b111111010011101100010101101101 V
b111111010011101100010101101101 ]
0"
1+
#220000
0+
#225000
b0 X
b110 Y
b111111010011101100010101101101 '
b111111010011101100010101101101 =
b111111010011101100010101101101 S
1"
1$
1+
#230000
0+
#235000
b111111110011101100010101101101 O
b111111110011101100010101101101 `
b1111111 h
b110011101100010101101101 j
b110011101100010101101101 e
b0 g
b110011101100010101101101 b
b1111110 d
b11000 ?
b111111010011101100010101101101 H
b111111010011101100010101101101 &
b111111010011101100010101101101 @
b111111010011101100010101101101 M
b111111010011101100010101101101 \
b1 X
0$
b11000 )
b11000 >
b11000 Q
1+
#240000
0+
#245000
b1110001000110011100111 i
b101110001000110011100111 j
b101110001000110011100111 f
b101110001000110011100111 a
b111111001110001000110011100111 O
b111111001110001000110011100111 `
b1111110 h
b0 e
b1111110 g
b0 b
b0 d
b10 X
b111111001110001000110011100111 V
b111111001110001000110011100111 ]
0"
b0 &
b0 @
b0 M
b0 \
1+
#250000
0+
#255000
b0 X
b111 Y
b111111001110001000110011100111 '
b111111001110001000110011100111 =
b111111001110001000110011100111 S
1"
1$
1+
#260000
0+
#265000
b111111101110001000110011100111 O
b111111101110001000110011100111 `
b1111111 h
b101110001000110011100111 j
b101110001000110011100111 e
b0 g
b101110001000110011100111 b
b11100 ?
b1111110 d
b1 X
0$
b11100 )
b11100 >
b11100 Q
b111111001110001000110011100111 I
b111111001110001000110011100111 &
b111111001110001000110011100111 @
b111111001110001000110011100111 M
b111111001110001000110011100111 \
1+
#270000
0+
#275000
b1001000010110000111101 i
b101001000010110000111101 j
b111111001001000010110000111101 O
b111111001001000010110000111101 `
b1111110 h
b101001000010110000111101 f
b0 e
b1111110 g
b0 b
b101001000010110000111101 a
b0 d
b0 &
b0 @
b0 M
b0 \
b10 X
b111111001001000010110000111101 V
b111111001001000010110000111101 ]
0"
1+
#280000
0+
#285000
b0 X
b1000 Y
b111111001001000010110000111101 '
b111111001001000010110000111101 =
b111111001001000010110000111101 S
1"
1$
1+
#290000
0+
#295000
b111111101001000010110000111101 O
b111111101001000010110000111101 `
b1111111 h
b101001000010110000111101 j
b101001000010110000111101 e
b0 g
b101001000010110000111101 b
b1111110 d
b100000 ?
b111111001001000010110000111101 J
b111111001001000010110000111101 &
b111111001001000010110000111101 @
b111111001001000010110000111101 M
b111111001001000010110000111101 \
b1 X
0$
b100000 )
b100000 >
b100000 Q
1+
#300000
0+
#305000
b100011110101110000101 i
b100100011110101110000101 j
b100100011110101110000101 f
b100100011110101110000101 a
b111111000100011110101110000101 O
b111111000100011110101110000101 `
b1111110 h
b0 e
b1111110 g
b0 b
b0 d
b10 X
b111111000100011110101110000101 V
b111111000100011110101110000101 ]
0"
b0 &
b0 @
b0 M
b0 \
1+
#310000
0+
#315000
b0 X
b1001 Y
b111111000100011110101110000101 '
b111111000100011110101110000101 =
b111111000100011110101110000101 S
1"
1$
1+
#320000
0+
#325000
b111111100100011110101110000101 O
b111111100100011110101110000101 `
b1111111 h
b100100011110101110000101 j
b100100011110101110000101 e
b0 g
b100100011110101110000101 b
b100100 ?
b1111110 d
b1 X
0$
b100100 )
b100100 >
b100100 Q
b111111000100011110101110000101 K
b111111000100011110101110000101 &
b111111000100011110101110000101 @
b111111000100011110101110000101 M
b111111000100011110101110000101 \
1+
#330000
0+
#335000
b11010100111111100 i
b100000011010100111111100 j
b111111000000011010100111111100 O
b111111000000011010100111111100 `
b1111110 h
b100000011010100111111100 f
b0 e
b1111110 g
b0 b
b100000011010100111111100 a
b0 d
b0 &
b0 @
b0 M
b0 \
b10 X
b111111000000011010100111111100 V
b111111000000011010100111111100 ]
0"
1+
#340000
0+
#345000
b0 X
b1010 Y
b111111000000011010100111111100 '
b111111000000011010100111111100 =
b111111000000011010100111111100 S
1"
1$
1+
#350000
0+
#355000
b111111100000011010100111111100 O
b111111100000011010100111111100 `
b1111111 h
b100000011010100111111100 j
b100000011010100111111100 e
b0 g
b100000011010100111111100 b
b1111110 d
b101000 ?
b111111000000011010100111111100 B
b111111000000011010100111111100 &
b111111000000011010100111111100 @
b111111000000011010100111111100 M
b111111000000011010100111111100 \
b1 X
0$
b101000 )
b101000 >
b101000 Q
1+
#360000
0+
#365000
b11001100111001110000010 i
b111001100111001110000010 j
b111001100111001110000010 f
b111001100111001110000010 a
b111110111001100111001110000010 O
b111110111001100111001110000010 `
b1111101 h
b0 e
b1111101 g
b0 b
b1111101 c
b0 d
b10 X
b111110111001100111001110000010 V
b111110111001100111001110000010 ]
0"
b0 &
b0 @
b0 M
b0 \
1+
#370000
0+
#375000
b0 X
b1011 Y
b111110111001100111001110000010 '
b111110111001100111001110000010 =
b111110111001100111001110000010 S
1"
1$
1+
#380000
0+
#385000
b111111011001100111001110000010 O
b111111011001100111001110000010 `
b1111110 h
b111001100111001110000010 j
b111001100111001110000010 e
b0 g
b111001100111001110000010 b
b101100 ?
b1111101 d
b1 X
0$
b101100 )
b101100 >
b101100 Q
b111110111001100111001110000010 C
b111110111001100111001110000010 &
b111110111001100111001110000010 @
b111110111001100111001110000010 M
b111110111001100111001110000010 \
1+
#390000
0+
#395000
b10011001011111110110001 i
b110011001011111110110001 j
b111110110011001011111110110001 O
b111110110011001011111110110001 `
b1111101 h
b110011001011111110110001 f
b0 e
b1111101 g
b0 b
b110011001011111110110001 a
b0 d
b0 &
b0 @
b0 M
b0 \
b10 X
b111110110011001011111110110001 V
b111110110011001011111110110001 ]
0"
1+
#400000
0+
#405000
b0 X
b1100 Y
b111110110011001011111110110001 '
b111110110011001011111110110001 =
b111110110011001011111110110001 S
1"
1$
1+
#410000
0+
#415000
b111111010011001011111110110001 O
b111111010011001011111110110001 `
b1111110 h
b110011001011111110110001 j
b110011001011111110110001 e
b0 g
b110011001011111110110001 b
b1111101 d
b110000 ?
b111110110011001011111110110001 &
b111110110011001011111110110001 @
b111110110011001011111110110001 M
b111110110011001011111110110001 \
b1 X
0$
b110000 )
b110000 >
b110000 Q
1+
#420000
0+
#425000
b1101011111011011111101 i
b101101011111011011111101 j
b101101011111011011111101 f
b101101011111011011111101 a
b111110101101011111011011111101 O
b111110101101011111011011111101 `
b1111101 h
b0 e
b1111101 g
b0 b
b0 d
b10 X
b111110101101011111011011111101 V
b111110101101011111011011111101 ]
0"
b0 &
b0 @
b0 M
b0 \
1+
#430000
0+
#435000
b0 X
b1101 Y
b111110101101011111011011111101 '
b111110101101011111011011111101 =
b111110101101011111011011111101 S
1"
1$
1+
#440000
0+
#445000
b111111001101011111011011111101 O
b111111001101011111011011111101 `
b1111110 h
b101101011111011011111101 j
b101101011111011011111101 e
b0 g
b101101011111011011111101 b
b110100 ?
b1111101 d
b1 X
0$
b110100 )
b110100 >
b110100 Q
b111110101101011111011011111101 &
b111110101101011111011011111101 @
b111110101101011111011011111101 M
b111110101101011111011011111101 \
1+
#450000
0+
#455000
b1000011011000010001010 i
b101000011011000010001010 j
b111110101000011011000010001010 O
b111110101000011011000010001010 `
b1111101 h
b101000011011000010001010 f
b0 e
b1111101 g
b0 b
b101000011011000010001010 a
b0 d
b0 &
b0 @
b0 M
b0 \
b10 X
b111110101000011011000010001010 V
b111110101000011011000010001010 ]
0"
1+
#460000
0+
#465000
b0 X
b1110 Y
b111110101000011011000010001010 '
b111110101000011011000010001010 =
b111110101000011011000010001010 S
1"
1$
1+
#470000
0+
#475000
b111111001000011011000010001010 O
b111111001000011011000010001010 `
b1111110 h
b101000011011000010001010 j
b101000011011000010001010 e
b0 g
b101000011011000010001010 b
b1111101 d
b111000 ?
b111110101000011011000010001010 &
b111110101000011011000010001010 @
b111110101000011011000010001010 M
b111110101000011011000010001010 \
b1 X
0$
b111000 )
b111000 >
b111000 Q
1+
#480000
0+
#485000
b11111010101011001110 i
b100011111010101011001110 j
b100011111010101011001110 f
b100011111010101011001110 a
b111110100011111010101011001110 O
b111110100011111010101011001110 `
b1111101 h
b0 e
b1111101 g
b0 b
b0 d
b10 X
b111110100011111010101011001110 V
b111110100011111010101011001110 ]
0"
b0 &
b0 @
b0 M
b0 \
1+
#490000
0+
