Verilog_file/PulseGenStM.v
`timescale 1ns / 1ps

module PulseGenStM(
    input wire clk,
    input wire [31:0] cps,
    output reg [31:0] bram_addr,
    output reg [31:0] bram_data_in,
    output reg [31:0] bram_data_pulse_in,
    output reg bram_we,
    output reg ena
);
    // 상태 정의
    parameter IDLE = 2'b00,
              INIT = 2'b01,
              RUN  = 2'b10,
              DONE = 2'b11;
    parameter GEN_LFSR = 2'b00;
    parameter READ_MEM = 2'b01;

    reg [1:0] state = IDLE;
    reg [1:0] sub_state = GEN_LFSR;

    reg [9:0] lfsr = 10'b1010101010;
    reg [31:0] count = 0;
    reg [31:0] sub_count = 0;
    reg [31:0] prev_cps = 0;

    always @(posedge clk) begin
        case (state)
            IDLE: begin
                bram_we <= 0;
                ena <= 0;
                bram_addr <= 0;
                bram_data_in <= 0;
                count <= 0;
                lfsr <= 10'b1010101010;

                sub_count <= 0;
                sub_state <= GEN_LFSR;

                if (cps > 0) begin
                    prev_cps <= cps;
                    state <= INIT;
                end
            end

            INIT: begin
                count <= 0;
                lfsr <= 10'b1010101010;
                bram_we <= 0;
                ena <= 0;
                state <= RUN;

                sub_count <= 0;
                sub_state <= GEN_LFSR;
            end

            RUN: begin
                if (cps != prev_cps) begin
                    prev_cps <= cps;
                    state <= INIT;

                    sub_count <= 0;
                    sub_state <= GEN_LFSR;
                end else if (count < cps) begin
                    case (sub_state)
                        GEN_LFSR: begin
                            // LFSR를 이용하여 주소 생성
                            lfsr <= {lfsr[8:0], lfsr[9] ^ lfsr[6]};
                            bram_addr <= lfsr * 4;  // 예시로 4배수 주소 사용
                            bram_data_in <= 1;      // 예시 데이터
                            bram_we <= 1;
                            ena <= 1;
                            count <= count + 1;
                            
                            sub_count <= 0;
                            sub_state <= READ_MEM; // 계속 LFSR 생성
                        end
                        READ_MEM: begin
                            // 현재 펄스 발생 시점 주소값 보내기
                            bram_addr <= bram_addr + sub_count * 4;  // 예시로 4배수 주소 사용
                            bram_data_in <= sub_count + 2;

                            sub_count <= sub_count + 1;

                            if (sub_count >= 10) begin
                                sub_state <= GEN_LFSR; // 다음 LFSR 생성으로 전환
                            end else begin
                                sub_state <= READ_MEM; // 계속 읽기 상태 유지
                            end

                        end

                        default: begin
                            bram_we <= 0;
                            ena <= 0;
                        end
                    endcase

                end else begin
                    state <= DONE;
                end
            end

            DONE: begin
                bram_we <= 0;
                ena <= 0;
                if (cps == 0) begin
                    state <= IDLE;
                end else if (cps != prev_cps) begin
                    prev_cps <= cps;
                    state <= INIT;
                end
            end

            default: state <= IDLE;
        endcase
    end

endmodule


module tb_PulseGenStM();

    // Inputs
    reg clk;
    reg [31:0] cps;

    // Outputs
    wire [31:0] bram_addr;
    wire [31:0] bram_data_in;
    wire bram_we;
    wire ena;

    // Instantiate the Unit Under Test (UUT)
    PulseGenStM uut (
        .clk(clk),
        .cps(cps),
        .bram_addr(bram_addr),
        .bram_data_in(bram_data_in),
        .bram_we(bram_we),
        .ena(ena)
    );

    // Clock generation: 10ns period
    always #5 clk = ~clk;

    initial begin
        $dumpfile("Verilog_file/PulseGenStM.vcd");
        $dumpvars(0, tb_PulseGenStM);
        // Initialize inputs
        clk = 0;
        cps = 0;

        // Wait for global reset
        #20;

        // Test 1: cps = 0 → 모듈 초기화 상태 유지
        cps = 0;
        #50;

        // Test 2: cps = 10 → 10개의 pulse 발생
        cps = 10;
        #1000;

        // Test 3: cps = 5 → 다시 시작됨 (변경된 cps 값)
        cps = 5;
        #500;

        // Test 4: cps = 0 → 종료
        cps = 0;
        #100;

        $finish;
    end

endmodule

Verilog_file/PulseGenStM.vcd
$date
	Tue Jul 29 15:05:57 2025
$end
$version
	Icarus Verilog
$end
$timescale
	1ps
$end
$scope module tb_PulseGenStM $end
$var wire 1 ! ena $end
$var wire 1 " bram_we $end
$var wire 32 # bram_data_in [31:0] $end
$var wire 32 $ bram_addr [31:0] $end
$var reg 1 % clk $end
$var reg 32 & cps [31:0] $end
$scope module uut $end
$var wire 1 % clk $end
$var wire 32 ' cps [31:0] $end
$var parameter 2 ( DONE $end
$var parameter 2 ) GEN_LFSR $end
$var parameter 2 * IDLE $end
$var parameter 2 + INIT $end
$var parameter 2 , READ_MEM $end
$var parameter 2 - RUN $end
$var reg 32 . bram_addr [31:0] $end
$var reg 32 / bram_data_in [31:0] $end
$var reg 1 " bram_we $end
$var reg 32 0 count [31:0] $end
$var reg 1 ! ena $end
$var reg 10 1 lfsr [9:0] $end
$var reg 32 2 prev_cps [31:0] $end
$var reg 2 3 state [1:0] $end
$var reg 32 4 sub_count [31:0] $end
$var reg 2 5 sub_state [1:0] $end
$upscope $end
$upscope $end
$enddefinitions $end
$comment Show the parameter values. $end
$dumpall
b10 -
b1 ,
b1 +
b0 *
b0 )
b11 (
$end
#0
$dumpvars
b0 5
b0 4
b0 3
b0 2
b1010101010 1
b0 0
bx /
bx .
b0 '
b0 &
0%
bx $
bx #
x"
x!
$end
#5000
b0 #
b0 /
b0 $
b0 .
0!
0"
1%
#10000
0%
#15000
1%
#20000
0%
#25000
1%
#30000
0%
#35000
1%
#40000
0%
#45000
1%
#50000
0%
#55000
1%
#60000
0%
#65000
1%
#70000
0%
b1010 &
b1010 '
#75000
b1 3
b1010 2
1%
#80000
0%
#85000
b10 3
1%
#90000
0%
#95000
b1 5
b1 0
1!
1"
b1 #
b1 /
b101010101000 $
b101010101000 .
b101010101 1
1%
#100000
0%
#105000
b1 4
b10 #
b10 /
1%
#110000
0%
#115000
b10 4
b11 #
b11 /
b101010101100 $
b101010101100 .
1%
#120000
0%
#125000
b11 4
b100 #
b100 /
b101010110100 $
b101010110100 .
1%
#130000
0%
#135000
b100 4
b101 #
b101 /
b101011000000 $
b101011000000 .
1%
#140000
0%
#145000
b101 4
b110 #
b110 /
b101011010000 $
b101011010000 .
1%
#150000
0%
#155000
b110 4
b111 #
b111 /
b101011100100 $
b101011100100 .
1%
#160000
0%
#165000
b111 4
b1000 #
b1000 /
b101011111100 $
b101011111100 .
1%
#170000
0%
#175000
b1000 4
b1001 #
b1001 /
b101100011000 $
b101100011000 .
1%
#180000
0%
#185000
b1001 4
b1010 #
b1010 /
b101100111000 $
b101100111000 .
1%
#190000
0%
#195000
b1010 4
b1011 #
b1011 /
b101101011100 $
b101101011100 .
1%
#200000
0%
#205000
b0 5
b1011 4
b1100 #
b1100 /
b101110000100 $
b101110000100 .
1%
#210000
0%
#215000
b1 5
b0 4
b10 0
b1 #
b1 /
b10101010100 $
b10101010100 .
b1010101011 1
1%
#220000
0%
#225000
b1 4
b10 #
b10 /
1%
#230000
0%
#235000
b10 4
b11 #
b11 /
b10101011000 $
b10101011000 .
1%
#240000
0%
#245000
b11 4
b100 #
b100 /
b10101100000 $
b10101100000 .
1%
#250000
0%
#255000
b100 4
b101 #
b101 /
b10101101100 $
b10101101100 .
1%
#260000
0%
#265000
b101 4
b110 #
b110 /
b10101111100 $
b10101111100 .
1%
#270000
0%
#275000
b110 4
b111 #
b111 /
b10110010000 $
b10110010000 .
1%
#280000
0%
#285000
b111 4
b1000 #
b1000 /
b10110101000 $
b10110101000 .
1%
#290000
0%
#295000
b1000 4
b1001 #
b1001 /
b10111000100 $
b10111000100 .
1%
#300000
0%
#305000
b1001 4
b1010 #
b1010 /
b10111100100 $
b10111100100 .
1%
#310000
0%
#315000
b1010 4
b1011 #
b1011 /
b11000001000 $
b11000001000 .
1%
#320000
0%
#325000
b0 5
b1011 4
b1100 #
b1100 /
b11000110000 $
b11000110000 .
1%
#330000
0%
#335000
b1 5
b0 4
b11 0
b1 #
b1 /
b101010101100 $
b101010101100 .
b101010111 1
1%
#340000
0%
#345000
b1 4
b10 #
b10 /
1%
#350000
0%
#355000
b10 4
b11 #
b11 /
b101010110000 $
b101010110000 .
1%
#360000
0%
#365000
b11 4
b100 #
b100 /
b101010111000 $
b101010111000 .
1%
#370000
0%
#375000
b100 4
b101 #
b101 /
b101011000100 $
b101011000100 .
1%
#380000
0%
#385000
b101 4
b110 #
b110 /
b101011010100 $
b101011010100 .
1%
#390000
0%
#395000
b110 4
b111 #
b111 /
b101011101000 $
b101011101000 .
1%
#400000
0%
#405000
b111 4
b1000 #
b1000 /
b101100000000 $
b101100000000 .
1%
#410000
0%
#415000
b1000 4
b1001 #
b1001 /
b101100011100 $
b101100011100 .
1%
#420000
0%
#425000
b1001 4
b1010 #
b1010 /
b101100111100 $
b101100111100 .
1%
#430000
0%
#435000
b1010 4
b1011 #
b1011 /
b101101100000 $
b101101100000 .
1%
#440000
0%
#445000
b0 5
b1011 4
b1100 #
b1100 /
b101110001000 $
b101110001000 .
1%
#450000
0%
#455000
b1 5
b0 4
b100 0
b1 #
b1 /
b10101011100 $
b10101011100 .
b1010101111 1
1%
#460000
0%
#465000
b1 4
b10 #
b10 /
1%
#470000
0%
#475000
b10 4
b11 #
b11 /
b10101100000 $
b10101100000 .
1%
#480000
0%
#485000
b11 4
b100 #
b100 /
b10101101000 $
b10101101000 .
1%
#490000
0%
#495000
b100 4
b101 #
b101 /
b10101110100 $
b10101110100 .
1%
#500000
0%
#505000
b101 4
b110 #
b110 /
b10110000100 $
b10110000100 .
1%
#510000
0%
#515000
b110 4
b111 #
b111 /
b10110011000 $
b10110011000 .
1%
#520000
0%
#525000
b111 4
b1000 #
b1000 /
b10110110000 $
b10110110000 .
1%
#530000
0%
#535000
b1000 4
b1001 #
b1001 /
b10111001100 $
b10111001100 .
1%
#540000
0%
#545000
b1001 4
b1010 #
b1010 /
b10111101100 $
b10111101100 .
1%
#550000
0%
#555000
b1010 4
b1011 #
b1011 /
b11000010000 $
b11000010000 .
1%
#560000
0%
#565000
b0 5
b1011 4
b1100 #
b1100 /
b11000111000 $
b11000111000 .
1%
#570000
0%
#575000
b1 5
b0 4
b101 0
b1 #
b1 /
b101010111100 $
b101010111100 .
b101011111 1
1%
#580000
0%
#585000
b1 4
b10 #
b10 /
1%
#590000
0%
#595000
b10 4
b11 #
b11 /
b101011000000 $
b101011000000 .
1%
#600000
0%
#605000
b11 4
b100 #
b100 /
b101011001000 $
b101011001000 .
1%
#610000
0%
#615000
b100 4
b101 #
b101 /
b101011010100 $
b101011010100 .
1%
#620000
0%
#625000
b101 4
b110 #
b110 /
b101011100100 $
b101011100100 .
1%
#630000
0%
#635000
b110 4
b111 #
b111 /
b101011111000 $
b101011111000 .
1%
#640000
0%
#645000
b111 4
b1000 #
b1000 /
b101100010000 $
b101100010000 .
1%
#650000
0%
#655000
b1000 4
b1001 #
b1001 /
b101100101100 $
b101100101100 .
1%
#660000
0%
#665000
b1001 4
b1010 #
b1010 /
b101101001100 $
b101101001100 .
1%
#670000
0%
#675000
b1010 4
b1011 #
b1011 /
b101101110000 $
b101101110000 .
1%
#680000
0%
#685000
b0 5
b1011 4
b1100 #
b1100 /
b101110011000 $
b101110011000 .
1%
#690000
0%
#695000
b1 5
b0 4
b110 0
b1 #
b1 /
b10101111100 $
b10101111100 .
b1010111111 1
1%
#700000
0%
#705000
b1 4
b10 #
b10 /
1%
#710000
0%
#715000
b10 4
b11 #
b11 /
b10110000000 $
b10110000000 .
1%
#720000
0%
#725000
b11 4
b100 #
b100 /
b10110001000 $
b10110001000 .
1%
#730000
0%
#735000
b100 4
b101 #
b101 /
b10110010100 $
b10110010100 .
1%
#740000
0%
#745000
b101 4
b110 #
b110 /
b10110100100 $
b10110100100 .
1%
#750000
0%
#755000
b110 4
b111 #
b111 /
b10110111000 $
b10110111000 .
1%
#760000
0%
#765000
b111 4
b1000 #
b1000 /
b10111010000 $
b10111010000 .
1%
#770000
0%
#775000
b1000 4
b1001 #
b1001 /
b10111101100 $
b10111101100 .
1%
#780000
0%
#785000
b1001 4
b1010 #
b1010 /
b11000001100 $
b11000001100 .
1%
#790000
0%
#795000
b1010 4
b1011 #
b1011 /
b11000110000 $
b11000110000 .
1%
#800000
0%
#805000
b0 5
b1011 4
b1100 #
b1100 /
b11001011000 $
b11001011000 .
1%
#810000
0%
#815000
b1 5
b0 4
b111 0
b1 #
b1 /
b101011111100 $
b101011111100 .
b101111111 1
1%
#820000
0%
#825000
b1 4
b10 #
b10 /
1%
#830000
0%
#835000
b10 4
b11 #
b11 /
b101100000000 $
b101100000000 .
1%
#840000
0%
#845000
b11 4
b100 #
b100 /
b101100001000 $
b101100001000 .
1%
#850000
0%
#855000
b100 4
b101 #
b101 /
b101100010100 $
b101100010100 .
1%
#860000
0%
#865000
b101 4
b110 #
b110 /
b101100100100 $
b101100100100 .
1%
#870000
0%
#875000
b110 4
b111 #
b111 /
b101100111000 $
b101100111000 .
1%
#880000
0%
#885000
b111 4
b1000 #
b1000 /
b101101010000 $
b101101010000 .
1%
#890000
0%
#895000
b1000 4
b1001 #
b1001 /
b101101101100 $
b101101101100 .
1%
#900000
0%
#905000
b1001 4
b1010 #
b1010 /
b101110001100 $
b101110001100 .
1%
#910000
0%
#915000
b1010 4
b1011 #
b1011 /
b101110110000 $
b101110110000 .
1%
#920000
0%
#925000
b0 5
b1011 4
b1100 #
b1100 /
b101111011000 $
b101111011000 .
1%
#930000
0%
#935000
b1 5
b0 4
b1000 0
b1 #
b1 /
b10111111100 $
b10111111100 .
b1011111111 1
1%
#940000
0%
#945000
b1 4
b10 #
b10 /
1%
#950000
0%
#955000
b10 4
b11 #
b11 /
b11000000000 $
b11000000000 .
1%
#960000
0%
#965000
b11 4
b100 #
b100 /
b11000001000 $
b11000001000 .
1%
#970000
0%
#975000
b100 4
b101 #
b101 /
b11000010100 $
b11000010100 .
1%
#980000
0%
#985000
b101 4
b110 #
b110 /
b11000100100 $
b11000100100 .
1%
#990000
0%
#995000
b110 4
b111 #
b111 /
b11000111000 $
b11000111000 .
1%
#1000000
0%
#1005000
b111 4
b1000 #
b1000 /
b11001010000 $
b11001010000 .
1%
#1010000
0%
#1015000
b1000 4
b1001 #
b1001 /
b11001101100 $
b11001101100 .
1%
#1020000
0%
#1025000
b1001 4
b1010 #
b1010 /
b11010001100 $
b11010001100 .
1%
#1030000
0%
#1035000
b1010 4
b1011 #
b1011 /
b11010110000 $
b11010110000 .
1%
#1040000
0%
#1045000
b0 5
b1011 4
b1100 #
b1100 /
b11011011000 $
b11011011000 .
1%
#1050000
0%
#1055000
b1 5
b0 4
b1001 0
b1 #
b1 /
b101111111100 $
b101111111100 .
b111111110 1
1%
#1060000
0%
#1065000
b1 4
b10 #
b10 /
1%
#1070000
0%
b101 &
b101 '
#1075000
b0 5
b0 4
b1 3
b101 2
1%
#1080000
0%
#1085000
b10 3
0!
0"
b1010101010 1
b0 0
1%
#1090000
0%
#1095000
b1 5
b1 0
1!
1"
b1 #
b1 /
b101010101000 $
b101010101000 .
b101010101 1
1%
#1100000
0%
#1105000
b1 4
b10 #
b10 /
1%
#1110000
0%
#1115000
b10 4
b11 #
b11 /
b101010101100 $
b101010101100 .
1%
#1120000
0%
#1125000
b11 4
b100 #
b100 /
b101010110100 $
b101010110100 .
1%
#1130000
0%
#1135000
b100 4
b101 #
b101 /
b101011000000 $
b101011000000 .
1%
#1140000
0%
#1145000
b101 4
b110 #
b110 /
b101011010000 $
b101011010000 .
1%
#1150000
0%
#1155000
b110 4
b111 #
b111 /
b101011100100 $
b101011100100 .
1%
#1160000
0%
#1165000
b111 4
b1000 #
b1000 /
b101011111100 $
b101011111100 .
1%
#1170000
0%
#1175000
b1000 4
b1001 #
b1001 /
b101100011000 $
b101100011000 .
1%
#1180000
0%
#1185000
b1001 4
b1010 #
b1010 /
b101100111000 $
b101100111000 .
1%
#1190000
0%
#1195000
b1010 4
b1011 #
b1011 /
b101101011100 $
b101101011100 .
1%
#1200000
0%
#1205000
b0 5
b1011 4
b1100 #
b1100 /
b101110000100 $
b101110000100 .
1%
#1210000
0%
#1215000
b1 5
b0 4
b10 0
b1 #
b1 /
b10101010100 $
b10101010100 .
b1010101011 1
1%
#1220000
0%
#1225000
b1 4
b10 #
b10 /
1%
#1230000
0%
#1235000
b10 4
b11 #
b11 /
b10101011000 $
b10101011000 .
1%
#1240000
0%
#1245000
b11 4
b100 #
b100 /
b10101100000 $
b10101100000 .
1%
#1250000
0%
#1255000
b100 4
b101 #
b101 /
b10101101100 $
b10101101100 .
1%
#1260000
0%
#1265000
b101 4
b110 #
b110 /
b10101111100 $
b10101111100 .
1%
#1270000
0%
#1275000
b110 4
b111 #
b111 /
b10110010000 $
b10110010000 .
1%
#1280000
0%
#1285000
b111 4
b1000 #
b1000 /
b10110101000 $
b10110101000 .
1%
#1290000
0%
#1295000
b1000 4
b1001 #
b1001 /
b10111000100 $
b10111000100 .
1%
#1300000
0%
#1305000
b1001 4
b1010 #
b1010 /
b10111100100 $
b10111100100 .
1%
#1310000
0%
#1315000
b1010 4
b1011 #
b1011 /
b11000001000 $
b11000001000 .
1%
#1320000
0%
#1325000
b0 5
b1011 4
b1100 #
b1100 /
b11000110000 $
b11000110000 .
1%
#1330000
0%
#1335000
b1 5
b0 4
b11 0
b1 #
b1 /
b101010101100 $
b101010101100 .
b101010111 1
1%
#1340000
0%
#1345000
b1 4
b10 #
b10 /
1%
#1350000
0%
#1355000
b10 4
b11 #
b11 /
b101010110000 $
b101010110000 .
1%
#1360000
0%
#1365000
b11 4
b100 #
b100 /
b101010111000 $
b101010111000 .
1%
#1370000
0%
#1375000
b100 4
b101 #
b101 /
b101011000100 $
b101011000100 .
1%
#1380000
0%
#1385000
b101 4
b110 #
b110 /
b101011010100 $
b101011010100 .
1%
#1390000
0%
#1395000
b110 4
b111 #
b111 /
b101011101000 $
b101011101000 .
1%
#1400000
0%
#1405000
b111 4
b1000 #
b1000 /
b101100000000 $
b101100000000 .
1%
#1410000
0%
#1415000
b1000 4
b1001 #
b1001 /
b101100011100 $
b101100011100 .
1%
#1420000
0%
#1425000
b1001 4
b1010 #
b1010 /
b101100111100 $
b101100111100 .
1%
#1430000
0%
#1435000
b1010 4
b1011 #
b1011 /
b101101100000 $
b101101100000 .
1%
#1440000
0%
#1445000
b0 5
b1011 4
b1100 #
b1100 /
b101110001000 $
b101110001000 .
1%
#1450000
0%
#1455000
b1 5
b0 4
b100 0
b1 #
b1 /
b10101011100 $
b10101011100 .
b1010101111 1
1%
#1460000
0%
#1465000
b1 4
b10 #
b10 /
1%
#1470000
0%
#1475000
b10 4
b11 #
b11 /
b10101100000 $
b10101100000 .
1%
#1480000
0%
#1485000
b11 4
b100 #
b100 /
b10101101000 $
b10101101000 .
1%
#1490000
0%
#1495000
b100 4
b101 #
b101 /
b10101110100 $
b10101110100 .
1%
#1500000
0%
#1505000
b101 4
b110 #
b110 /
b10110000100 $
b10110000100 .
1%
#1510000
0%
#1515000
b110 4
b111 #
b111 /
b10110011000 $
b10110011000 .
1%
#1520000
0%
#1525000
b111 4
b1000 #
b1000 /
b10110110000 $
b10110110000 .
1%
#1530000
0%
#1535000
b1000 4
b1001 #
b1001 /
b10111001100 $
b10111001100 .
1%
#1540000
0%
#1545000
b1001 4
b1010 #
b1010 /
b10111101100 $
b10111101100 .
1%
#1550000
0%
#1555000
b1010 4
b1011 #
b1011 /
b11000010000 $
b11000010000 .
1%
#1560000
0%
#1565000
b0 5
b1011 4
b1100 #
b1100 /
b11000111000 $
b11000111000 .
1%
#1570000
0%
b0 &
b0 '
#1575000
b0 4
b1 3
b0 2
1%
#1580000
0%
#1585000
b10 3
0!
0"
b1010101010 1
b0 0
1%
#1590000
0%
#1595000
b11 3
1%
#1600000
0%
#1605000
b0 3
1%
#1610000
0%
#1615000
b0 #
b0 /
b0 $
b0 .
1%
