Verilog_file/BRAM_Model.v
module bram(
    input  wire            clka,
    input  wire            ena,
    input  wire            wea,
    input  wire  [31:0]    addra,
    input  wire  [31:0]    dina,
    output reg   [31:0]    douta
);

    reg [31:0] mem [0:7999];
    reg [31:0] mem1;
    reg [31:0] mem2;
    reg [31:0] mem3;
    reg [31:0] mem4;
    reg [31:0] mem5;
    reg [31:0] mem6;
    reg [31:0] mem7;
    reg [31:0] mem8;
    reg [31:0] mem9;
    reg [31:0] mem10;
    reg [31:0] mem11;

    // 13비트 주소 인덱스 (0~8191까지 가능, 실제는 0~7999만 사용)
    wire [12:0] addr_index = addra[12:0];

    integer i;

    // 초기화 블록 (시뮬레이션용)
    initial begin
        for (i = 0; i <= 7999; i = i + 1) begin
            mem[i] = 32'd0;
        end
    end

    // 동기식 동작 (읽기/쓰기)
    always @(posedge clka) begin
        if (ena) begin
            if (wea != 1'b0) begin
                mem[addr_index] = dina;
            end
            douta <= mem[addr_index];

            // 디버깅용 특정 위치 레지스터 저장
            mem1 <= mem[0];
            mem2 <= mem[4];
            mem3 <= mem[8];
            mem4 <= mem[12];
            mem5 <= mem[16];
            mem6 <= mem[20];
            mem7 <= mem[24];
            mem8 <= mem[28];
            mem9 <= mem[32];
            mem10 <= mem[36];
            mem11 <= mem[40];

            // 디버깅 출력
            // $display("[READ ] MEM[%0d] [0x%08X] => 0x%08X", addr_index, dina, mem[addr_index]);
        end
    end

endmodule

Verilog_file/PulseGenFin/fp32_adder.v
module fp32_adder (
    input  [31:0] a,
    input  [31:0] b,
    output [31:0] result
);
    wire sign_a = a[31];
    wire sign_b = b[31];
    wire [7:0] exp_a = a[30:23];
    wire [7:0] exp_b = b[30:23];
    wire [23:0] mant_a = (exp_a == 0) ? {1'b0, a[22:0]} : {1'b1, a[22:0]};
    wire [23:0] mant_b = (exp_b == 0) ? {1'b0, b[22:0]} : {1'b1, b[22:0]};

    reg [7:0] exp_diff;
    reg [23:0] aligned_a, aligned_b;
    reg [7:0] exp_res;
    reg [24:0] mant_sum;
    reg sign_res;
    reg [22:0] frac_res;

    always @(*) begin
        // 지수 맞춤
        if (exp_a > exp_b) begin
            exp_diff = exp_a - exp_b;
            aligned_a = mant_a;
            aligned_b = mant_b >> exp_diff;
            exp_res = exp_a;
            sign_res = sign_a;
        end else begin
            exp_diff = exp_b - exp_a;
            aligned_a = mant_a >> exp_diff;
            aligned_b = mant_b;
            exp_res = exp_b;
            sign_res = sign_b;
        end

        // 같은 부호만 지원 (간단 버전)
        if (sign_a == sign_b) begin
            mant_sum = aligned_a + aligned_b;
            if (mant_sum[24]) begin
                mant_sum = mant_sum >> 1;
                exp_res = exp_res + 1;
            end
        end else begin
            // 부호 다르면 뺄셈인데, 여기선 간단히 무시
            mant_sum = 0;
        end

        frac_res = mant_sum[22:0];
    end

    assign result = {sign_res, exp_res, frac_res};
endmodule

Verilog_file/PulseGenSpeed/PulseGenSpeedGam.v
`timescale 1ns / 1ps
`include "./Verilog_file/PulseGenSpeed/BRAM_Model.v"
`include "./Verilog_file/PulseGenSpeed/fp32_adder.v"

module PulseGenSpeedGam(
    input wire clk,
    input wire [31:0] cps,
    output reg [31:0] bram_addr,
    output reg [31:0] bram_data_in,
    output reg bram_we,
    output reg bram_ena,
    input wire [31:0] bram_data_out
);
    // reg [9:0] lfsr = 10'b1010101010;  // 10비트 초기값
    reg [10:0] lfsr = 11'b10101010101;  // 11비트 초기값
    reg [31:0] count = 0;
    reg [31:0] prev_cps = 0;
    reg [31:0] mem_count = 0;
    reg [1:0]  mem_gam_count = 0;
    reg [3:0]  mem_control_state = 0;

    // Neutron Pulse Data Table
    reg [31:0] float_data [0:12];

    initial begin
        float_data[0] = 32'h3D7C5048; // 0.0616
        float_data[1] = 32'h3E99652C; // 0.2996
        float_data[2] = 32'h3E0E3BCD; // 0.1389
        float_data[3] = 32'h3D83126F; // 0.0640
        float_data[4] = 32'h3CF1A9FC; // 0.0295
        float_data[5] = 32'h3C5ED289; // 0.0136
        float_data[6] = 32'h3BCE703B; // 0.0063
        float_data[7] = 32'h3B3E0DED; // 0.0029
        float_data[8] = 32'h3AAA64C3; // 0.0013
        float_data[9] = 32'h3A1D4952; // 0.0006
        float_data[10] = 32'h399D4952; // 0.0003
        float_data[11] = 32'h38D1B717; // 0.0001
        float_data[12] = 32'h38D1B717; // 0.0001
    end

    reg [31:0] save_data [0:12];
    initial begin
        save_data[0] = 32'd0;
        save_data[1] = 32'd0;
        save_data[2] = 32'd0;
        save_data[3] = 32'd0;
        save_data[4] = 32'd0;
        save_data[5] = 32'd0;
        save_data[6] = 32'd0;
        save_data[7] = 32'd0;
        save_data[8] = 32'd0;
        save_data[9] = 32'd0;
        save_data[10] = 32'd0;
        save_data[11] = 32'd0;
        save_data[12] = 32'd0;
    end
    
    reg [2:0] state;

    wire [31:0] float_add_result_0;
    wire [31:0] float_add_result_1;
    wire [31:0] float_add_result_2;
    wire [31:0] float_add_result_3;
    wire [31:0] float_add_result_4;
    wire [31:0] float_add_result_5;
    wire [31:0] float_add_result_6;
    wire [31:0] float_add_result_7;
    wire [31:0] float_add_result_8;
    wire [31:0] float_add_result_9;
    wire [31:0] float_add_result_10;
    wire [31:0] float_add_result_11;
    wire [31:0] float_add_result_12;
    // fp32_adder 모듈 인스턴스화
    fp32_adder adder0 (
        .a(save_data[0]),
        .b(float_data[0]),
        .result(float_add_result_0)
    );
    fp32_adder adder1 (
        .a(save_data[1]),
        .b(float_data[1]),
        .result(float_add_result_1)
    );
    fp32_adder adder2 (
        .a(save_data[2]),
        .b(float_data[2]),
        .result(float_add_result_2)
    );
    fp32_adder adder3 (
        .a(save_data[3]),
        .b(float_data[3]),
        .result(float_add_result_3)
    );
    fp32_adder adder4 (
        .a(save_data[4]),
        .b(float_data[4]),
        .result(float_add_result_4)
    );
    fp32_adder adder5 (
        .a(save_data[5]),
        .b(float_data[5]),
        .result(float_add_result_5)
    );
    fp32_adder adder6 (
        .a(save_data[6]),
        .b(float_data[6]),
        .result(float_add_result_6)
    );
    fp32_adder adder7 (
        .a(save_data[7]),
        .b(float_data[7]),
        .result(float_add_result_7)
    );
    fp32_adder adder8 (
        .a(save_data[8]),
        .b(float_data[8]),
        .result(float_add_result_8)
    );
    fp32_adder adder9 (
        .a(save_data[9]),
        .b(float_data[9]),
        .result(float_add_result_9)
    );
    fp32_adder adder10 (
        .a(save_data[10]),
        .b(float_data[10]),
        .result(float_add_result_10)
    );
    fp32_adder adder11 (
        .a(save_data[11]),
        .b(float_data[11]),
        .result(float_add_result_11)
    );
    fp32_adder adder12 (
        .a(save_data[12]),
        .b(float_data[12]),
        .result(float_add_result_12)
    );

    always @(posedge clk) begin
        if (cps == 0) begin
            // Module Input Section
                bram_addr <= 0;         // Bram 주소 초기화
                bram_we <= 0;           // Bram 쓰기 비활성화
                bram_ena <= 0;          // Bram 비활성화

            // Module Local Variables
            // lfsr <= 10'b1010101010;
            // lfsr <= 11'b10101010101; // 11비트 초기값
            lfsr <= {lfsr[9:0], lfsr[10] ^ lfsr[7]}; // 11비트 LFSR로 변경 (이전 변경 값을 가져다 씀)
            count <= 0;
            prev_cps <= 0;

            mem_count <= 0;
            mem_control_state <= 0;
        end else begin
            // cps가 변경되었을 경우 재시작
            if (cps != prev_cps) begin
                // Module Input Section
                bram_addr <= 0;         // Bram 주소 초기화
                bram_we <= 0;           // Bram 쓰기 비활성화
                bram_ena <= 1;          // Bram 활성화

                // Module Local Variables
                // lfsr <= 10'b1010101010;
                // lfsr <= 11'b10101010101; // 11비트 초기값
                lfsr <= {lfsr[9:0], lfsr[10] ^ lfsr[7]}; // 11비트 LFSR로 변경 (이전 변경 값을 가져다 씀)

                count <= 0;
                prev_cps <= cps;

                mem_count <= 0;
                mem_gam_count <= 0;     // 감마의 경우 2배
                mem_control_state <= 0;
            end else if (count < cps) begin
                case (mem_control_state)
                    0: begin
                        // 읽기 상태: Bram에서 데이터 읽기
                        // Module Input Section
                        bram_addr <= mem_count * 4; // 주소 설정 [0]
                        bram_we <= 0;               // Bram 쓰기 비활성화
                        bram_ena <= 1;              // Bram 활성화
                        // Module Local Variables
                        mem_count <= mem_count + 1; // 다음 인덱스로 이동
                        mem_control_state <= 1; // 다음 상태로 전환
                    end

                    1: begin
                        // 저장 상태: Bram에서 읽은 데이터 저장
                        bram_addr <= mem_count * 4; // 주소 설정 [1]
                        bram_we <= 0;               // Bram 쓰기 비활성화
                        bram_ena <= 1;              // Bram 활성화

                        // Module Local Variables
                        save_data[mem_count] <= bram_data_out; // 데이터 입력

                        if (mem_count < 13) begin
                            mem_count <= mem_count + 1; // 다음 인덱스로 이동
                        end else begin
                            mem_control_state <= 2; // 다음 상태로 전환
                            mem_count <= 0; // 인덱스 초기화
                        end
                    end

                    2: begin
                        // 계산 상태: 저장된 데이터와 Neutron Pulse Data Table의 데이터 더하기
                        save_data[0] <= float_add_result_0;
                        save_data[1] <= float_add_result_1;
                        save_data[2] <= float_add_result_2;
                        save_data[3] <= float_add_result_3;
                        save_data[4] <= float_add_result_4;
                        save_data[5] <= float_add_result_5;
                        save_data[6] <= float_add_result_6;
                        save_data[7] <= float_add_result_7;
                        save_data[8] <= float_add_result_8;
                        save_data[9] <= float_add_result_9;
                        save_data[10] <= float_add_result_10;
                        save_data[11] <= float_add_result_11;
                        save_data[12] <= float_add_result_12;
                        mem_control_state <= 3; // 다음 상태로 전환
                    end

                    3: begin
                        // 쓰기 상태: 계산된 데이터를 Bram에 쓰기
                        bram_addr <= mem_count * 4; // 주소 설정 [1]
                        bram_we <= 1;               // Bram 쓰기 활성화
                        bram_ena <= 1;              // Bram 활성화
                        // Module Local Variables
                        bram_data_in <= save_data[mem_count]; // 저장된 데이터 쓰기

                        if (mem_count < 13) begin
                            mem_count <= mem_count + 1; // 다음 인덱스로 이동
                        end else begin
                            mem_count <= 0; // 인덱스 초기화
                            mem_control_state <= 4; // 다음 상태로 전환
                        end
                    end

                    4: begin
                        // 완료 상태: 모든 작업 완료 후 초기화
                        bram_we <= 0;               // Bram 쓰기 비활성화
                        bram_ena <= 0;              // Bram 비활성화

                        if (mem_gam_count == 1) begin
                            count <= count + 1;         // CPS 카운트 증가
                            mem_gam_count <= 0;
                        end else begin
                            mem_gam_count <= mem_gam_count + 1;
                        end
                        
                        mem_control_state <= 0;     // 상태 초기화
                    end
                endcase
            end
        end
    end
endmodule


module tb_PulseGenSpeedGam();

    // Inputs
    reg clk;
    reg [31:0] cps;

    // Outputs
    wire [31:0] bram_addr;
    wire [31:0] bram_data_in;
    wire bram_we;
    wire bram_ena;

    wire [31:0] bram_data_out;

    // Instantiate the Unit Under Test (UUT)
    PulseGenSpeedGam uut (
        .clk(clk),
        .cps(cps),
        .bram_addr(bram_addr),
        .bram_data_in(bram_data_in),
        .bram_we(bram_we),
        .bram_ena(bram_ena),
        .bram_data_out(bram_data_out)
    );

    bram pulse_bram_inst (
        .clka(clk),
        .ena(bram_ena),
        .wea(bram_we),
        .addra(bram_addr),
        .dina(bram_data_in),
        .douta(bram_data_out)
    );

    // Clock generation: 10ns period
    always #5 clk = ~clk;

    initial begin
        $dumpfile("Verilog_file/PulseGenSpeed/PulseGenSpeedGam.vcd");
        $dumpvars(0, tb_PulseGenSpeedGam);
        // Initialize inputs
        clk = 0;
        cps = 0;

        // Wait for global reset
        #20;

        // Test 1: cps = 0 → 모듈 초기화 상태 유지
        cps = 0;
        #50;

        // Test 2: cps = 10 → 10개의 pulse 발생
        cps = 1;
        #2000;

        cps = 0;
        #50

        // Test 2: cps = 10 → 10개의 pulse 발생
        cps = 1;
        #2000;

        cps = 0;
        #50

        // // Test 2: cps = 10 → 10개의 pulse 발생
        // cps = 1;
        // #1000;

        // // Test 3: cps = 5 → 다시 시작됨 (변경된 cps 값)
        // cps = 5;
        // #500;

        // // Test 4: cps = 0 → 종료
        // cps = 0;
        // #100;

        $finish;
    end

endmodule

Verilog_file/PulseGenSpeed/PulseGenSpeedGam.vcd
$date
	Mon Aug 04 11:06:53 2025
$end
$version
	Icarus Verilog
$end
$timescale
	1ps
$end
$scope module tb_PulseGenSpeedGam $end
$var wire 1 ! bram_we $end
$var wire 1 " bram_ena $end
$var wire 32 # bram_data_out [31:0] $end
$var wire 32 $ bram_data_in [31:0] $end
$var wire 32 % bram_addr [31:0] $end
$var reg 1 & clk $end
$var reg 32 ' cps [31:0] $end
$scope module pulse_bram_inst $end
$var wire 1 & clka $end
$var wire 1 ! wea $end
$var wire 1 " ena $end
$var wire 32 ( dina [31:0] $end
$var wire 32 ) addra [31:0] $end
$var wire 13 * addr_index [12:0] $end
$var reg 32 + douta [31:0] $end
$var reg 32 , mem1 [31:0] $end
$var reg 32 - mem10 [31:0] $end
$var reg 32 . mem11 [31:0] $end
$var reg 32 / mem2 [31:0] $end
$var reg 32 0 mem3 [31:0] $end
$var reg 32 1 mem4 [31:0] $end
$var reg 32 2 mem5 [31:0] $end
$var reg 32 3 mem6 [31:0] $end
$var reg 32 4 mem7 [31:0] $end
$var reg 32 5 mem8 [31:0] $end
$var reg 32 6 mem9 [31:0] $end
$var integer 32 7 i [31:0] $end
$upscope $end
$scope module uut $end
$var wire 32 8 bram_data_out [31:0] $end
$var wire 1 & clk $end
$var wire 32 9 cps [31:0] $end
$var wire 32 : float_add_result_9 [31:0] $end
$var wire 32 ; float_add_result_8 [31:0] $end
$var wire 32 < float_add_result_7 [31:0] $end
$var wire 32 = float_add_result_6 [31:0] $end
$var wire 32 > float_add_result_5 [31:0] $end
$var wire 32 ? float_add_result_4 [31:0] $end
$var wire 32 @ float_add_result_3 [31:0] $end
$var wire 32 A float_add_result_2 [31:0] $end
$var wire 32 B float_add_result_12 [31:0] $end
$var wire 32 C float_add_result_11 [31:0] $end
$var wire 32 D float_add_result_10 [31:0] $end
$var wire 32 E float_add_result_1 [31:0] $end
$var wire 32 F float_add_result_0 [31:0] $end
$var reg 32 G bram_addr [31:0] $end
$var reg 32 H bram_data_in [31:0] $end
$var reg 1 " bram_ena $end
$var reg 1 ! bram_we $end
$var reg 32 I count [31:0] $end
$var reg 11 J lfsr [10:0] $end
$var reg 4 K mem_control_state [3:0] $end
$var reg 32 L mem_count [31:0] $end
$var reg 2 M mem_gam_count [1:0] $end
$var reg 32 N prev_cps [31:0] $end
$scope module adder0 $end
$var wire 32 O a [31:0] $end
$var wire 32 P b [31:0] $end
$var wire 1 Q sign_b $end
$var wire 1 R sign_a $end
$var wire 32 S result [31:0] $end
$var wire 24 T mant_b [23:0] $end
$var wire 24 U mant_a [23:0] $end
$var wire 8 V exp_b [7:0] $end
$var wire 8 W exp_a [7:0] $end
$var reg 24 X aligned_a [23:0] $end
$var reg 24 Y aligned_b [23:0] $end
$var reg 8 Z exp_diff [7:0] $end
$var reg 8 [ exp_res [7:0] $end
$var reg 23 \ frac_res [22:0] $end
$var reg 25 ] mant_sum [24:0] $end
$var reg 1 ^ sign_res $end
$upscope $end
$scope module adder1 $end
$var wire 32 _ a [31:0] $end
$var wire 32 ` b [31:0] $end
$var wire 1 a sign_b $end
$var wire 1 b sign_a $end
$var wire 32 c result [31:0] $end
$var wire 24 d mant_b [23:0] $end
$var wire 24 e mant_a [23:0] $end
$var wire 8 f exp_b [7:0] $end
$var wire 8 g exp_a [7:0] $end
$var reg 24 h aligned_a [23:0] $end
$var reg 24 i aligned_b [23:0] $end
$var reg 8 j exp_diff [7:0] $end
$var reg 8 k exp_res [7:0] $end
$var reg 23 l frac_res [22:0] $end
$var reg 25 m mant_sum [24:0] $end
$var reg 1 n sign_res $end
$upscope $end
$scope module adder10 $end
$var wire 32 o a [31:0] $end
$var wire 32 p b [31:0] $end
$var wire 1 q sign_b $end
$var wire 1 r sign_a $end
$var wire 32 s result [31:0] $end
$var wire 24 t mant_b [23:0] $end
$var wire 24 u mant_a [23:0] $end
$var wire 8 v exp_b [7:0] $end
$var wire 8 w exp_a [7:0] $end
$var reg 24 x aligned_a [23:0] $end
$var reg 24 y aligned_b [23:0] $end
$var reg 8 z exp_diff [7:0] $end
$var reg 8 { exp_res [7:0] $end
$var reg 23 | frac_res [22:0] $end
$var reg 25 } mant_sum [24:0] $end
$var reg 1 ~ sign_res $end
$upscope $end
$scope module adder11 $end
$var wire 32 !" a [31:0] $end
$var wire 32 "" b [31:0] $end
$var wire 1 #" sign_b $end
$var wire 1 $" sign_a $end
$var wire 32 %" result [31:0] $end
$var wire 24 &" mant_b [23:0] $end
$var wire 24 '" mant_a [23:0] $end
$var wire 8 (" exp_b [7:0] $end
$var wire 8 )" exp_a [7:0] $end
$var reg 24 *" aligned_a [23:0] $end
$var reg 24 +" aligned_b [23:0] $end
$var reg 8 ," exp_diff [7:0] $end
$var reg 8 -" exp_res [7:0] $end
$var reg 23 ." frac_res [22:0] $end
$var reg 25 /" mant_sum [24:0] $end
$var reg 1 0" sign_res $end
$upscope $end
$scope module adder12 $end
$var wire 32 1" a [31:0] $end
$var wire 32 2" b [31:0] $end
$var wire 1 3" sign_b $end
$var wire 1 4" sign_a $end
$var wire 32 5" result [31:0] $end
$var wire 24 6" mant_b [23:0] $end
$var wire 24 7" mant_a [23:0] $end
$var wire 8 8" exp_b [7:0] $end
$var wire 8 9" exp_a [7:0] $end
$var reg 24 :" aligned_a [23:0] $end
$var reg 24 ;" aligned_b [23:0] $end
$var reg 8 <" exp_diff [7:0] $end
$var reg 8 =" exp_res [7:0] $end
$var reg 23 >" frac_res [22:0] $end
$var reg 25 ?" mant_sum [24:0] $end
$var reg 1 @" sign_res $end
$upscope $end
$scope module adder2 $end
$var wire 32 A" a [31:0] $end
$var wire 32 B" b [31:0] $end
$var wire 1 C" sign_b $end
$var wire 1 D" sign_a $end
$var wire 32 E" result [31:0] $end
$var wire 24 F" mant_b [23:0] $end
$var wire 24 G" mant_a [23:0] $end
$var wire 8 H" exp_b [7:0] $end
$var wire 8 I" exp_a [7:0] $end
$var reg 24 J" aligned_a [23:0] $end
$var reg 24 K" aligned_b [23:0] $end
$var reg 8 L" exp_diff [7:0] $end
$var reg 8 M" exp_res [7:0] $end
$var reg 23 N" frac_res [22:0] $end
$var reg 25 O" mant_sum [24:0] $end
$var reg 1 P" sign_res $end
$upscope $end
$scope module adder3 $end
$var wire 32 Q" a [31:0] $end
$var wire 32 R" b [31:0] $end
$var wire 1 S" sign_b $end
$var wire 1 T" sign_a $end
$var wire 32 U" result [31:0] $end
$var wire 24 V" mant_b [23:0] $end
$var wire 24 W" mant_a [23:0] $end
$var wire 8 X" exp_b [7:0] $end
$var wire 8 Y" exp_a [7:0] $end
$var reg 24 Z" aligned_a [23:0] $end
$var reg 24 [" aligned_b [23:0] $end
$var reg 8 \" exp_diff [7:0] $end
$var reg 8 ]" exp_res [7:0] $end
$var reg 23 ^" frac_res [22:0] $end
$var reg 25 _" mant_sum [24:0] $end
$var reg 1 `" sign_res $end
$upscope $end
$scope module adder4 $end
$var wire 32 a" a [31:0] $end
$var wire 32 b" b [31:0] $end
$var wire 1 c" sign_b $end
$var wire 1 d" sign_a $end
$var wire 32 e" result [31:0] $end
$var wire 24 f" mant_b [23:0] $end
$var wire 24 g" mant_a [23:0] $end
$var wire 8 h" exp_b [7:0] $end
$var wire 8 i" exp_a [7:0] $end
$var reg 24 j" aligned_a [23:0] $end
$var reg 24 k" aligned_b [23:0] $end
$var reg 8 l" exp_diff [7:0] $end
$var reg 8 m" exp_res [7:0] $end
$var reg 23 n" frac_res [22:0] $end
$var reg 25 o" mant_sum [24:0] $end
$var reg 1 p" sign_res $end
$upscope $end
$scope module adder5 $end
$var wire 32 q" a [31:0] $end
$var wire 32 r" b [31:0] $end
$var wire 1 s" sign_b $end
$var wire 1 t" sign_a $end
$var wire 32 u" result [31:0] $end
$var wire 24 v" mant_b [23:0] $end
$var wire 24 w" mant_a [23:0] $end
$var wire 8 x" exp_b [7:0] $end
$var wire 8 y" exp_a [7:0] $end
$var reg 24 z" aligned_a [23:0] $end
$var reg 24 {" aligned_b [23:0] $end
$var reg 8 |" exp_diff [7:0] $end
$var reg 8 }" exp_res [7:0] $end
$var reg 23 ~" frac_res [22:0] $end
$var reg 25 !# mant_sum [24:0] $end
$var reg 1 "# sign_res $end
$upscope $end
$scope module adder6 $end
$var wire 32 ## a [31:0] $end
$var wire 32 $# b [31:0] $end
$var wire 1 %# sign_b $end
$var wire 1 &# sign_a $end
$var wire 32 '# result [31:0] $end
$var wire 24 (# mant_b [23:0] $end
$var wire 24 )# mant_a [23:0] $end
$var wire 8 *# exp_b [7:0] $end
$var wire 8 +# exp_a [7:0] $end
$var reg 24 ,# aligned_a [23:0] $end
$var reg 24 -# aligned_b [23:0] $end
$var reg 8 .# exp_diff [7:0] $end
$var reg 8 /# exp_res [7:0] $end
$var reg 23 0# frac_res [22:0] $end
$var reg 25 1# mant_sum [24:0] $end
$var reg 1 2# sign_res $end
$upscope $end
$scope module adder7 $end
$var wire 32 3# a [31:0] $end
$var wire 32 4# b [31:0] $end
$var wire 1 5# sign_b $end
$var wire 1 6# sign_a $end
$var wire 32 7# result [31:0] $end
$var wire 24 8# mant_b [23:0] $end
$var wire 24 9# mant_a [23:0] $end
$var wire 8 :# exp_b [7:0] $end
$var wire 8 ;# exp_a [7:0] $end
$var reg 24 <# aligned_a [23:0] $end
$var reg 24 =# aligned_b [23:0] $end
$var reg 8 ># exp_diff [7:0] $end
$var reg 8 ?# exp_res [7:0] $end
$var reg 23 @# frac_res [22:0] $end
$var reg 25 A# mant_sum [24:0] $end
$var reg 1 B# sign_res $end
$upscope $end
$scope module adder8 $end
$var wire 32 C# a [31:0] $end
$var wire 32 D# b [31:0] $end
$var wire 1 E# sign_b $end
$var wire 1 F# sign_a $end
$var wire 32 G# result [31:0] $end
$var wire 24 H# mant_b [23:0] $end
$var wire 24 I# mant_a [23:0] $end
$var wire 8 J# exp_b [7:0] $end
$var wire 8 K# exp_a [7:0] $end
$var reg 24 L# aligned_a [23:0] $end
$var reg 24 M# aligned_b [23:0] $end
$var reg 8 N# exp_diff [7:0] $end
$var reg 8 O# exp_res [7:0] $end
$var reg 23 P# frac_res [22:0] $end
$var reg 25 Q# mant_sum [24:0] $end
$var reg 1 R# sign_res $end
$upscope $end
$scope module adder9 $end
$var wire 32 S# a [31:0] $end
$var wire 32 T# b [31:0] $end
$var wire 1 U# sign_b $end
$var wire 1 V# sign_a $end
$var wire 32 W# result [31:0] $end
$var wire 24 X# mant_b [23:0] $end
$var wire 24 Y# mant_a [23:0] $end
$var wire 8 Z# exp_b [7:0] $end
$var wire 8 [# exp_a [7:0] $end
$var reg 24 \# aligned_a [23:0] $end
$var reg 24 ]# aligned_b [23:0] $end
$var reg 8 ^# exp_diff [7:0] $end
$var reg 8 _# exp_res [7:0] $end
$var reg 23 `# frac_res [22:0] $end
$var reg 25 a# mant_sum [24:0] $end
$var reg 1 b# sign_res $end
$upscope $end
$upscope $end
$upscope $end
$enddefinitions $end
$comment Show the parameter values. $end
$dumpall
$end
#0
$dumpvars
0b#
b100111010100100101010010 a#
b111010100100101010010 `#
b1110100 _#
b1110100 ^#
b100111010100100101010010 ]#
b0 \#
b0 [#
b1110100 Z#
b0 Y#
b100111010100100101010010 X#
b111010000111010100100101010010 W#
0V#
0U#
b111010000111010100100101010010 T#
b0 S#
0R#
b101010100110010011000011 Q#
b1010100110010011000011 P#
b1110101 O#
b1110101 N#
b101010100110010011000011 M#
b0 L#
b0 K#
b1110101 J#
b0 I#
b101010100110010011000011 H#
b111010101010100110010011000011 G#
0F#
0E#
b111010101010100110010011000011 D#
b0 C#
0B#
b101111100000110111101101 A#
b1111100000110111101101 @#
b1110110 ?#
b1110110 >#
b101111100000110111101101 =#
b0 <#
b0 ;#
b1110110 :#
b0 9#
b101111100000110111101101 8#
b111011001111100000110111101101 7#
06#
05#
b111011001111100000110111101101 4#
b0 3#
02#
b110011100111000000111011 1#
b10011100111000000111011 0#
b1110111 /#
b1110111 .#
b110011100111000000111011 -#
b0 ,#
b0 +#
b1110111 *#
b0 )#
b110011100111000000111011 (#
b111011110011100111000000111011 '#
0&#
0%#
b111011110011100111000000111011 $#
b0 ##
0"#
b110111101101001010001001 !#
b10111101101001010001001 ~"
b1111000 }"
b1111000 |"
b110111101101001010001001 {"
b0 z"
b0 y"
b1111000 x"
b0 w"
b110111101101001010001001 v"
b111100010111101101001010001001 u"
0t"
0s"
b111100010111101101001010001001 r"
b0 q"
0p"
b111100011010100111111100 o"
b11100011010100111111100 n"
b1111001 m"
b1111001 l"
b111100011010100111111100 k"
b0 j"
b0 i"
b1111001 h"
b0 g"
b111100011010100111111100 f"
b111100111100011010100111111100 e"
0d"
0c"
b111100111100011010100111111100 b"
b0 a"
0`"
b100000110001001001101111 _"
b110001001001101111 ^"
b1111011 ]"
b1111011 \"
b100000110001001001101111 ["
b0 Z"
b0 Y"
b1111011 X"
b0 W"
b100000110001001001101111 V"
b111101100000110001001001101111 U"
0T"
0S"
b111101100000110001001001101111 R"
b0 Q"
0P"
b100011100011101111001101 O"
b11100011101111001101 N"
b1111100 M"
b1111100 L"
b100011100011101111001101 K"
b0 J"
b0 I"
b1111100 H"
b0 G"
b100011100011101111001101 F"
b111110000011100011101111001101 E"
0D"
0C"
b111110000011100011101111001101 B"
b0 A"
0@"
b110100011011011100010111 ?"
b10100011011011100010111 >"
b1110001 ="
b1110001 <"
b110100011011011100010111 ;"
b0 :"
b0 9"
b1110001 8"
b0 7"
b110100011011011100010111 6"
b111000110100011011011100010111 5"
04"
03"
b111000110100011011011100010111 2"
b0 1"
00"
b110100011011011100010111 /"
b10100011011011100010111 ."
b1110001 -"
b1110001 ,"
b110100011011011100010111 +"
b0 *"
b0 )"
b1110001 ("
b0 '"
b110100011011011100010111 &"
b111000110100011011011100010111 %"
0$"
0#"
b111000110100011011011100010111 ""
b0 !"
0~
b100111010100100101010010 }
b111010100100101010010 |
b1110011 {
b1110011 z
b100111010100100101010010 y
b0 x
b0 w
b1110011 v
b0 u
b100111010100100101010010 t
b111001100111010100100101010010 s
0r
0q
b111001100111010100100101010010 p
b0 o
0n
b100110010110010100101100 m
b110010110010100101100 l
b1111101 k
b1111101 j
b100110010110010100101100 i
b0 h
b0 g
b1111101 f
b0 e
b100110010110010100101100 d
b111110100110010110010100101100 c
0b
0a
b111110100110010110010100101100 `
b0 _
0^
b111111000101000001001000 ]
b11111000101000001001000 \
b1111010 [
b1111010 Z
b111111000101000001001000 Y
b0 X
b0 W
b1111010 V
b0 U
b111111000101000001001000 T
b111101011111000101000001001000 S
0R
0Q
b111101011111000101000001001000 P
b0 O
b0 N
b0 M
b0 L
b0 K
b10101010101 J
b0 I
bx H
bx G
b111101011111000101000001001000 F
b111110100110010110010100101100 E
b111001100111010100100101010010 D
b111000110100011011011100010111 C
b111000110100011011011100010111 B
b111110000011100011101111001101 A
b111101100000110001001001101111 @
b111100111100011010100111111100 ?
b111100010111101101001010001001 >
b111011110011100111000000111011 =
b111011001111100000110111101101 <
b111010101010100110010011000011 ;
b111010000111010100100101010010 :
b0 9
bx 8
b1111101000000 7
bx 6
bx 5
bx 4
bx 3
bx 2
bx 1
bx 0
bx /
bx .
bx -
bx ,
bx +
bx *
bx )
bx (
b0 '
0&
bx %
bx $
bx #
x"
x!
$end
#5000
b0 *
b1010101011 J
0"
0!
b0 %
b0 )
b0 G
1&
#10000
0&
#15000
b10101010111 J
1&
#20000
0&
#25000
b1010101111 J
1&
#30000
0&
#35000
b10101011111 J
1&
#40000
0&
#45000
b1010111111 J
1&
#50000
0&
#55000
b10101111111 J
1&
#60000
0&
#65000
b1011111111 J
1&
#70000
0&
b1 '
b1 9
#75000
b1 N
b10111111111 J
1"
1&
#80000
0&
#85000
b1 K
b1 L
b0 .
b0 -
b0 6
b0 5
b0 4
b0 3
b0 2
b0 1
b0 0
b0 /
b0 ,
b0 #
b0 +
b0 8
1&
#90000
0&
#95000
b100 *
b10 L
b100 %
b100 )
b100 G
1&
#100000
0&
#105000
b1000 *
b11 L
b1000 %
b1000 )
b1000 G
1&
#110000
0&
#115000
b1100 *
b100 L
b1100 %
b1100 )
b1100 G
1&
#120000
0&
#125000
b10000 *
b101 L
b10000 %
b10000 )
b10000 G
1&
#130000
0&
#135000
b10100 *
b110 L
b10100 %
b10100 )
b10100 G
1&
#140000
0&
#145000
b11000 *
b111 L
b11000 %
b11000 )
b11000 G
1&
#150000
0&
#155000
b11100 *
b1000 L
b11100 %
b11100 )
b11100 G
1&
#160000
0&
#165000
b100000 *
b1001 L
b100000 %
b100000 )
b100000 G
1&
#170000
0&
#175000
b100100 *
b1010 L
b100100 %
b100100 )
b100100 G
1&
#180000
0&
#185000
b101000 *
b1011 L
b101000 %
b101000 )
b101000 G
1&
#190000
0&
#195000
b101100 *
b1100 L
b101100 %
b101100 )
b101100 G
1&
#200000
0&
#205000
b110000 *
b1101 L
b110000 %
b110000 )
b110000 G
1&
#210000
0&
#215000
b110100 *
b0 L
b10 K
b110100 %
b110100 )
b110100 G
1&
#220000
0&
